Workbook

Sheet DADOS_RM_SITUACAO
A1: CODCLIENTE | B1: DESCRICAO
A2: A | B2: Ativo
A3: C | B3: Contrato de Trabalho Suspenso
A4: D | B4: Demitido
A5: E | B5: Licença Mater.
A6: F | B6: Férias
A7: G | B7: Recesso Remunerado de Estagio
A8: I | B8: Apos. por Incapacidade Permanente
A9: K | B9: Cessão / Requisição
A10: L | B10: Licença s/venc
A11: M | B11: Serv.Militar
A12: N | B12: Mandato Sindical Ônus do Empregador
... A24: Z | B24: Admissão prox.mês

Sheet DADOS_RM_EVENTOS_original
A1: CODIGO | B1: DESCRICAO | C1: TIPOEVENTO | D1: VALHORDIAREF | E1: NAT_ESOCIAL | F1: CONFERE COD | H1: CONFERE DESCR
A2: 0001 | B2: Salario Base em Horas | C2: PROVENTO | D2: HORA | E2: 1000-Salario, vencimento, soldo | F2: 0001 | G2: =IF(F2=A2,1,FALSE) -> 1 | H2: SALARIO BASE EM HORAS | I2: =IF(H2=B2,1,FALSE) -> 1
A3: 0002 | B3: Salario Base em Dias | C3: PROVENTO | D3: DIA | E3: 1000-Salario, vencimento, soldo | F3: 0002 | G3: =IF(F3=A3,1,FALSE) -> 1 | H3: SALARIO BASE EM DIAS | I3: =IF(H3=B3,1,FALSE) -> 1
A4: 0003 | B4: Desc. INSS Segurado | C4: DESCONTO | D4: VALOR | E4: 9201-Contribuicao Previdenciaria | F4: 0003 | G4: =IF(F4=A4,1,FALSE) -> 1 | H4: DESC. INSS SEGURADO | I4: =IF(H4=B4,1,FALSE) -> 1
A5: 0004 | B5: Desc. IRRF na Fonte | C5: DESCONTO | D5: VALOR | E5: 9203-Imposto de renda retido na fonte | F5: 0004 | G5: =IF(F5=A5,1,FALSE) -> 1 | H5: DESC. IRRF NA FONTE | I5: =IF(H5=B5,1,FALSE) -> 1
A6: 0005 | B6: Cota de Salario Familia | C6: PROVENTO | D6: VALOR | E6: 1409-Salario familia | F6: 0005 | G6: =IF(F6=A6,1,FALSE) -> 1 | H6: COTA DE SALARIO FAMILIA | I6: =IF(H6=B6,1,FALSE) -> 1
A7: 0006 | B7: Desc. Vale Transporte | C7: DESCONTO | D7: VALOR | E7: 9216-Desconto de valetransporte | F7: 0006 | G7: =IF(F7=A7,1,FALSE) -> 1 | H7: DESC. VALE TRANSPORTE | I7: =IF(H7=B7,1,FALSE) -> 1
A8: 0007 | B8: Adicional de Penosidade | C8: PROVENTO | D8: VALOR | E8: 1214-Adicional de penosidade | F8: 0007 | G8: =IF(F8=A8,1,FALSE) -> 1 | H8: ADICIONAL DE PENOSIDADE | I8: =IF(H8=B8,1,FALSE) -> 1
A9: 0008 | B9: Desc. Faltas (em Dias) | C9: DESCONTO | D9: DIA | E9: 9209-Faltas ou atrasos | F9: 0008 | G9: =IF(F9=A9,1,FALSE) -> 1 | H9: DESC. FALTAS (EM DIAS) | I9: =IF(H9=B9,1,FALSE) -> 1
A10: 0009 | B10: 1ª Parcela 13º Salario | C10: PROVENTO | D10: VALOR | E10: 5504-13º salario ¿ Adiantamento | F10: 0009 | G10: =IF(F10=A10,1,FALSE) -> 1 | H10: 1ª PARCELA 13º SALARIO | I10: =IF(H10=B10,1,FALSE) -> 1
A11: 0010 | B11: Reflexo Sobre Escala | C11: PROVENTO | D11: VALOR | E11: 1012-Descanso semanal remunerado - DSR e feriado | F11: 0010 | G11: =IF(F11=A11,1,FALSE) -> 1 | H11: REFLEXO SOBRE ESCALA | I11: =IF(H11=B11,1,FALSE) -> 1
A12: 0011 | B12: Desc. INSS 13º Salario | C12: DESCONTO | D12: VALOR | E12: 9201-Contribuicao Previdenciaria | F12: 0011 | G12: =IF(F12=A12,1,FALSE) -> 1 | H12: DESC. INSS 13º SALARIO | I12: =IF(H12=B12,1,FALSE) -> 1
A13: 0012 | B13: Desc. Contribuicao Sindical Compulsoria | C13: DESCONTO | D13: DIA | E13: 9230-Contribuicao sindical laboral | F13: 0012 | G13: =IF(F13=A13,1,FALSE) -> 1 | H13: DESC. CONTRIBUICAO SINDICAL COMPULSORIA | I13: =IF(H13=B13,1,FALSE) -> 1
... A24: 0023 | B24: Adic de Periculosidade | C24: PROVENTO | D24: VALOR | E24: 1203-Adicional de periculosidade | F24: 0023 | G24: =IF(F24=A24,1,FALSE) -> 1 | H24: ADIC DE PERICULOSIDADE | I24: =IF(H24=B24,1,FALSE) -> 1
A25: 0024 | B25: Ferias Indenizadas Rescisao | C25: PROVENTO | D25: VALOR | E25: 6007-Ferias vencidas na rescisao | F25: 0024 | G25: =IF(F25=A25,1,FALSE) -> 1 | H25: FERIAS VENCIDAS | I25: 1
A26: 0025 | B26: Ferias Proporcionais | C26: PROVENTO | D26: VALOR | E26: 6006-Ferias proporcionais | F26: 0025 | G26: =IF(F26=A26,1,FALSE) -> 1 | H26: FERIAS PROPORCIONAIS | I26: =IF(H26=B26,1,FALSE) -> 1
A27: 0026 | B27: GRRF - FGTS Quitacao | C27: BASE | D27: VALOR | E27: 9989-Outros valores informativos | F27: 0026 | G27: =IF(F27=A27,1,FALSE) -> 1 | H27: GRRF - FGTS QUITACAO | I27: =IF(H27=B27,1,FALSE) -> 1
A28: 0027 | B28: Base - FGTS Mes anterior | C28: BASE | D28: VALOR | E28: 9989-Outros valores informativos | F28: 0027 | G28: =IF(F28=A28,1,FALSE) -> 1 | H28: BASE - FGTS MES ANTERIOR | I28: =IF(H28=B28,1,FALSE) -> 1
A29: 0028 | B29: GRRF - FGTS Artigo 22 | C29: BASE | D29: VALOR | E29: 9989-Outros valores informativos | F29: 0028 | G29: =IF(F29=A29,1,FALSE) -> 1 | H29: GRRF - FGTS ARTIGO 22 | I29: =IF(H29=B29,1,FALSE) -> 1
A30: 0029 | B30: Base - INSS Outro Emprego | C30: BASE | D30: VALOR | E30: 9989-Outros valores informativos | F30: 0029 | G30: =IF(F30=A30,1,FALSE) -> 1 | H30: BASE - INSS OUTRO EMPREGO | I30: =IF(H30=B30,1,FALSE) -> 1
A31: 0030 | B31: Desc. IRRF Ferias | C31: DESCONTO | D31: VALOR | E31: 9203-Imposto de renda retido na fonte | F31: 0030 | G31: =IF(F31=A31,1,FALSE) -> 1 | H31: DESC. IRRF FERIAS | I31: =IF(H31=B31,1,FALSE) -> 1
A32: 0031 | B32: GRRF - FGTS 13º rescisao | C32: BASE | D32: VALOR | E32: 9989-Outros valores informativos | F32: 0031 | G32: =IF(F32=A32,1,FALSE) -> 1 | H32: GRRF - FGTS 13º RESCISAO | I32: =IF(H32=B32,1,FALSE) -> 1
A33: 0032 | B33: Total Entregue Vale Transporte | C33: BASE | D33: VALOR | E33: 9989-Outros valores informativos | F33: 0032 | G33: =IF(F33=A33,1,FALSE) -> 1 | H33: TOTAL ENTREGUE VALE TRANSPORTE | I33: =IF(H33=B33,1,FALSE) -> 1
A34: 0033 | B34: Base - Saldo FGTS no Banco | C34: BASE | D34: VALOR | E34: 9989-Outros valores informativos | F34: 0033 | G34: =IF(F34=A34,1,FALSE) -> 1 | H34: BASE - SALDO FGTS NO BANCO | I34: =IF(H34=B34,1,FALSE) -> 1
A35: 0034 | B35: ( + ) Adiantamento Salarial (P) | C35: PROVENTO | D35: VALOR | E35: 5501-Adiantamento de salario | F35: 0034 | G35: =IF(F35=A35,1,FALSE) -> 1 | H35: ( + ) ADIANTAMENTO SALARIAL (P) | I35: =IF(H35=B35,1,FALSE) -> 1
A36: 0035 | B36: Desc. Adiantamento 13º salario | C36: DESCONTO | D36: VALOR | E36: 9214-13° salario - desconto de adiantamento | F36: 0035 | G36: =IF(F36=A36,1,FALSE) -> 1 | H36: DESC. ADIANTAMENTO 13º SALARIO | I36: =IF(H36=B36,1,FALSE) -> 1
A37: 0036 | B37: Desc. de uma parcela | C37: DESCONTO | D37: VALOR | E37: 9254-Emprestimos consignados - desconto | F37: 0036 | G37: =IF(F37=A37,1,FALSE) -> 1 | H37: DESC. DE UMA PARCELA | I37: =IF(H37=B37,1,FALSE) -> 1
A38: 0037 | B38: Dif. Salarial | C38: PROVENTO | D38: VALOR | E38: 1099-Outras verbas salariais | F38: 0037 | G38: =IF(F38=A38,1,FALSE) -> 1 | H38: DIF. SALARIAL | I38: =IF(H38=B38,1,FALSE) -> 1
A39: 0038 | B39: Dias de Ferias (Recibo) | C39: PROVENTO | D39: VALOR | E39: 1016-Ferias | F39: 0038 | G39: =IF(F39=A39,1,FALSE) -> 1 | H39: REMUNERACAO DE FERIAS (RECIBO) | I39: 1
A40: 0039 | B40: Abono de Ferias | C40: PROVENTO | D40: VALOR | E40: 1023-Ferias - abono pecuniario | F40: 0039 | G40: =IF(F40=A40,1,FALSE) -> 1 | H40: ABONO DE FERIAS | I40: =IF(H40=B40,1,FALSE) -> 1
A41: 0040 | B41: 1/3 de Ferias (Recibo) | C41: PROVENTO | D41: VALOR | E41: 1016-Ferias | F41: 0040 | G41: =IF(F41=A41,1,FALSE) -> 1 | H41: 1/3 DE FERIAS (RECIBO) | I41: =IF(H41=B41,1,FALSE) -> 1
A42: 0041 | B42: Ferias no Mes | C42: PROVENTO | D42: VALOR | E42: 1016-Ferias | F42: 0041 | G42: =IF(F42=A42,1,FALSE) -> 1 | H42: FERIAS NO MES | I42: =IF(H42=B42,1,FALSE) -> 1
A43: 0042 | B43: Ferias no Proximo Mes | C43: PROVENTO | D43: VALOR | E43: 1016-Ferias | F43: 0042 | G43: =IF(F43=A43,1,FALSE) -> 1 | H43: FERIAS NO PROXIMO MES | I43: =IF(H43=B43,1,FALSE) -> 1
A44: 0043 | B44: Desc. Adto Liquido de Ferias | C44: DESCONTO | D44: VALOR | E44: 9200-Desconto de Adiantamentos | F44: 0043 | G44: =IF(F44=A44,1,FALSE) -> 1 | H44: DESC. ADTO LIQUIDO DE FERIAS | I44: =IF(H44=B44,1,FALSE) -> 1
A45: 0044 | B45: Base - Ferias Pagas no Mes Anterior | C45: BASE | D45: VALOR | E45: 1016-Ferias | F45: 0044 | G45: =IF(F45=A45,1,FALSE) -> 1 | H45: BASE - FERIAS PAGAS NO MES ANTERIOR | I45: =IF(H45=B45,1,FALSE) -> 1
A46: 0045 | B46: Dif. Ferias Pagas no Mes | C46: PROVENTO | D46: VALOR | E46: 1016-Ferias | F46: 0045 | G46: =IF(F46=A46,1,FALSE) -> 1 | H46: DIF. FERIAS PAGAS NO MES | I46: =IF(H46=B46,1,FALSE) -> 1
A47: 0046 | B47: Honorarios a Conselheiros | C47: PROVENTO | D47: VALOR | E47: 3509-Honorarios a conselheiros | F47: 0046 | G47: =IF(F47=A47,1,FALSE) -> 1 | H47: HONORARIOS A CONSELHEIROS | I47: =IF(H47=B47,1,FALSE) -> 1
A48: 0047 | B48: Desc. 2a via PASSCARD | C48: DESCONTO | D48: VALOR | E48: 9299-Outros descontos | F48: 0047 | G48: =IF(F48=A48,1,FALSE) -> 1 | H48: DESC. 2A VIA PASSCARD | I48: =IF(H48=B48,1,FALSE) -> 1
A49: 0048 | B49: 13º Salario Rescisao | C49: PROVENTO | D49: VALOR | E49: 6002-13º salario - proporcional na rescisao | F49: 0048 | G49: =IF(F49=A49,1,FALSE) -> 1 | H49: 13º SALARIO RESCISAO | I49: =IF(H49=B49,1,FALSE) -> 1
A50: 0049 | B50: Desc. IRRF s/13º Salario | C50: DESCONTO | D50: VALOR | E50: 9203-Imposto de renda retido na fonte | F50: 0049 | G50: =IF(F50=A50,1,FALSE) -> 1 | H50: DESC. IRRF S/13º SALARIO | I50: =IF(H50=B50,1,FALSE) -> 1
A51: 0050 | B51: Salario Hora Mes Anterior | C51: PROVENTO | D51: REFERENCIA | E51: 1000-Salario, vencimento, soldo | F51: 0050 | G51: =IF(F51=A51,1,FALSE) -> 1 | H51: SALARIO HORA MES ANTERIOR | I51: =IF(H51=B51,1,FALSE) -> 1
... A70: 0069 | B70: Remuneracao Variavel | C70: PROVENTO | D70: VALOR | E70: 1099-Outras verbas salariais | F70: 0069 | G70: =IF(F70=A70,1,FALSE) -> 1 | H70: REMUNERACAO VARIAVEL | I70: =IF(H70=B70,1,FALSE) -> 1
A71: 0070 | B71: Desc. DSR Perdido | C71: DESCONTO | D71: DIA | E71: 9210-DSR s/faltas e atrasos | F71: 0070 | G71: =IF(F71=A71,1,FALSE) -> 1 | H71: DESC. DSR PERDIDO H | I71: 1
A72: 0071 | B72: 13º Salario Indenizado | C72: PROVENTO | D72: VALOR | E72: 6001-13º salario - relativo ao aviso previo indenizado | F72: 0071 | G72: =IF(F72=A72,1,FALSE) -> 1 | H72: 13º SALARIO INDENIZADO | I72: =IF(H72=B72,1,FALSE) -> 1
A73: 0072 | B73: Base de Calculo INSS Outro Emprego | C73: BASE | D73: VALOR | E73: 9989-Outros valores informativos | F73: 0072 | G73: =IF(F73=A73,1,FALSE) -> 1 | H73: BASE DE CALCULO INSS OUTRO EMPREGO | I73: =IF(H73=B73,1,FALSE) -> 1
A74: 0073 | B74: Base - FGTS Depositado na rescisao | C74: BASE | D74: VALOR | E74: 9989-Outros valores informativos | F74: 0073 | G74: =IF(F74=A74,1,FALSE) -> 1 | H74: BASE - FGTS DEPOSITADO NA RESCISAO | I74: =IF(H74=B74,1,FALSE) -> 1
A75: 0074 | B75: INSS Ferias Aliquota Normal | C75: BASE | D75: VALOR | E75: 9989-Outros valores informativos | F75: 0074 | G75: =IF(F75=A75,1,FALSE) -> 1 | H75: INSS FERIAS ALIQUOTA NORMAL | I75: =IF(H75=B75,1,FALSE) -> 1
A76: 0075 | B76: Devol. Desc. Pl Saude UNIMED Dep | C76: PROVENTO | D76: VALOR | E76: 1405-Assistencia medica | F76: 0075 | G76: =IF(F76=A76,1,FALSE) -> 1 | H76: DEVOL. DESC. PL SAUDE UNIMED DEP | I76: =IF(H76=B76,1,FALSE) -> 1
A77: 0076 | B77: 1/3 Ferias no Mes | C77: PROVENTO | D77: VALOR | E77: 1016-Ferias | F77: 0076 | G77: =IF(F77=A77,1,FALSE) -> 1 | H77: 1/3 FERIAS NO MES | I77: =IF(H77=B77,1,FALSE) -> 1
A78: 0077 | B78: 1/3 Ferias no Proximo Mes | C78: PROVENTO | D78: VALOR | E78: 1016-Ferias | F78: 0077 | G78: =IF(F78=A78,1,FALSE) -> 1 | H78: 1/3 FERIAS NO PROXIMO MES | I78: =IF(H78=B78,1,FALSE) -> 1
A79: 0078 | B79: Base 1/3 Ferias Pagas Mes Anterior | C79: BASE | D79: VALOR | E79: 1016-Ferias | F79: 0078 | G79: =IF(F79=A79,1,FALSE) -> 1 | H79: BASE 1/3 FERIAS PAGAS MES ANTERIOR | I79: =IF(H79=B79,1,FALSE) -> 1
A80: 0079 | B80: Dif. 1/3 Ferias Mes | C80: PROVENTO | D80: VALOR | E80: 1016-Ferias | F80: 0079 | G80: =IF(F80=A80,1,FALSE) -> 1 | H80: DIF. 1/3 FERIAS MES | I80: =IF(H80=B80,1,FALSE) -> 1
A81: 0080 | B81: Dif. Ferias Proximo Mes | C81: PROVENTO | D81: VALOR | E81: 1016-Ferias | F81: 0080 | G81: =IF(F81=A81,1,FALSE) -> 1 | H81: DIF. FERIAS PROXIMO MES | I81: =IF(H81=B81,1,FALSE) -> 1
A82: 0081 | B82: Dif. 1/3 Ferias Proximo Mes | C82: PROVENTO | D82: VALOR | E82: 1016-Ferias | F82: 0081 | G82: =IF(F82=A82,1,FALSE) -> 1 | H82: DIF. 1/3 FERIAS PROXIMO MES | I82: =IF(H82=B82,1,FALSE) -> 1
A83: 0082 | B83: Horas Normais em Rescisao | C83: PROVENTO | D83: HORA | E83: 6000-Saldo de salarios na rescisao contratual | F83: 0082 | G83: =IF(F83=A83,1,FALSE) -> 1 | H83: HORAS NORMAIS EM RESCISAO | I83: =IF(H83=B83,1,FALSE) -> 1
A84: 0083 | B84: Dias Trabalhados em Rescisao | C84: PROVENTO | D84: DIA | E84: 6000-Saldo de salarios na rescisao contratual | F84: 0083 | G84: =IF(F84=A84,1,FALSE) -> 1 | H84: DIAS TRABALHADOS EM RESCISAO | I84: =IF(H84=B84,1,FALSE) -> 1
A85: 0084 | B85: Comissao Commis | C85: PROVENTO | D85: VALOR | E85: 1207-Comissoes, porcentagens, producao | F85: 0084 | G85: =IF(F85=A85,1,FALSE) -> 1 | H85: SALARIO COMISSAO | I85: 1
A86: 0085 | B86: Gratificacao de Ferias | C86: PROVENTO | D86: VALOR | E86: 1016-Ferias | F86: 0085 | G86: =IF(F86=A86,1,FALSE) -> 1 | H86: GRATIFICACAO DE FERIAS | I86: =IF(H86=B86,1,FALSE) -> 1
A87: 0086 | B87: Media Hora Extra ferias | C87: PROVENTO | D87: VALOR | E87: 1016-Ferias | F87: 0086 | G87: =IF(F87=A87,1,FALSE) -> 1 | H87: MEDIA HORA EXTRA FERIAS | I87: =IF(H87=B87,1,FALSE) -> 1
A88: 0087 | B88: Media Comissao Ferias | C88: PROVENTO | D88: VALOR | E88: 1016-Ferias | F88: 0087 | G88: =IF(F88=A88,1,FALSE) -> 1 | H88: MEDIA COMISSAO FERIAS | I88: =IF(H88=B88,1,FALSE) -> 1
A89: 0088 | B89: Media Hora Extra 13º rescisao | C89: PROVENTO | D89: VALOR | E89: 6002-13º salario - proporcional na rescisao | F89: 0088 | G89: =IF(F89=A89,1,FALSE) -> 1 | H89: MEDIA HORA EXTRA 13º RESCISAO | I89: =IF(H89=B89,1,FALSE) -> 1
A90: 0089 | B90: Media Comissao 13º Rescisao | C90: PROVENTO | D90: VALOR | E90: 6002-13º salario - proporcional na rescisao | F90: 0089 | G90: =IF(F90=A90,1,FALSE) -> 1 | H90: MEDIA COMISSAO 13º RESCISAO | I90: =IF(H90=B90,1,FALSE) -> 1
A91: 0090 | B91: Media Hora Extra Aviso Previo | C91: PROVENTO | D91: VALOR | E91: 6003-Indenizacao compensatoria do aviso-previo | F91: 0090 | G91: =IF(F91=A91,1,FALSE) -> 1 | H91: MEDIA HORA EXTRA AVISO PREVIO | I91: =IF(H91=B91,1,FALSE) -> 1
A92: 0091 | B92: Media Comissao Aviso Previo | C92: PROVENTO | D92: VALOR | E92: 6003-Indenizacao compensatoria do aviso-previo | F92: 0091 | G92: =IF(F92=A92,1,FALSE) -> 1 | H92: MEDIA COMISSAO AVISO PREVIO | I92: =IF(H92=B92,1,FALSE) -> 1
A93: 0092 | B93: Desc. Vale Alimentacao | C93: DESCONTO | D93: VALOR | E93: - | F93: 0092 | G93: =IF(F93=A93,1,FALSE) -> 1 | H93: DESC. VALE ALIMENTACAO | I93: =IF(H93=B93,1,FALSE) -> 1
A94: 0093 | B94: Estagiario - Dias de Bolsa s/Rescisao | C94: PROVENTO | D94: DIA | E94: 1350-Bolsa de estudo - estagiario | F94: 0093 | G94: =IF(F94=A94,1,FALSE) -> 1 | H94: ESTAGIARIO - DIAS DE BOLSA S/RESCISAO | I94: =IF(H94=B94,1,FALSE) -> 1
A95: 0094 | B95: Dif. Gratificacao por Funcao | C95: PROVENTO | D95: VALOR | E95: 1201-Adicional de funcao / cargo confianca | F95: 0094 | G95: =IF(F95=A95,1,FALSE) -> 1 | H95: DIF. GRATIFICACAO POR FUNCAO | I95: =IF(H95=B95,1,FALSE) -> 1
A96: 0095 | B96: Devol. Desc. Pl Odontologico Uniodonto | C96: PROVENTO | D96: VALOR | E96: 1405-Assistencia medica | F96: 0095 | G96: =IF(F96=A96,1,FALSE) -> 1 | H96: DEVOL. DESC. PL ODONTOLOGICO UNIODONTO | I96: =IF(H96=B96,1,FALSE) -> 1
A97: 0096 | B97: Desc. Vale Refeicao | C97: DESCONTO | D97: REFERENCIA | E97: 9242-Alimentacao em ticket ou cartao, nao vinculada ao PAT - Desconto | F97: 0096 | G97: =IF(F97=A97,1,FALSE) -> 1 | H97: DESC. VALE REFEICAO | I97: =IF(H97=B97,1,FALSE) -> 1
... A121: 0120 | B121: Desc. Outros Eventos Pagos Rescisao | C121: DESCONTO | D121: VALOR | E121: 9299-Outros descontos | F121: 0120 | G121: =IF(F121=A121,1,FALSE) -> 1 | H121: DESC. OUTROS EVENTOS PAGOS RESCISAO | I121: =IF(H121=B121,1,FALSE) -> 1
A122: 0121 | B122: Gratificacao 30% | C122: PROVENTO | D122: VALOR | E122: 1211-Gratificacoes | I122: =IF(H122=B122,1,FALSE) -> FALSE
A123: 0122 | B123: Dif. Media Comissao Ferias Venc | C123: PROVENTO | D123: VALOR | E123: 6007-Ferias vencidas na rescisao | F123: 0122 | G123: =IF(F123=A123,1,FALSE) -> 1 | H123: DIF. MEDIA COMISSAO FERIAS VENC | I123: =IF(H123=B123,1,FALSE) -> 1
A124: 0123 | B124: Dif. Media Hora Extra 13º Salario Rescis | C124: PROVENTO | D124: VALOR | E124: 6002-13º salario - proporcional na rescisao | F124: 0123 | G124: =IF(F124=A124,1,FALSE) -> 1 | H124: DIF. MEDIA HORA EXTRA 13º SALARIO RESCIS | I124: =IF(H124=B124,1,FALSE) -> 1
A125: 0124 | B125: Dif. Media Comissao 13º Salario Rescisao | C125: PROVENTO | D125: VALOR | E125: 6002-13º salario - proporcional na rescisao | F125: 0124 | G125: =IF(F125=A125,1,FALSE) -> 1 | H125: DIF. MEDIA COMISSAO 13º SALARIO RESCISAO | I125: =IF(H125=B125,1,FALSE) -> 1
A126: 0125 | B126: Desc. Faltas X Suspensao (em Horas) | C126: DESCONTO | D126: HORA | E126: 9209-Faltas ou atrasos | F126: 0125 | G126: =IF(F126=A126,1,FALSE) -> 1 | H126: DESC. FALTAS X SUSPENSAO (EM HORAS) | I126: =IF(H126=B126,1,FALSE) -> 1
A127: 0126 | B127: Dif. Media Comissao Aviso Previo | C127: PROVENTO | D127: VALOR | E127: 6003-Indenizacao compensatoria do aviso-previo | F127: 0126 | G127: =IF(F127=A127,1,FALSE) -> 1 | H127: DIF. MEDIA COMISSAO AVISO PREVIO | I127: =IF(H127=B127,1,FALSE) -> 1
A128: 0127 | B128: Pagamento PIS Empresa | C128: PROVENTO | D128: VALOR | E128: 1402-Abono PIS / PASEP | F128: 0127 | G128: =IF(F128=A128,1,FALSE) -> 1 | H128: PAGAMENTO PIS EMPRESA | I128: =IF(H128=B128,1,FALSE) -> 1
A129: 0128 | B129: Desc. 13º Pago Pela Previdencia | C129: DESCONTO | D129: VALOR | E129: 9299-Outros descontos | F129: 0128 | G129: =IF(F129=A129,1,FALSE) -> 1 | H129: DESC. 13º PAGO PELA PREVIDENCIA | I129: =IF(H129=B129,1,FALSE) -> 1
A130: 0129 | B130: 2ª Parcela 13º Salario | C130: PROVENTO | D130: VALOR | E130: 5001-13º salario | F130: 0129 | G130: =IF(F130=A130,1,FALSE) -> 1 | H130: 2ª PARCELA 13º SALARIO | I130: =IF(H130=B130,1,FALSE) -> 1
A131: 0130 | B131: Desc. INSS 2ª Parcela 13º Salario | C131: DESCONTO | D131: VALOR | E131: 9201-Contribuicao Previdenciaria | F131: 0130 | G131: =IF(F131=A131,1,FALSE) -> 1 | H131: DESC. INSS 2ª PARCELA 13º SALARIO | I131: =IF(H131=B131,1,FALSE) -> 1
A132: 0131 | B132: Desc. Salario Pago a Maior | C132: DESCONTO | D132: VALOR | E132: - | F132: 0131 | G132: =IF(F132=A132,1,FALSE) -> 1 | H132: DESC. SALARIO PAGO A MAIOR | I132: =IF(H132=B132,1,FALSE) -> 1
A133: 0132 | B133: Desc. Adic. Noturn Pago a Maior | C133: DESCONTO | D133: VALOR | E133: - | F133: 0132 | G133: =IF(F133=A133,1,FALSE) -> 1 | H133: DESC. ADIC. NOTURN PAGO A MAIOR | I133: =IF(H133=B133,1,FALSE) -> 1
A134: 0133 | B134: Media Hora Extra 2ª parcela 13º | C134: PROVENTO | D134: VALOR | E134: 5001-13º salario | F134: 0133 | G134: =IF(F134=A134,1,FALSE) -> 1 | H134: MEDIA HORA EXTRA 2ª PARCELA 13º | I134: =IF(H134=B134,1,FALSE) -> 1
... A136: 0135 | B136: Media Val Var Salario Maternidade | C136: PROVENTO | D136: VALOR | E136: 4050-Salario maternidade | F136: 0135 | G136: =IF(F136=A136,1,FALSE) -> 1 | H136: MEDIA VAL VAR SALARIO MATERNIDADE | I136: =IF(H136=B136,1,FALSE) -> 1
A137: 0136 | B137: Devol. Desc. Pl Odontologico OdontoSyste | C137: PROVENTO | D137: VALOR | E137: 1405-Assistencia medica | F137: 0136 | G137: =IF(F137=A137,1,FALSE) -> 1 | H137: DEVOL. DESC. PL ODONTOL ODONTOSYSTEM | I137: 1
A138: 0137 | B138: MP 434 - Indenizacao 50% Salario | C138: PROVENTO | D138: VALOR | E138: 6129-Outras multas ou indenizacoes | F138: 0137 | G138: =IF(F138=A138,1,FALSE) -> 1 | H138: MP 434 - INDENIZACAO 50% SALARIO | I138: =IF(H138=B138,1,FALSE) -> 1
A139: 0138 | B139: Desc. Pl Odontol UNIODONTO Tit | C139: DESCONTO | D139: VALOR | E139: 9219-Desconto de assistencia medica ou odontologica | F139: 0138 | G139: =IF(F139=A139,1,FALSE) -> 1 | H139: DESC. PL ODONTOL UNIODONTO TIT | I139: =IF(H139=B139,1,FALSE) -> 1
A140: 0139 | B140: Reembolso Desc. Vale Alimentacao | C140: PROVENTO | D140: VALOR | E140: - | F140: 0139 | G140: =IF(F140=A140,1,FALSE) -> 1 | H140: REEMBOLSO DESC. VALE ALIMENTACAO | I140: =IF(H140=B140,1,FALSE) -> 1
A141: 0140 | B141: Devol. Desc. Pl Saude HAPVIDA Tit | C141: PROVENTO | D141: VALOR | E141: 1405-Assistencia medica | F141: 0140 | G141: =IF(F141=A141,1,FALSE) -> 1 | H141: DEVOL. DESC. PL SAUDE HAPVIDA TIT | I141: =IF(H141=B141,1,FALSE) -> 1
A142: 0141 | B142: Devol. Desc. Pl Odontologico UniDental | C142: PROVENTO | D142: VALOR | E142: 1405-Assistencia medica | F142: 0141 | G142: =IF(F142=A142,1,FALSE) -> 1 | H142: DEVOL. DESC. PL ODONTOLOGICO UNIDENTAL | I142: =IF(H142=B142,1,FALSE) -> 1
A143: 0142 | B143: Devol. Desc. Pl Saude HAPVIDA Dep | C143: PROVENTO | D143: VALOR | E143: 1405-Assistencia medica | F143: 0142 | G143: =IF(F143=A143,1,FALSE) -> 1 | H143: DEVOL. DESC. PL SAUDE HAPVIDA DEP | I143: =IF(H143=B143,1,FALSE) -> 1
A144: 0143 | B144: Devol. Desc. Pl Saude BRADESCO Tit | C144: PROVENTO | D144: VALOR | E144: 1405-Assistencia medica | F144: 0143 | G144: =IF(F144=A144,1,FALSE) -> 1 | H144: DEVOL. DESC. PL SAUDE BRADESCO TIT | I144: =IF(H144=B144,1,FALSE) -> 1
A145: 0144 | B145: Reembolso Desc. DSR | C145: PROVENTO | D145: VALOR | E145: 1012-Descanso semanal remunerado - DSR e feriado | F145: 0144 | G145: =IF(F145=A145,1,FALSE) -> 1 | H145: REEMBOLSO DESC. DSR | I145: =IF(H145=B145,1,FALSE) -> 1
A146: 0145 | B146: Atestado Medico (Previdencia) (D) | C146: PROVENTO | D146: DIA | E146: 1050-Remuneracao de dias de afastamento | F146: 0145 | G146: =IF(F146=A146,1,FALSE) -> 1 | H146: ATESTADO MEDICO (PREVIDENCIA) (D) | I146: =IF(H146=B146,1,FALSE) -> 1
A147: 0146 | B147: Reembolso Desc. Faltas | C147: PROVENTO | D147: HORA | E147: 9207-Faltas | F147: 0146 | G147: =IF(F147=A147,1,FALSE) -> 1 | H147: REEMBOLSO DESC. FALTAS | I147: =IF(H147=B147,1,FALSE) -> 1
A148: 0147 | B148: Reembolso Desc. Vale Refeicao | C148: PROVENTO | D148: VALOR | E148: - | F148: 0147 | G148: =IF(F148=A148,1,FALSE) -> 1 | H148: REEMBOLSO DESC. VALE REFEICAO | I148: =IF(H148=B148,1,FALSE) -> 1
A149: 0148 | B149: Premio Assiduidade | C149: PROVENTO | D149: VALOR | E149: 2501-Premios | F149: 0148 | G149: =IF(F149=A149,1,FALSE) -> 1 | H149: PREMIO ASSIDUIDADE | I149: =IF(H149=B149,1,FALSE) -> 1
... A155: 0154 | B155: Salario Maternidade Conforme Sefip | C155: BASE | D155: VALOR | E155: 9989-Outros valores informativos | F155: 0154 | G155: =IF(F155=A155,1,FALSE) -> 1 | H155: SALARIO MATERNIDADE CONFORME SEFIP | I155: =IF(H155=B155,1,FALSE) -> 1
A156: 0155 | B156: Desc. PGBL Previdencia Privada PREVVIDA | C156: DESCONTO | D156: VALOR | E156: 9223-Previdencia complementar - parte do empregado | F156: 0155 | G156: =IF(F156=A156,1,FALSE) -> 1 | H156: DESC. PGBL PREVIDENCIA PRIVADA | I156: 1
A157: 0156 | B157: Desc. VGBL Previdencia Privada PREVVIDA | C157: DESCONTO | D157: VALOR | E157: 9223-Previdencia complementar - parte do empregado | F157: 0156 | G157: =IF(F157=A157,1,FALSE) -> 1 | H157: DESC. PGBL PREVIDENCIA PRIV ENVELOPE | I157: 1
...

Sheet ZDEPARA_EVENTOS_original
A1: EMPRESA_DE | B1: CODIGO_DE | C1: NOME_DE | D1: TIPO_EVENTO | E1: COLIGADA_PARA | F1: CODIGO_PARA | G1: NOME_RM | H1: CODIGO_PARA_FICHA_MES1 | I1: NOME_RM_1 | J1: CODIGO_PARA_FICHA_MES2 | K1: NOME_RM_2 | L1: CODIGO_PARA_VERBAS_FERIAS | M1: NOME_RM_3
A2: 0004 | B2: 0967 | C2: # 1ª via cartão hapvida | D2: D-DESCONTO | E2: 1 | F2: CRIAR EVENTO | G2: =IFERROR(VLOOKUP(F2, DADOS_RM_EVENTOS_original!A:B, 2, FALSE), "Código não encontrado/Não digitado") -> Código não encontrado/Não digitado | I2: =IFERROR(VLOOKUP(H2, DADOS_RM_EVENTOS_original!C:D, 2, FALSE), "Código não encontrado/Não digitado") -> Código não encontrado/Não digitado | K2: =IFERROR(VLOOKUP(J2, DADOS_RM_EVENTOS_original!E:J, 2, FALSE), "Código não encontrado/Não digitado") -> Código não encontrado/Não digitado | M2: =IFERROR(VLOOKUP(L2, DADOS_RM_EVENTOS_original!K:L, 2, FALSE), "Código não encontrado/Não digitado") -> Código não encontrado/Não digitado
A3: 0004 | B3: 0608 | C3: # adiantamento base de cálculo | D3: B-BASE | E3: 1 | F3: NÃO IMPORTAR | G3: =IFERROR(VLOOKUP(F3, DADOS_RM_EVENTOS_original!A:B, 2, FALSE), "Código não encontrado/Não digitado") -> Código não encontrado/Não digitado | I3: =IFERROR(VLOOKUP(H3, DADOS_RM_EVENTOS_original!C:D, 2, FALSE), "Código não encontrado/Não digitado") -> Código não encontrado/Não digitado | K3: =IFERROR(VLOOKUP(J3, DADOS_RM_EVENTOS_original!E:J, 2, FALSE), "Código não encontrado/Não digitado") -> Código não encontrado/Não digitado | M3: =IFERROR(VLOOKUP(L3, DADOS_RM_EVENTOS_original!K:L, 2, FALSE), "Código não encontrado/Não digitado") -> Código não encontrado/Não digitado
A4: 0015 | B4: 0151 | C4: # adiantamento de 13º salário (férias) | D4: P-PROVENTO | E4: 2 | F4: 0444 | G4: =IFERROR(VLOOKUP(F4, DADOS_RM_EVENTOS_original!A:B, 2, FALSE), "Código não encontrado/Não digitado") -> Antecipacao Primeira Parcela 13º nas Fer | I4: =IFERROR(VLOOKUP(H4, DADOS_RM_EVENTOS_original!C:D, 2, FALSE), "Código não encontrado/Não digitado") -> Código não encontrado/Não digitado | K4: =IFERROR(VLOOKUP(J4, DADOS_RM_EVENTOS_original!E:J, 2, FALSE), "Código não encontrado/Não digitado") -> Código não encontrado/Não digitado | M4: =IFERROR(VLOOKUP(L4, DADOS_RM_EVENTOS_original!K:L, 2, FALSE), "Código não encontrado/Não digitado") -> Código não encontrado/Não digitado
A5: 0004 | B5: 0345 | C5: # adiantamento extra | D5: D-DESCONTO | E5: 1 | F5: 0019 | G5: =IFERROR(VLOOKUP(F5, DADOS_RM_EVENTOS_original!A:B, 2, FALSE), "Código não encontrado/Não digitado") -> ( - ) Desc. Adiantamento Salarial | I5: =IFERROR(VLOOKUP(H5, DADOS_RM_EVENTOS_original!C:D, 2, FALSE), "Código não encontrado/Não digitado") -> Código não encontrado/Não digitado | K5: =IFERROR(VLOOKUP(J5, DADOS_RM_EVENTOS_original!E:J, 2, FALSE), "Código não encontrado/Não digitado") -> Código não encontrado/Não digitado | M5: =IFERROR(VLOOKUP(L5, DADOS_RM_EVENTOS_original!K:L, 2, FALSE), "Código não encontrado/Não digitado") -> Código não encontrado/Não digitado
A6: 0004 | B6: 0342 | C6: # almoco | D6: D-DESCONTO | E6: 1 | F6: 0092 | G6: =IFERROR(VLOOKUP(F6, DADOS_RM_EVENTOS_original!A:B, 2, FALSE), "Código não encontrado/Não digitado") -> Desc. Vale Alimentacao | I6: =IFERROR(VLOOKUP(H6, DADOS_RM_EVENTOS_original!C:D, 2, FALSE), "Código não encontrado/Não digitado") -> Código não encontrado/Não digitado | K6: =IFERROR(VLOOKUP(J6, DADOS_RM_EVENTOS_original!E:J, 2, FALSE), "Código não encontrado/Não digitado") -> Código não encontrado/Não digitado | M6: =IFERROR(VLOOKUP(L6, DADOS_RM_EVENTOS_original!K:L, 2, FALSE), "Código não encontrado/Não digitado") -> Código não encontrado/Não digitado
A7: 0004 | B7: 0391 | C7: # arredondamento (desconto) | D7: D-DESCONTO | E7: 1 | F7: 0275 | G7: =IFERROR(VLOOKUP(F7, DADOS_RM_EVENTOS_original!A:B, 2, FALSE), "Código não encontrado/Não digitado") -> Desc. Arred. Liquido Insufuciente | I7: =IFERROR(VLOOKUP(H7, DADOS_RM_EVENTOS_original!C:D, 2, FALSE), "Código não encontrado/Não digitado") -> Código não encontrado/Não digitado | K7: =IFERROR(VLOOKUP(J7, DADOS_RM_EVENTOS_original!E:J, 2, FALSE), "Código não encontrado/Não digitado") -> Código não encontrado/Não digitado | M7: =IFERROR(VLOOKUP(L7, DADOS_RM_EVENTOS_original!K:L, 2, FALSE), "Código não encontrado/Não digitado") -> Código não encontrado/Não digitado
A8: 0004 | B8: 0091 | C8: # arredondamento (provento) | D8: P-PROVENTO | E8: 1 | F8: 0817 | G8: =IFERROR(VLOOKUP(F8, DADOS_RM_EVENTOS_original!A:B, 2, FALSE), "Código não encontrado/Não digitado") -> Arredondamento Liquido Insuficiente | I8: =IFERROR(VLOOKUP(H8, DADOS_RM_EVENTOS_original!C:D, 2, FALSE), "Código não encontrado/Não digitado") -> Código não encontrado/Não digitado | K8: =IFERROR(VLOOKUP(J8, DADOS_RM_EVENTOS_original!E:J, 2, FALSE), "Código não encontrado/Não digitado") -> Código não encontrado/Não digitado | M8: =IFERROR(VLOOKUP(L8, DADOS_RM_EVENTOS_original!K:L, 2, FALSE), "Código não encontrado/Não digitado") -> Código não encontrado/Não digitado
A9: 0004 | B9: 0392 | C9: # arredondamento compensação (desconto) | D9: D-DESCONTO | E9: 1 | F9: 0275 | G9: =IFERROR(VLOOKUP(F9, DADOS_RM_EVENTOS_original!A:B, 2, FALSE), "Código não encontrado/Não digitado") -> Desc. Arred. Liquido Insufuciente | I9: =IFERROR(VLOOKUP(H9, DADOS_RM_EVENTOS_original!C:D, 2, FALSE), "Código não encontrado/Não digitado") -> Código não encontrado/Não digitado | K9: =IFERROR(VLOOKUP(J9, DADOS_RM_EVENTOS_original!E:J, 2, FALSE), "Código não encontrado/Não digitado") -> Código não encontrado/Não digitado | M9: =IFERROR(VLOOKUP(L9, DADOS_RM_EVENTOS_original!K:L, 2, FALSE), "Código não encontrado/Não digitado") -> Código não encontrado/Não digitado
A10: 0004 | B10: 0170 | C10: # complemento de 13º salário | D10: P-PROVENTO | E10: 1 | F10: 0839 | G10: =IFERROR(VLOOKUP(F10, DADOS_RM_EVENTOS_original!A:B, 2, FALSE), "Código não encontrado/Não digitado") -> Dif. 13º Salario (Janeiro) | I10: =IFERROR(VLOOKUP(H10, DADOS_RM_EVENTOS_original!C:D, 2, FALSE), "Código não encontrado/Não digitado") -> Código não encontrado/Não digitado | K10: =IFERROR(VLOOKUP(J10, DADOS_RM_EVENTOS_original!E:J, 2, FALSE), "Código não encontrado/Não digitado") -> Código não encontrado/Não digitado | M10: =IFERROR(VLOOKUP(L10, DADOS_RM_EVENTOS_original!K:L, 2, FALSE), "Código não encontrado/Não digitado") -> Código não encontrado/Não digitado
A11: 0004 | B11: 0338 | C11: # contribuicao sindical mensal | D11: D-DESCONTO | E11: 1 | F11: 0201 | G11: =IFERROR(VLOOKUP(F11, DADOS_RM_EVENTOS_original!A:B, 2, FALSE), "Código não encontrado/Não digitado") -> Desc. Mensalidade Sindical | I11: =IFERROR(VLOOKUP(H11, DADOS_RM_EVENTOS_original!C:D, 2, FALSE), "Código não encontrado/Não digitado") -> Código não encontrado/Não digitado | K11: =IFERROR(VLOOKUP(J11, DADOS_RM_EVENTOS_original!E:J, 2, FALSE), "Código não encontrado/Não digitado") -> Código não encontrado/Não digitado | M11: =IFERROR(VLOOKUP(L11, DADOS_RM_EVENTOS_original!K:L, 2, FALSE), "Código não encontrado/Não digitado") -> Código não encontrado/Não digitado
A12: 0004 | B12: 0221 | C12: # desc cartao vale transporte eletronico | D12: D-DESCONTO | E12: 1 | F12: 0047 | G12: =IFERROR(VLOOKUP(F12, DADOS_RM_EVENTOS_original!A:B, 2, FALSE), "Código não encontrado/Não digitado") -> Desc. 2a via PASSCARD | I12: =IFERROR(VLOOKUP(H12, DADOS_RM_EVENTOS_original!C:D, 2, FALSE), "Código não encontrado/Não digitado") -> Código não encontrado/Não digitado | K12: =IFERROR(VLOOKUP(J12, DADOS_RM_EVENTOS_original!E:J, 2, FALSE), "Código não encontrado/Não digitado") -> Código não encontrado/Não digitado | M12: =IFERROR(VLOOKUP(L12, DADOS_RM_EVENTOS_original!K:L, 2, FALSE), "Código não encontrado/Não digitado") -> Código não encontrado/Não digitado
A13: 0004 | B13: 0139 | C13: # devol.contribuicao sindical | D13: P-PROVENTO | E13: 1 | F13: 0324 | G13: =IFERROR(VLOOKUP(F13, DADOS_RM_EVENTOS_original!A:B, 2, FALSE), "Código não encontrado/Não digitado") -> Reembolso de Contribuicao Sindical | I13: =IFERROR(VLOOKUP(H13, DADOS_RM_EVENTOS_original!C:D, 2, FALSE), "Código não encontrado/Não digitado") -> Código não encontrado/Não digitado | K13: =IFERROR(VLOOKUP(J13, DADOS_RM_EVENTOS_original!E:J, 2, FALSE), "Código não encontrado/Não digitado") -> Código não encontrado/Não digitado | M13: =IFERROR(VLOOKUP(L13, DADOS_RM_EVENTOS_original!K:L, 2, FALSE), "Código não encontrado/Não digitado") -> Código não encontrado/Não digitado
... A56: 0012 | B56: 0967 | C56: 1/3 de Abono Pecuniário | D56: P-PROVENTO | E56: 5 | F56: 0056 | G56: =IFERROR(VLOOKUP(F56, DADOS_RM_EVENTOS_original!A:B, 2, FALSE), "Código não encontrado/Não digitado") -> 1/3 Abono de Ferias | I56: =IFERROR(VLOOKUP(H56, DADOS_RM_EVENTOS_original!C:D, 2, FALSE), "Código não encontrado/Não digitado") -> Código não encontrado/Não digitado | K56: =IFERROR(VLOOKUP(J56, DADOS_RM_EVENTOS_original!E:J, 2, FALSE), "Código não encontrado/Não digitado") -> Código não encontrado/Não digitado | M56: =IFERROR(VLOOKUP(L56, DADOS_RM_EVENTOS_original!K:L, 2, FALSE), "Código não encontrado/Não digitado") -> Código não encontrado/Não digitado
A57: 0004 | B57: 0111 | C57: 1/3 DE FÉRIAS | D57: P-PROVENTO | E57: 1 | F57: 0076 | G57: =IFERROR(VLOOKUP(F57, DADOS_RM_EVENTOS_original!A:B, 2, FALSE), "Código não encontrado/Não digitado") -> 1/3 Ferias no Mes | H57: 0076 | I57: =IFERROR(VLOOKUP(H57, DADOS_RM_EVENTOS_original!A:D, 2, FALSE), "Código não encontrado/Não digitado") -> 1/3 Ferias no Mes | J57: 0077 | K57: =IFERROR(VLOOKUP(J57, DADOS_RM_EVENTOS_original!A:J, 2, FALSE), "Código não encontrado/Não digitado") -> 1/3 Ferias no Proximo Mes | L57: 0040 | M57: =IFERROR(VLOOKUP(L57, DADOS_RM_EVENTOS_original!A:L, 2, FALSE), "Código não encontrado/Não digitado") -> 1/3 de Ferias (Recibo)
A58: 0015 | B58: 0111 | C58: 1/3 DE FÉRIAS | D58: P-PROVENTO | E58: 2 | F58: 0076 | G58: =IFERROR(VLOOKUP(F58, DADOS_RM_EVENTOS_original!A:B, 2, FALSE), "Código não encontrado/Não digitado") -> 1/3 Ferias no Mes | H58: 0076 | I58: =IFERROR(VLOOKUP(H58, DADOS_RM_EVENTOS_original!A:D, 2, FALSE), "Código não encontrado/Não digitado") -> 1/3 Ferias no Mes | J58: 0077 | K58: =IFERROR(VLOOKUP(J58, DADOS_RM_EVENTOS_original!A:J, 2, FALSE), "Código não encontrado/Não digitado") -> 1/3 Ferias no Proximo Mes | L58: 0040 | M58: =IFERROR(VLOOKUP(L58, DADOS_RM_EVENTOS_original!A:L, 2, FALSE), "Código não encontrado/Não digitado") -> 1/3 de Ferias (Recibo)
A59: 0017 | B59: 0111 | C59: 1/3 de Férias | D59: P-PROVENTO | E59: 3 | F59: 0076 | G59: =IFERROR(VLOOKUP(F59, DADOS_RM_EVENTOS_original!A:B, 2, FALSE), "Código não encontrado/Não digitado") -> 1/3 Ferias no Mes | H59: 0076 | I59: =IFERROR(VLOOKUP(H59, DADOS_RM_EVENTOS_original!A:D, 2, FALSE), "Código não encontrado/Não digitado") -> 1/3 Ferias no Mes | J59: 0077 | K59: =IFERROR(VLOOKUP(J59, DADOS_RM_EVENTOS_original!A:J, 2, FALSE), "Código não encontrado/Não digitado") -> 1/3 Ferias no Proximo Mes | L59: 0040 | M59: =IFERROR(VLOOKUP(L59, DADOS_RM_EVENTOS_original!A:L, 2, FALSE), "Código não encontrado/Não digitado") -> 1/3 de Ferias (Recibo)
A60: 0005 | B60: 0111 | C60: 1/3 de Férias | D60: P-PROVENTO | E60: 4 | F60: 0076 | G60: =IFERROR(VLOOKUP(F60, DADOS_RM_EVENTOS_original!A:B, 2, FALSE), "Código não encontrado/Não digitado") -> 1/3 Ferias no Mes | H60: 0076 | I60: =IFERROR(VLOOKUP(H60, DADOS_RM_EVENTOS_original!A:D, 2, FALSE), "Código não encontrado/Não digitado") -> 1/3 Ferias no Mes | J60: 0077 | K60: =IFERROR(VLOOKUP(J60, DADOS_RM_EVENTOS_original!A:J, 2, FALSE), "Código não encontrado/Não digitado") -> 1/3 Ferias no Proximo Mes | L60: 0040 | M60: =IFERROR(VLOOKUP(L60, DADOS_RM_EVENTOS_original!A:L, 2, FALSE), "Código não encontrado/Não digitado") -> 1/3 de Ferias (Recibo)
A61: 0012 | B61: 0111 | C61: 1/3 de Férias | D61: P-PROVENTO | E61: 5 | F61: 0076 | G61: =IFERROR(VLOOKUP(F61, DADOS_RM_EVENTOS_original!A:B, 2, FALSE), "Código não encontrado/Não digitado") -> 1/3 Ferias no Mes | H61: 0076 | I61: =IFERROR(VLOOKUP(H61, DADOS_RM_EVENTOS_original!A:D, 2, FALSE), "Código não encontrado/Não digitado") -> 1/3 Ferias no Mes | J61: 0077 | K61: =IFERROR(VLOOKUP(J61, DADOS_RM_EVENTOS_original!A:J, 2, FALSE), "Código não encontrado/Não digitado") -> 1/3 Ferias no Proximo Mes | L61: 0040 | M61: =IFERROR(VLOOKUP(L61, DADOS_RM_EVENTOS_original!A:L, 2, FALSE), "Código não encontrado/Não digitado") -> 1/3 de Ferias (Recibo)
A62: 0022 | B62: 0111 | C62: 1/3 de Férias | D62: P-PROVENTO | E62: 6 | F62: 0076 | G62: =IFERROR(VLOOKUP(F62, DADOS_RM_EVENTOS_original!A:B, 2, FALSE), "Código não encontrado/Não digitado") -> 1/3 Ferias no Mes | H62: 0076 | I62: =IFERROR(VLOOKUP(H62, DADOS_RM_EVENTOS_original!A:D, 2, FALSE), "Código não encontrado/Não digitado") -> 1/3 Ferias no Mes | J62: 0077 | K62: =IFERROR(VLOOKUP(J62, DADOS_RM_EVENTOS_original!A:J, 2, FALSE), "Código não encontrado/Não digitado") -> 1/3 Ferias no Proximo Mes | L62: 0040 | M62: =IFERROR(VLOOKUP(L62, DADOS_RM_EVENTOS_original!A:L, 2, FALSE), "Código não encontrado/Não digitado") -> 1/3 de Ferias (Recibo)
A63: 0004 | B63: 0207 | C63: 1/3 DE FÉRIAS (RESCISÃO) | D63: P-PROVENTO | E63: 1 | F63: 0063 | G63: =IFERROR(VLOOKUP(F63, DADOS_RM_EVENTOS_original!A:B, 2, FALSE), "Código não encontrado/Não digitado") -> 1/3 Ferias Rescisao | I63: =IFERROR(VLOOKUP(H63, DADOS_RM_EVENTOS_original!C:D, 2, FALSE), "Código não encontrado/Não digitado") -> Código não encontrado/Não digitado | K63: =IFERROR(VLOOKUP(J63, DADOS_RM_EVENTOS_original!E:J, 2, FALSE), "Código não encontrado/Não digitado") -> Código não encontrado/Não digitado | M63: =IFERROR(VLOOKUP(L63, DADOS_RM_EVENTOS_original!K:L, 2, FALSE), "Código não encontrado/Não digitado") -> Código não encontrado/Não digitado
A64: 0005 | B64: 0207 | C64: 1/3 de Férias (Rescisão) | D64: P-PROVENTO | E64: 4 | F64: 0063 | G64: =IFERROR(VLOOKUP(F64, DADOS_RM_EVENTOS_original!A:B, 2, FALSE), "Código não encontrado/Não digitado") -> 1/3 Ferias Rescisao | I64: =IFERROR(VLOOKUP(H64, DADOS_RM_EVENTOS_original!C:D, 2, FALSE), "Código não encontrado/Não digitado") -> Código não encontrado/Não digitado | K64: =IFERROR(VLOOKUP(J64, DADOS_RM_EVENTOS_original!E:J, 2, FALSE), "Código não encontrado/Não digitado") -> Código não encontrado/Não digitado | M64: =IFERROR(VLOOKUP(L64, DADOS_RM_EVENTOS_original!K:L, 2, FALSE), "Código não encontrado/Não digitado") -> Código não encontrado/Não digitado
A65: 0012 | B65: 0207 | C65: 1/3 de Férias (Rescisão) | D65: P-PROVENTO | E65: 5 | F65: 0063 | G65: =IFERROR(VLOOKUP(F65, DADOS_RM_EVENTOS_original!A:B, 2, FALSE), "Código não encontrado/Não digitado") -> 1/3 Ferias Rescisao | I65: =IFERROR(VLOOKUP(H65, DADOS_RM_EVENTOS_original!C:D, 2, FALSE), "Código não encontrado/Não digitado") -> Código não encontrado/Não digitado | K65: =IFERROR(VLOOKUP(J65, DADOS_RM_EVENTOS_original!E:J, 2, FALSE), "Código não encontrado/Não digitado") -> Código não encontrado/Não digitado | M65: =IFERROR(VLOOKUP(L65, DADOS_RM_EVENTOS_original!K:L, 2, FALSE), "Código não encontrado/Não digitado") -> Código não encontrado/Não digitado
A66: 0004 | B66: 0987 | C66: 1/3 de Férias Indenizadas | D66: P-PROVENTO | E66: 1 | F66: 0063 | G66: =IFERROR(VLOOKUP(F66, DADOS_RM_EVENTOS_original!A:B, 2, FALSE), "Código não encontrado/Não digitado") -> 1/3 Ferias Rescisao | I66: =IFERROR(VLOOKUP(H66, DADOS_RM_EVENTOS_original!C:D, 2, FALSE), "Código não encontrado/Não digitado") -> Código não encontrado/Não digitado | K66: =IFERROR(VLOOKUP(J66, DADOS_RM_EVENTOS_original!E:J, 2, FALSE), "Código não encontrado/Não digitado") -> Código não encontrado/Não digitado | M66: =IFERROR(VLOOKUP(L66, DADOS_RM_EVENTOS_original!K:L, 2, FALSE), "Código não encontrado/Não digitado") -> Código não encontrado/Não digitado
A67: 0017 | B67: 0968 | C67: 1/3 de Férias Proporcionais | D67: P-PROVENTO | E67: 3 | F67: 0063 | G67: =IFERROR(VLOOKUP(F67, DADOS_RM_EVENTOS_original!A:B, 2, FALSE), "Código não encontrado/Não digitado") -> 1/3 Ferias Rescisao | I67: =IFERROR(VLOOKUP(H67, DADOS_RM_EVENTOS_original!C:D, 2, FALSE), "Código não encontrado/Não digitado") -> Código não encontrado/Não digitado | K67: =IFERROR(VLOOKUP(J67, DADOS_RM_EVENTOS_original!E:J, 2, FALSE), "Código não encontrado/Não digitado") -> Código não encontrado/Não digitado | M67: =IFERROR(VLOOKUP(L67, DADOS_RM_EVENTOS_original!K:L, 2, FALSE), "Código não encontrado/Não digitado") -> Código não encontrado/Não digitado
A68: 0005 | B68: 0960 | C68: 1/3 de Férias Proporcionais | D68: P-PROVENTO | E68: 4 | F68: 0063 | G68: =IFERROR(VLOOKUP(F68, DADOS_RM_EVENTOS_original!A:B, 2, FALSE), "Código não encontrado/Não digitado") -> 1/3 Ferias Rescisao | I68: =IFERROR(VLOOKUP(H68, DADOS_RM_EVENTOS_original!C:D, 2, FALSE), "Código não encontrado/Não digitado") -> Código não encontrado/Não digitado | K68: =IFERROR(VLOOKUP(J68, DADOS_RM_EVENTOS_original!E:J, 2, FALSE), "Código não encontrado/Não digitado") -> Código não encontrado/Não digitado | M68: =IFERROR(VLOOKUP(L68, DADOS_RM_EVENTOS_original!K:L, 2, FALSE), "Código não encontrado/Não digitado") -> Código não encontrado/Não digitado
A69: 0012 | B69: 0959 | C69: 1/3 de Férias Proporcionais | D69: P-PROVENTO | E69: 5 | F69: 0063 | G69: =IFERROR(VLOOKUP(F69, DADOS_RM_EVENTOS_original!A:B, 2, FALSE), "Código não encontrado/Não digitado") -> 1/3 Ferias Rescisao | I69: =IFERROR(VLOOKUP(H69, DADOS_RM_EVENTOS_original!C:D, 2, FALSE), "Código não encontrado/Não digitado") -> Código não encontrado/Não digitado | K69: =IFERROR(VLOOKUP(J69, DADOS_RM_EVENTOS_original!E:J, 2, FALSE), "Código não encontrado/Não digitado") -> Código não encontrado/Não digitado | M69: =IFERROR(VLOOKUP(L69, DADOS_RM_EVENTOS_original!K:L, 2, FALSE), "Código não encontrado/Não digitado") -> Código não encontrado/Não digitado
A70: 0022 | B70: 0212 | C70: 1/3 de Férias Proporcionais | D70: P-PROVENTO | E70: 6 | F70: 0063 | G70: =IFERROR(VLOOKUP(F70, DADOS_RM_EVENTOS_original!A:B, 2, FALSE), "Código não encontrado/Não digitado") -> 1/3 Ferias Rescisao | I70: =IFERROR(VLOOKUP(H70, DADOS_RM_EVENTOS_original!C:D, 2, FALSE), "Código não encontrado/Não digitado") -> Código não encontrado/Não digitado | K70: =IFERROR(VLOOKUP(J70, DADOS_RM_EVENTOS_original!E:J, 2, FALSE), "Código não encontrado/Não digitado") -> Código não encontrado/Não digitado | M70: =IFERROR(VLOOKUP(L70, DADOS_RM_EVENTOS_original!K:L, 2, FALSE), "Código não encontrado/Não digitado") -> Código não encontrado/Não digitado
A71: 0004 | B71: 0973 | C71: 1/3 de Férias Proporcionais 1 | D71: P-PROVENTO | E71: 1 | F71: 0063 | G71: =IFERROR(VLOOKUP(F71, DADOS_RM_EVENTOS_original!A:B, 2, FALSE), "Código não encontrado/Não digitado") -> 1/3 Ferias Rescisao | I71: =IFERROR(VLOOKUP(H71, DADOS_RM_EVENTOS_original!C:D, 2, FALSE), "Código não encontrado/Não digitado") -> Código não encontrado/Não digitado | K71: =IFERROR(VLOOKUP(J71, DADOS_RM_EVENTOS_original!E:J, 2, FALSE), "Código não encontrado/Não digitado") -> Código não encontrado/Não digitado | M71: =IFERROR(VLOOKUP(L71, DADOS_RM_EVENTOS_original!K:L, 2, FALSE), "Código não encontrado/Não digitado") -> Código não encontrado/Não digitado
A72: 0015 | B72: 0973 | C72: 1/3 de Férias Proporcionais 1 | D72: P-PROVENTO | E72: 2 | F72: 0063 | G72: =IFERROR(VLOOKUP(F72, DADOS_RM_EVENTOS_original!A:B, 2, FALSE), "Código não encontrado/Não digitado") -> 1/3 Ferias Rescisao | I72: =IFERROR(VLOOKUP(H72, DADOS_RM_EVENTOS_original!C:D, 2, FALSE), "Código não encontrado/Não digitado") -> Código não encontrado/Não digitado | K72: =IFERROR(VLOOKUP(J72, DADOS_RM_EVENTOS_original!E:J, 2, FALSE), "Código não encontrado/Não digitado") -> Código não encontrado/Não digitado | M72: =IFERROR(VLOOKUP(L72, DADOS_RM_EVENTOS_original!K:L, 2, FALSE), "Código não encontrado/Não digitado") -> Código não encontrado/Não digitado
A73: 0017 | B73: 0969 | C73: 1/3 de Férias Vencidas | D73: P-PROVENTO | E73: 3 | F73: 0803 | G73: =IFERROR(VLOOKUP(F73, DADOS_RM_EVENTOS_original!A:B, 2, FALSE), "Código não encontrado/Não digitado") -> Adicional 1/3 Ferias Vencidas | I73: =IFERROR(VLOOKUP(H73, DADOS_RM_EVENTOS_original!C:D, 2, FALSE), "Código não encontrado/Não digitado") -> Código não encontrado/Não digitado | K73: =IFERROR(VLOOKUP(J73, DADOS_RM_EVENTOS_original!E:J, 2, FALSE), "Código não encontrado/Não digitado") -> Código não encontrado/Não digitado | M73: =IFERROR(VLOOKUP(L73, DADOS_RM_EVENTOS_original!K:L, 2, FALSE), "Código não encontrado/Não digitado") -> Código não encontrado/Não digitado
A74: 0005 | B74: 0961 | C74: 1/3 de Férias Vencidas | D74: P-PROVENTO | E74: 4 | F74: 0803 | G74: =IFERROR(VLOOKUP(F74, DADOS_RM_EVENTOS_original!A:B, 2, FALSE), "Código não encontrado/Não digitado") -> Adicional 1/3 Ferias Vencidas | I74: =IFERROR(VLOOKUP(H74, DADOS_RM_EVENTOS_original!C:D, 2, FALSE), "Código não encontrado/Não digitado") -> Código não encontrado/Não digitado | K74: =IFERROR(VLOOKUP(J74, DADOS_RM_EVENTOS_original!E:J, 2, FALSE), "Código não encontrado/Não digitado") -> Código não encontrado/Não digitado | M74: =IFERROR(VLOOKUP(L74, DADOS_RM_EVENTOS_original!K:L, 2, FALSE), "Código não encontrado/Não digitado") -> Código não encontrado/Não digitado
... A558: 0012 | B558: 0949 | C558: Refeição Mês Anterior | D558: P-PROVENTO | E558: 5 | F558: 0147 | G558: =IFERROR(VLOOKUP(F558, DADOS_RM_EVENTOS_original!A:B, 2, FALSE), "Código não encontrado/Não digitado") -> Reembolso Desc. Vale Refeicao | I558: =IFERROR(VLOOKUP(H558, DADOS_RM_EVENTOS_original!C:D, 2, FALSE), "Código não encontrado/Não digitado") -> Código não encontrado/Não digitado | K558: =IFERROR(VLOOKUP(J558, DADOS_RM_EVENTOS_original!E:J, 2, FALSE), "Código não encontrado/Não digitado") -> Código não encontrado/Não digitado | M558: =IFERROR(VLOOKUP(L558, DADOS_RM_EVENTOS_original!K:L, 2, FALSE), "Código não encontrado/Não digitado") -> Código não encontrado/Não digitado
A559: 0004 | B559: 0110 | C559: REMUNERAÇÃO DE FÉRIAS | D559: P-PROVENTO | E559: 1 | F559: 0041 | G559: =IFERROR(VLOOKUP(F559, DADOS_RM_EVENTOS_original!A:B, 2, FALSE), "Código não encontrado/Não digitado") -> Ferias no Mes | H559: 0041 | I559: =IFERROR(VLOOKUP(H559, DADOS_RM_EVENTOS_original!A:D, 2, FALSE), "Código não encontrado/Não digitado") -> Ferias no Mes | J559: 0042 | K559: =IFERROR(VLOOKUP(J559, DADOS_RM_EVENTOS_original!A:J, 2, FALSE), "Código não encontrado/Não digitado") -> Ferias no Proximo Mes | L559: 0038 | M559: =IFERROR(VLOOKUP(L559, DADOS_RM_EVENTOS_original!A:L, 2, FALSE), "Código não encontrado/Não digitado") -> Dias de Ferias (Recibo)
A560: 0015 | B560: 0110 | C560: REMUNERAÇÃO DE FÉRIAS | D560: P-PROVENTO | E560: 2 | F560: 0041 | G560: =IFERROR(VLOOKUP(F560, DADOS_RM_EVENTOS_original!A:B, 2, FALSE), "Código não encontrado/Não digitado") -> Ferias no Mes | H560: 0041 | I560: =IFERROR(VLOOKUP(H560, DADOS_RM_EVENTOS_original!A:D, 2, FALSE), "Código não encontrado/Não digitado") -> Ferias no Mes | J560: 0042 | K560: =IFERROR(VLOOKUP(J560, DADOS_RM_EVENTOS_original!A:J, 2, FALSE), "Código não encontrado/Não digitado") -> Ferias no Proximo Mes | L560: 0038 | M560: =IFERROR(VLOOKUP(L560, DADOS_RM_EVENTOS_original!A:L, 2, FALSE), "Código não encontrado/Não digitado") -> Dias de Ferias (Recibo)
A561: 0017 | B561: 0110 | C561: Remuneração de Férias | D561: P-PROVENTO | E561: 3 | F561: 0016 | G561: =IFERROR(VLOOKUP(F561, DADOS_RM_EVENTOS_original!A:B, 2, FALSE), "Código não encontrado/Não digitado") -> Provento ferias | I561: =IFERROR(VLOOKUP(H561, DADOS_RM_EVENTOS_original!C:D, 2, FALSE), "Código não encontrado/Não digitado") -> Código não encontrado/Não digitado | K561: =IFERROR(VLOOKUP(J561, DADOS_RM_EVENTOS_original!E:J, 2, FALSE), "Código não encontrado/Não digitado") -> Código não encontrado/Não digitado | M561: =IFERROR(VLOOKUP(L561, DADOS_RM_EVENTOS_original!K:L, 2, FALSE), "Código não encontrado/Não digitado") -> Código não encontrado/Não digitado
A562: 0005 | B562: 0110 | C562: Remuneração de Férias | D562: P-PROVENTO | E562: 4 | F562: 0041 | G562: =IFERROR(VLOOKUP(F562, DADOS_RM_EVENTOS_original!A:B, 2, FALSE), "Código não encontrado/Não digitado") -> Ferias no Mes | H562: 0041 | I562: =IFERROR(VLOOKUP(H562, DADOS_RM_EVENTOS_original!A:D, 2, FALSE), "Código não encontrado/Não digitado") -> Ferias no Mes | J562: 0042 | K562: =IFERROR(VLOOKUP(J562, DADOS_RM_EVENTOS_original!A:J, 2, FALSE), "Código não encontrado/Não digitado") -> Ferias no Proximo Mes | L562: 0038 | M562: =IFERROR(VLOOKUP(L562, DADOS_RM_EVENTOS_original!A:L, 2, FALSE), "Código não encontrado/Não digitado") -> Dias de Ferias (Recibo)
A563: 0012 | B563: 0110 | C563: Remuneração de Férias | D563: P-PROVENTO | E563: 5 | F563: 0041 | G563: =IFERROR(VLOOKUP(F563, DADOS_RM_EVENTOS_original!A:B, 2, FALSE), "Código não encontrado/Não digitado") -> Ferias no Mes | H563: 0041 | I563: =IFERROR(VLOOKUP(H563, DADOS_RM_EVENTOS_original!A:D, 2, FALSE), "Código não encontrado/Não digitado") -> Ferias no Mes | J563: 0042 | K563: =IFERROR(VLOOKUP(J563, DADOS_RM_EVENTOS_original!A:J, 2, FALSE), "Código não encontrado/Não digitado") -> Ferias no Proximo Mes | L563: 0038 | M563: =IFERROR(VLOOKUP(L563, DADOS_RM_EVENTOS_original!A:L, 2, FALSE), "Código não encontrado/Não digitado") -> Dias de Ferias (Recibo)
A564: 0022 | B564: 0110 | C564: Remuneração de Férias | D564: P-PROVENTO | E564: 6 | F564: 0041 | G564: =IFERROR(VLOOKUP(F564, DADOS_RM_EVENTOS_original!A:B, 2, FALSE), "Código não encontrado/Não digitado") -> Ferias no Mes | H564: 0041 | I564: =IFERROR(VLOOKUP(H564, DADOS_RM_EVENTOS_original!A:D, 2, FALSE), "Código não encontrado/Não digitado") -> Ferias no Mes | J564: 0042 | K564: =IFERROR(VLOOKUP(J564, DADOS_RM_EVENTOS_original!A:J, 2, FALSE), "Código não encontrado/Não digitado") -> Ferias no Proximo Mes | L564: 0038 | M564: =IFERROR(VLOOKUP(L564, DADOS_RM_EVENTOS_original!A:L, 2, FALSE), "Código não encontrado/Não digitado") -> Dias de Ferias (Recibo)
A565: 0004 | B565: 0112 | C565: REMUNERAÇÃO DE FÉRIAS EM DOBRO | D565: P-PROVENTO | E565: 1 | F565: 0240 | G565: =IFERROR(VLOOKUP(F565, DADOS_RM_EVENTOS_original!A:B, 2, FALSE), "Código não encontrado/Não digitado") -> Ferias em Dobro | I565: =IFERROR(VLOOKUP(H565, DADOS_RM_EVENTOS_original!C:D, 2, FALSE), "Código não encontrado/Não digitado") -> Código não encontrado/Não digitado | K565: =IFERROR(VLOOKUP(J565, DADOS_RM_EVENTOS_original!E:J, 2, FALSE), "Código não encontrado/Não digitado") -> Código não encontrado/Não digitado | M565: =IFERROR(VLOOKUP(L565, DADOS_RM_EVENTOS_original!K:L, 2, FALSE), "Código não encontrado/Não digitado") -> Código não encontrado/Não digitado
A566: 0017 | B566: 0601 | C566: Remuneração Fixa | D566: B-BASE | E566: 3 | F566: NÃO IMPORTAR | G566: =IFERROR(VLOOKUP(F566, DADOS_RM_EVENTOS_original!A:B, 2, FALSE), "Código não encontrado/Não digitado") -> Código não encontrado/Não digitado | I566: =IFERROR(VLOOKUP(H566, DADOS_RM_EVENTOS_original!C:D, 2, FALSE), "Código não encontrado/Não digitado") -> Código não encontrado/Não digitado | K566: =IFERROR(VLOOKUP(J566, DADOS_RM_EVENTOS_original!E:J, 2, FALSE), "Código não encontrado/Não digitado") -> Código não encontrado/Não digitado | M566: =IFERROR(VLOOKUP(L566, DADOS_RM_EVENTOS_original!K:L, 2, FALSE), "Código não encontrado/Não digitado") -> Código não encontrado/Não digitado
A567: 0005 | B567: 0601 | C567: Remuneração Fixa | D567: B-BASE | E567: 4 | F567: NÃO IMPORTAR | G567: =IFERROR(VLOOKUP(F567, DADOS_RM_EVENTOS_original!A:B, 2, FALSE), "Código não encontrado/Não digitado") -> Código não encontrado/Não digitado | I567: =IFERROR(VLOOKUP(H567, DADOS_RM_EVENTOS_original!C:D, 2, FALSE), "Código não encontrado/Não digitado") -> Código não encontrado/Não digitado | K567: =IFERROR(VLOOKUP(J567, DADOS_RM_EVENTOS_original!E:J, 2, FALSE), "Código não encontrado/Não digitado") -> Código não encontrado/Não digitado | M567: =IFERROR(VLOOKUP(L567, DADOS_RM_EVENTOS_original!K:L, 2, FALSE), "Código não encontrado/Não digitado") -> Código não encontrado/Não digitado
A568: 0012 | B568: 0601 | C568: Remuneração Fixa | D568: B-BASE | E568: 5 | F568: NÃO IMPORTAR | G568: =IFERROR(VLOOKUP(F568, DADOS_RM_EVENTOS_original!A:B, 2, FALSE), "Código não encontrado/Não digitado") -> Código não encontrado/Não digitado | I568: =IFERROR(VLOOKUP(H568, DADOS_RM_EVENTOS_original!C:D, 2, FALSE), "Código não encontrado/Não digitado") -> Código não encontrado/Não digitado | K568: =IFERROR(VLOOKUP(J568, DADOS_RM_EVENTOS_original!E:J, 2, FALSE), "Código não encontrado/Não digitado") -> Código não encontrado/Não digitado | M568: =IFERROR(VLOOKUP(L568, DADOS_RM_EVENTOS_original!K:L, 2, FALSE), "Código não encontrado/Não digitado") -> Código não encontrado/Não digitado
A569: 0022 | B569: 0601 | C569: Remuneração Fixa | D569: B-BASE | E569: 6 | F569: NÃO IMPORTAR | G569: =IFERROR(VLOOKUP(F569, DADOS_RM_EVENTOS_original!A:B, 2, FALSE), "Código não encontrado/Não digitado") -> Código não encontrado/Não digitado | I569: =IFERROR(VLOOKUP(H569, DADOS_RM_EVENTOS_original!C:D, 2, FALSE), "Código não encontrado/Não digitado") -> Código não encontrado/Não digitado | K569: =IFERROR(VLOOKUP(J569, DADOS_RM_EVENTOS_original!E:J, 2, FALSE), "Código não encontrado/Não digitado") -> Código não encontrado/Não digitado | M569: =IFERROR(VLOOKUP(L569, DADOS_RM_EVENTOS_original!K:L, 2, FALSE), "Código não encontrado/Não digitado") -> Código não encontrado/Não digitado
A570: 0004 | B570: 0914 | C570: Reposiçao de Adicional Noturno | D570: P-PROVENTO | E570: 1 | F570: CRIAR EVENTO | G570: =IFERROR(VLOOKUP(F570, DADOS_RM_EVENTOS_original!A:B, 2, FALSE), "Código não encontrado/Não digitado") -> Código não encontrado/Não digitado | I570: =IFERROR(VLOOKUP(H570, DADOS_RM_EVENTOS_original!C:D, 2, FALSE), "Código não encontrado/Não digitado") -> Código não encontrado/Não digitado | K570: =IFERROR(VLOOKUP(J570, DADOS_RM_EVENTOS_original!E:J, 2, FALSE), "Código não encontrado/Não digitado") -> Código não encontrado/Não digitado | M570: =IFERROR(VLOOKUP(L570, DADOS_RM_EVENTOS_original!K:L, 2, FALSE), "Código não encontrado/Não digitado") -> Código não encontrado/Não digitado
A571: 0004 | B571: 0501 | C571: RESC. ANTES DO PRAZO DETERMINADO (DESC.) | D571: D-DESCONTO | E571: 1 | F571: 0514 | G571: =IFERROR(VLOOKUP(F571, DADOS_RM_EVENTOS_original!A:B, 2, FALSE), "Código não encontrado/Não digitado") -> Desc. Artigo 480 - Multa da CLT | I571: =IFERROR(VLOOKUP(H571, DADOS_RM_EVENTOS_original!C:D, 2, FALSE), "Código não encontrado/Não digitado") -> Código não encontrado/Não digitado | K571: =IFERROR(VLOOKUP(J571, DADOS_RM_EVENTOS_original!E:J, 2, FALSE), "Código não encontrado/Não digitado") -> Código não encontrado/Não digitado | M571: =IFERROR(VLOOKUP(L571, DADOS_RM_EVENTOS_original!K:L, 2, FALSE), "Código não encontrado/Não digitado") -> Código não encontrado/Não digitado
A572: 0017 | B572: 0501 | C572: Resc. Antes do Prazo Determinado (Desc.) | D572: D-DESCONTO | E572: 3 | F572: 0514 | G572: =IFERROR(VLOOKUP(F572, DADOS_RM_EVENTOS_original!A:B, 2, FALSE), "Código não encontrado/Não digitado") -> Desc. Artigo 480 - Multa da CLT | I572: =IFERROR(VLOOKUP(H572, DADOS_RM_EVENTOS_original!C:D, 2, FALSE), "Código não encontrado/Não digitado") -> Código não encontrado/Não digitado | K572: =IFERROR(VLOOKUP(J572, DADOS_RM_EVENTOS_original!E:J, 2, FALSE), "Código não encontrado/Não digitado") -> Código não encontrado/Não digitado | M572: =IFERROR(VLOOKUP(L572, DADOS_RM_EVENTOS_original!K:L, 2, FALSE), "Código não encontrado/Não digitado") -> Código não encontrado/Não digitado
A573: 0005 | B573: 0501 | C573: Resc. Antes do Prazo Determinado (Desc.) | D573: D-DESCONTO | E573: 4 | F573: 0514 | G573: =IFERROR(VLOOKUP(F573, DADOS_RM_EVENTOS_original!A:B, 2, FALSE), "Código não encontrado/Não digitado") -> Desc. Artigo 480 - Multa da CLT | I573: =IFERROR(VLOOKUP(H573, DADOS_RM_EVENTOS_original!C:D, 2, FALSE), "Código não encontrado/Não digitado") -> Código não encontrado/Não digitado | K573: =IFERROR(VLOOKUP(J573, DADOS_RM_EVENTOS_original!E:J, 2, FALSE), "Código não encontrado/Não digitado") -> Código não encontrado/Não digitado | M573: =IFERROR(VLOOKUP(L573, DADOS_RM_EVENTOS_original!K:L, 2, FALSE), "Código não encontrado/Não digitado") -> Código não encontrado/Não digitado
A574: 0004 | B574: 0201 | C574: RESC. ANTES DO PRAZO DETERMINADO (PROV.) | D574: P-PROVENTO | E574: 1 | F574: 0171 | G574: =IFERROR(VLOOKUP(F574, DADOS_RM_EVENTOS_original!A:B, 2, FALSE), "Código não encontrado/Não digitado") -> Art 479 - Indenizacao da CLT | I574: =IFERROR(VLOOKUP(H574, DADOS_RM_EVENTOS_original!C:D, 2, FALSE), "Código não encontrado/Não digitado") -> Código não encontrado/Não digitado | K574: =IFERROR(VLOOKUP(J574, DADOS_RM_EVENTOS_original!E:J, 2, FALSE), "Código não encontrado/Não digitado") -> Código não encontrado/Não digitado | M574: =IFERROR(VLOOKUP(L574, DADOS_RM_EVENTOS_original!K:L, 2, FALSE), "Código não encontrado/Não digitado") -> Código não encontrado/Não digitado
A575: 0017 | B575: 0201 | C575: Resc. Antes do Prazo Determinado (Prov.) | D575: P-PROVENTO | E575: 3 | F575: 0171 | G575: =IFERROR(VLOOKUP(F575, DADOS_RM_EVENTOS_original!A:B, 2, FALSE), "Código não encontrado/Não digitado") -> Art 479 - Indenizacao da CLT | I575: =IFERROR(VLOOKUP(H575, DADOS_RM_EVENTOS_original!C:D, 2, FALSE), "Código não encontrado/Não digitado") -> Código não encontrado/Não digitado | K575: =IFERROR(VLOOKUP(J575, DADOS_RM_EVENTOS_original!E:J, 2, FALSE), "Código não encontrado/Não digitado") -> Código não encontrado/Não digitado | M575: =IFERROR(VLOOKUP(L575, DADOS_RM_EVENTOS_original!K:L, 2, FALSE), "Código não encontrado/Não digitado") -> Código não encontrado/Não digitado
A576: 0005 | B576: 0201 | C576: Resc. Antes do Prazo Determinado (Prov.) | D576: P-PROVENTO | E576: 4 | F576: 0171 | G576: =IFERROR(VLOOKUP(F576, DADOS_RM_EVENTOS_original!A:B, 2, FALSE), "Código não encontrado/Não digitado") -> Art 479 - Indenizacao da CLT | I576: =IFERROR(VLOOKUP(H576, DADOS_RM_EVENTOS_original!C:D, 2, FALSE), "Código não encontrado/Não digitado") -> Código não encontrado/Não digitado | K576: =IFERROR(VLOOKUP(J576, DADOS_RM_EVENTOS_original!E:J, 2, FALSE), "Código não encontrado/Não digitado") -> Código não encontrado/Não digitado | M576: =IFERROR(VLOOKUP(L576, DADOS_RM_EVENTOS_original!K:L, 2, FALSE), "Código não encontrado/Não digitado") -> Código não encontrado/Não digitado
... A651: 0022 | B651: 0320 | C651: Vale-Transporte | D651: D-DESCONTO | E651: 6 | F651: 0006 | G651: =IFERROR(VLOOKUP(F651, DADOS_RM_EVENTOS_original!A:B, 2, FALSE), "Código não encontrado/Não digitado") -> Desc. Vale Transporte | I651: =IFERROR(VLOOKUP(H651, DADOS_RM_EVENTOS_original!C:D, 2, FALSE), "Código não encontrado/Não digitado") -> Código não encontrado/Não digitado | K651: =IFERROR(VLOOKUP(J651, DADOS_RM_EVENTOS_original!E:J, 2, FALSE), "Código não encontrado/Não digitado") -> Código não encontrado/Não digitado | M651: =IFERROR(VLOOKUP(L651, DADOS_RM_EVENTOS_original!K:L, 2, FALSE), "Código não encontrado/Não digitado") -> Código não encontrado/Não digitado

Sheet ZDEPARA_EVENTOS
A1: EMPRESA_DE | B1: CODIGO_DE | C1: NOME_DE | D1: TIPO_EVENTO | E1: COLIGADA_PARA | F1: CODIGO_PARA | G1: NOME_RM | H1: CODIGO_PARA_FICHA_MES1 | I1: NOME_RM_1 | J1: CODIGO_PARA_FICHA_MES2 | K1: NOME_RM_2 | L1: CODIGO_PARA_VERBAS_FERIAS | M1: NOME_RM_3
A2: 0004 | B2: 0967 | C2: # 1ª via cartão hapvida | D2: D-DESCONTO | E2: 1 | F2: CRIAR EVENTO | G2: Código não encontrado/Não digitado | I2: =IFERROR(VLOOKUP(H2, DADOS_RM_EVENTOS_original!C:D, 2, FALSE), "Código não encontrado/Não digitado") -> Código não encontrado/Não digitado | K2: =IFERROR(VLOOKUP(J2, DADOS_RM_EVENTOS_original!E:J, 2, FALSE), "Código não encontrado/Não digitado") -> Código não encontrado/Não digitado | M2: =IFERROR(VLOOKUP(L2, DADOS_RM_EVENTOS_original!K:L, 2, FALSE), "Código não encontrado/Não digitado") -> Código não encontrado/Não digitado
A3: 0004 | B3: 0608 | C3: # adiantamento base de cálculo | D3: B-BASE | E3: 1 | F3: NÃO IMPORTAR | G3: Código não encontrado/Não digitado | I3: =IFERROR(VLOOKUP(H3, DADOS_RM_EVENTOS_original!C:D, 2, FALSE), "Código não encontrado/Não digitado") -> Código não encontrado/Não digitado | K3: =IFERROR(VLOOKUP(J3, DADOS_RM_EVENTOS_original!E:J, 2, FALSE), "Código não encontrado/Não digitado") -> Código não encontrado/Não digitado | M3: =IFERROR(VLOOKUP(L3, DADOS_RM_EVENTOS_original!K:L, 2, FALSE), "Código não encontrado/Não digitado") -> Código não encontrado/Não digitado
A4: 0015 | B4: 0151 | C4: # adiantamento de 13º salário (férias) | D4: P-PROVENTO | E4: 2 | F4: 0444 | G4: Antecipacao Primeira Parcela 13º nas Fer | I4: =IFERROR(VLOOKUP(H4, DADOS_RM_EVENTOS_original!C:D, 2, FALSE), "Código não encontrado/Não digitado") -> Código não encontrado/Não digitado | K4: =IFERROR(VLOOKUP(J4, DADOS_RM_EVENTOS_original!E:J, 2, FALSE), "Código não encontrado/Não digitado") -> Código não encontrado/Não digitado | M4: =IFERROR(VLOOKUP(L4, DADOS_RM_EVENTOS_original!K:L, 2, FALSE), "Código não encontrado/Não digitado") -> Código não encontrado/Não digitado
A5: 0004 | B5: 0345 | C5: # adiantamento extra | D5: D-DESCONTO | E5: 1 | F5: 0019 | G5: ( - ) Desc. Adiantamento Salarial | I5: =IFERROR(VLOOKUP(H5, DADOS_RM_EVENTOS_original!C:D, 2, FALSE), "Código não encontrado/Não digitado") -> Código não encontrado/Não digitado | K5: =IFERROR(VLOOKUP(J5, DADOS_RM_EVENTOS_original!E:J, 2, FALSE), "Código não encontrado/Não digitado") -> Código não encontrado/Não digitado | M5: =IFERROR(VLOOKUP(L5, DADOS_RM_EVENTOS_original!K:L, 2, FALSE), "Código não encontrado/Não digitado") -> Código não encontrado/Não digitado
A6: 0004 | B6: 0342 | C6: # almoco | D6: D-DESCONTO | E6: 1 | F6: 0092 | G6: Desc. Vale Alimentacao | I6: =IFERROR(VLOOKUP(H6, DADOS_RM_EVENTOS_original!C:D, 2, FALSE), "Código não encontrado/Não digitado") -> Código não encontrado/Não digitado | K6: =IFERROR(VLOOKUP(J6, DADOS_RM_EVENTOS_original!E:J, 2, FALSE), "Código não encontrado/Não digitado") -> Código não encontrado/Não digitado | M6: =IFERROR(VLOOKUP(L6, DADOS_RM_EVENTOS_original!K:L, 2, FALSE), "Código não encontrado/Não digitado") -> Código não encontrado/Não digitado
A7: 0004 | B7: 0391 | C7: # arredondamento (desconto) | D7: D-DESCONTO | E7: 1 | F7: 0275 | G7: Desc. Arred. Liquido Insufuciente | I7: =IFERROR(VLOOKUP(H7, DADOS_RM_EVENTOS_original!C:D, 2, FALSE), "Código não encontrado/Não digitado") -> Código não encontrado/Não digitado | K7: =IFERROR(VLOOKUP(J7, DADOS_RM_EVENTOS_original!E:J, 2, FALSE), "Código não encontrado/Não digitado") -> Código não encontrado/Não digitado | M7: =IFERROR(VLOOKUP(L7, DADOS_RM_EVENTOS_original!K:L, 2, FALSE), "Código não encontrado/Não digitado") -> Código não encontrado/Não digitado
A8: 0004 | B8: 0091 | C8: # arredondamento (provento) | D8: P-PROVENTO | E8: 1 | F8: 0817 | G8: Arredondamento Liquido Insuficiente | I8: =IFERROR(VLOOKUP(H8, DADOS_RM_EVENTOS_original!C:D, 2, FALSE), "Código não encontrado/Não digitado") -> Código não encontrado/Não digitado | K8: =IFERROR(VLOOKUP(J8, DADOS_RM_EVENTOS_original!E:J, 2, FALSE), "Código não encontrado/Não digitado") -> Código não encontrado/Não digitado | M8: =IFERROR(VLOOKUP(L8, DADOS_RM_EVENTOS_original!K:L, 2, FALSE), "Código não encontrado/Não digitado") -> Código não encontrado/Não digitado
A9: 0004 | B9: 0392 | C9: # arredondamento compensação (desconto) | D9: D-DESCONTO | E9: 1 | F9: 0275 | G9: Desc. Arred. Liquido Insufuciente | I9: =IFERROR(VLOOKUP(H9, DADOS_RM_EVENTOS_original!C:D, 2, FALSE), "Código não encontrado/Não digitado") -> Código não encontrado/Não digitado | K9: =IFERROR(VLOOKUP(J9, DADOS_RM_EVENTOS_original!E:J, 2, FALSE), "Código não encontrado/Não digitado") -> Código não encontrado/Não digitado | M9: =IFERROR(VLOOKUP(L9, DADOS_RM_EVENTOS_original!K:L, 2, FALSE), "Código não encontrado/Não digitado") -> Código não encontrado/Não digitado
A10: 0004 | B10: 0170 | C10: # complemento de 13º salário | D10: P-PROVENTO | E10: 1 | F10: 0839 | G10: Dif. 13º Salario (Janeiro) | I10: =IFERROR(VLOOKUP(H10, DADOS_RM_EVENTOS_original!C:D, 2, FALSE), "Código não encontrado/Não digitado") -> Código não encontrado/Não digitado | K10: =IFERROR(VLOOKUP(J10, DADOS_RM_EVENTOS_original!E:J, 2, FALSE), "Código não encontrado/Não digitado") -> Código não encontrado/Não digitado | M10: =IFERROR(VLOOKUP(L10, DADOS_RM_EVENTOS_original!K:L, 2, FALSE), "Código não encontrado/Não digitado") -> Código não encontrado/Não digitado
A11: 0004 | B11: 0338 | C11: # contribuicao sindical mensal | D11: D-DESCONTO | E11: 1 | F11: 0201 | G11: Desc. Mensalidade Sindical | I11: =IFERROR(VLOOKUP(H11, DADOS_RM_EVENTOS_original!C:D, 2, FALSE), "Código não encontrado/Não digitado") -> Código não encontrado/Não digitado | K11: =IFERROR(VLOOKUP(J11, DADOS_RM_EVENTOS_original!E:J, 2, FALSE), "Código não encontrado/Não digitado") -> Código não encontrado/Não digitado | M11: =IFERROR(VLOOKUP(L11, DADOS_RM_EVENTOS_original!K:L, 2, FALSE), "Código não encontrado/Não digitado") -> Código não encontrado/Não digitado
A12: 0004 | B12: 0221 | C12: # desc cartao vale transporte eletronico | D12: D-DESCONTO | E12: 1 | F12: 0047 | G12: Desc. 2a via PASSCARD | I12: =IFERROR(VLOOKUP(H12, DADOS_RM_EVENTOS_original!C:D, 2, FALSE), "Código não encontrado/Não digitado") -> Código não encontrado/Não digitado | K12: =IFERROR(VLOOKUP(J12, DADOS_RM_EVENTOS_original!E:J, 2, FALSE), "Código não encontrado/Não digitado") -> Código não encontrado/Não digitado | M12: =IFERROR(VLOOKUP(L12, DADOS_RM_EVENTOS_original!K:L, 2, FALSE), "Código não encontrado/Não digitado") -> Código não encontrado/Não digitado
A13: 0004 | B13: 0139 | C13: # devol.contribuicao sindical | D13: P-PROVENTO | E13: 1 | F13: 0324 | G13: Reembolso de Contribuicao Sindical | I13: =IFERROR(VLOOKUP(H13, DADOS_RM_EVENTOS_original!C:D, 2, FALSE), "Código não encontrado/Não digitado") -> Código não encontrado/Não digitado | K13: =IFERROR(VLOOKUP(J13, DADOS_RM_EVENTOS_original!E:J, 2, FALSE), "Código não encontrado/Não digitado") -> Código não encontrado/Não digitado | M13: =IFERROR(VLOOKUP(L13, DADOS_RM_EVENTOS_original!K:L, 2, FALSE), "Código não encontrado/Não digitado") -> Código não encontrado/Não digitado
... A56: 0012 | B56: 0967 | C56: 1/3 de Abono Pecuniário | D56: P-PROVENTO | E56: 5 | F56: 0056 | G56: 1/3 Abono de Ferias | I56: =IFERROR(VLOOKUP(H56, DADOS_RM_EVENTOS_original!C:D, 2, FALSE), "Código não encontrado/Não digitado") -> Código não encontrado/Não digitado | K56: =IFERROR(VLOOKUP(J56, DADOS_RM_EVENTOS_original!E:J, 2, FALSE), "Código não encontrado/Não digitado") -> Código não encontrado/Não digitado | M56: =IFERROR(VLOOKUP(L56, DADOS_RM_EVENTOS_original!K:L, 2, FALSE), "Código não encontrado/Não digitado") -> Código não encontrado/Não digitado
A57: 0004 | B57: 0111 | C57: 1/3 DE FÉRIAS | D57: P-PROVENTO | E57: 1 | F57: 0076 | G57: 1/3 Ferias no Mes | H57: 0076 | I57: =IFERROR(VLOOKUP(H57, DADOS_RM_EVENTOS_original!A:D, 2, FALSE), "Código não encontrado/Não digitado") -> 1/3 Ferias no Mes | J57: 0077 | K57: =IFERROR(VLOOKUP(J57, DADOS_RM_EVENTOS_original!A:J, 2, FALSE), "Código não encontrado/Não digitado") -> 1/3 Ferias no Proximo Mes | L57: 0040 | M57: =IFERROR(VLOOKUP(L57, DADOS_RM_EVENTOS_original!A:L, 2, FALSE), "Código não encontrado/Não digitado") -> 1/3 de Ferias (Recibo)
A58: 0015 | B58: 0111 | C58: 1/3 DE FÉRIAS | D58: P-PROVENTO | E58: 2 | F58: 0076 | G58: 1/3 Ferias no Mes | H58: 0076 | I58: =IFERROR(VLOOKUP(H58, DADOS_RM_EVENTOS_original!A:D, 2, FALSE), "Código não encontrado/Não digitado") -> 1/3 Ferias no Mes | J58: 0077 | K58: =IFERROR(VLOOKUP(J58, DADOS_RM_EVENTOS_original!A:J, 2, FALSE), "Código não encontrado/Não digitado") -> 1/3 Ferias no Proximo Mes | L58: 0040 | M58: =IFERROR(VLOOKUP(L58, DADOS_RM_EVENTOS_original!A:L, 2, FALSE), "Código não encontrado/Não digitado") -> 1/3 de Ferias (Recibo)
A59: 0017 | B59: 0111 | C59: 1/3 de Férias | D59: P-PROVENTO | E59: 3 | F59: 0076 | G59: 1/3 Ferias no Mes | H59: 0076 | I59: =IFERROR(VLOOKUP(H59, DADOS_RM_EVENTOS_original!A:D, 2, FALSE), "Código não encontrado/Não digitado") -> 1/3 Ferias no Mes | J59: 0077 | K59: =IFERROR(VLOOKUP(J59, DADOS_RM_EVENTOS_original!A:J, 2, FALSE), "Código não encontrado/Não digitado") -> 1/3 Ferias no Proximo Mes | L59: 0040 | M59: =IFERROR(VLOOKUP(L59, DADOS_RM_EVENTOS_original!A:L, 2, FALSE), "Código não encontrado/Não digitado") -> 1/3 de Ferias (Recibo)
A60: 0005 | B60: 0111 | C60: 1/3 de Férias | D60: P-PROVENTO | E60: 4 | F60: 0076 | G60: 1/3 Ferias no Mes | H60: 0076 | I60: =IFERROR(VLOOKUP(H60, DADOS_RM_EVENTOS_original!A:D, 2, FALSE), "Código não encontrado/Não digitado") -> 1/3 Ferias no Mes | J60: 0077 | K60: =IFERROR(VLOOKUP(J60, DADOS_RM_EVENTOS_original!A:J, 2, FALSE), "Código não encontrado/Não digitado") -> 1/3 Ferias no Proximo Mes | L60: 0040 | M60: =IFERROR(VLOOKUP(L60, DADOS_RM_EVENTOS_original!A:L, 2, FALSE), "Código não encontrado/Não digitado") -> 1/3 de Ferias (Recibo)
A61: 0012 | B61: 0111 | C61: 1/3 de Férias | D61: P-PROVENTO | E61: 5 | F61: 0076 | G61: 1/3 Ferias no Mes | H61: 0076 | I61: =IFERROR(VLOOKUP(H61, DADOS_RM_EVENTOS_original!A:D, 2, FALSE), "Código não encontrado/Não digitado") -> 1/3 Ferias no Mes | J61: 0077 | K61: =IFERROR(VLOOKUP(J61, DADOS_RM_EVENTOS_original!A:J, 2, FALSE), "Código não encontrado/Não digitado") -> 1/3 Ferias no Proximo Mes | L61: 0040 | M61: =IFERROR(VLOOKUP(L61, DADOS_RM_EVENTOS_original!A:L, 2, FALSE), "Código não encontrado/Não digitado") -> 1/3 de Ferias (Recibo)
A62: 0022 | B62: 0111 | C62: 1/3 de Férias | D62: P-PROVENTO | E62: 6 | F62: 0076 | G62: 1/3 Ferias no Mes | H62: 0076 | I62: =IFERROR(VLOOKUP(H62, DADOS_RM_EVENTOS_original!A:D, 2, FALSE), "Código não encontrado/Não digitado") -> 1/3 Ferias no Mes | J62: 0077 | K62: =IFERROR(VLOOKUP(J62, DADOS_RM_EVENTOS_original!A:J, 2, FALSE), "Código não encontrado/Não digitado") -> 1/3 Ferias no Proximo Mes | L62: 0040 | M62: =IFERROR(VLOOKUP(L62, DADOS_RM_EVENTOS_original!A:L, 2, FALSE), "Código não encontrado/Não digitado") -> 1/3 de Ferias (Recibo)
A63: 0004 | B63: 0207 | C63: 1/3 DE FÉRIAS (RESCISÃO) | D63: P-PROVENTO | E63: 1 | F63: 0063 | G63: 1/3 Ferias Rescisao | I63: =IFERROR(VLOOKUP(H63, DADOS_RM_EVENTOS_original!C:D, 2, FALSE), "Código não encontrado/Não digitado") -> Código não encontrado/Não digitado | K63: =IFERROR(VLOOKUP(J63, DADOS_RM_EVENTOS_original!E:J, 2, FALSE), "Código não encontrado/Não digitado") -> Código não encontrado/Não digitado | M63: =IFERROR(VLOOKUP(L63, DADOS_RM_EVENTOS_original!K:L, 2, FALSE), "Código não encontrado/Não digitado") -> Código não encontrado/Não digitado
A64: 0005 | B64: 0207 | C64: 1/3 de Férias (Rescisão) | D64: P-PROVENTO | E64: 4 | F64: 0063 | G64: 1/3 Ferias Rescisao | I64: =IFERROR(VLOOKUP(H64, DADOS_RM_EVENTOS_original!C:D, 2, FALSE), "Código não encontrado/Não digitado") -> Código não encontrado/Não digitado | K64: =IFERROR(VLOOKUP(J64, DADOS_RM_EVENTOS_original!E:J, 2, FALSE), "Código não encontrado/Não digitado") -> Código não encontrado/Não digitado | M64: =IFERROR(VLOOKUP(L64, DADOS_RM_EVENTOS_original!K:L, 2, FALSE), "Código não encontrado/Não digitado") -> Código não encontrado/Não digitado
A65: 0012 | B65: 0207 | C65: 1/3 de Férias (Rescisão) | D65: P-PROVENTO | E65: 5 | F65: 0063 | G65: 1/3 Ferias Rescisao | I65: =IFERROR(VLOOKUP(H65, DADOS_RM_EVENTOS_original!C:D, 2, FALSE), "Código não encontrado/Não digitado") -> Código não encontrado/Não digitado | K65: =IFERROR(VLOOKUP(J65, DADOS_RM_EVENTOS_original!E:J, 2, FALSE), "Código não encontrado/Não digitado") -> Código não encontrado/Não digitado | M65: =IFERROR(VLOOKUP(L65, DADOS_RM_EVENTOS_original!K:L, 2, FALSE), "Código não encontrado/Não digitado") -> Código não encontrado/Não digitado
A66: 0004 | B66: 0987 | C66: 1/3 de Férias Indenizadas | D66: P-PROVENTO | E66: 1 | F66: 0063 | G66: 1/3 Ferias Rescisao | I66: =IFERROR(VLOOKUP(H66, DADOS_RM_EVENTOS_original!C:D, 2, FALSE), "Código não encontrado/Não digitado") -> Código não encontrado/Não digitado | K66: =IFERROR(VLOOKUP(J66, DADOS_RM_EVENTOS_original!E:J, 2, FALSE), "Código não encontrado/Não digitado") -> Código não encontrado/Não digitado | M66: =IFERROR(VLOOKUP(L66, DADOS_RM_EVENTOS_original!K:L, 2, FALSE), "Código não encontrado/Não digitado") -> Código não encontrado/Não digitado
A67: 0017 | B67: 0968 | C67: 1/3 de Férias Proporcionais | D67: P-PROVENTO | E67: 3 | F67: 0063 | G67: 1/3 Ferias Rescisao | I67: =IFERROR(VLOOKUP(H67, DADOS_RM_EVENTOS_original!C:D, 2, FALSE), "Código não encontrado/Não digitado") -> Código não encontrado/Não digitado | K67: =IFERROR(VLOOKUP(J67, DADOS_RM_EVENTOS_original!E:J, 2, FALSE), "Código não encontrado/Não digitado") -> Código não encontrado/Não digitado | M67: =IFERROR(VLOOKUP(L67, DADOS_RM_EVENTOS_original!K:L, 2, FALSE), "Código não encontrado/Não digitado") -> Código não encontrado/Não digitado
A68: 0005 | B68: 0960 | C68: 1/3 de Férias Proporcionais | D68: P-PROVENTO | E68: 4 | F68: 0063 | G68: 1/3 Ferias Rescisao | I68: =IFERROR(VLOOKUP(H68, DADOS_RM_EVENTOS_original!C:D, 2, FALSE), "Código não encontrado/Não digitado") -> Código não encontrado/Não digitado | K68: =IFERROR(VLOOKUP(J68, DADOS_RM_EVENTOS_original!E:J, 2, FALSE), "Código não encontrado/Não digitado") -> Código não encontrado/Não digitado | M68: =IFERROR(VLOOKUP(L68, DADOS_RM_EVENTOS_original!K:L, 2, FALSE), "Código não encontrado/Não digitado") -> Código não encontrado/Não digitado
A69: 0012 | B69: 0959 | C69: 1/3 de Férias Proporcionais | D69: P-PROVENTO | E69: 5 | F69: 0063 | G69: 1/3 Ferias Rescisao | I69: =IFERROR(VLOOKUP(H69, DADOS_RM_EVENTOS_original!C:D, 2, FALSE), "Código não encontrado/Não digitado") -> Código não encontrado/Não digitado | K69: =IFERROR(VLOOKUP(J69, DADOS_RM_EVENTOS_original!E:J, 2, FALSE), "Código não encontrado/Não digitado") -> Código não encontrado/Não digitado | M69: =IFERROR(VLOOKUP(L69, DADOS_RM_EVENTOS_original!K:L, 2, FALSE), "Código não encontrado/Não digitado") -> Código não encontrado/Não digitado
A70: 0022 | B70: 0212 | C70: 1/3 de Férias Proporcionais | D70: P-PROVENTO | E70: 6 | F70: 0063 | G70: 1/3 Ferias Rescisao | I70: =IFERROR(VLOOKUP(H70, DADOS_RM_EVENTOS_original!C:D, 2, FALSE), "Código não encontrado/Não digitado") -> Código não encontrado/Não digitado | K70: =IFERROR(VLOOKUP(J70, DADOS_RM_EVENTOS_original!E:J, 2, FALSE), "Código não encontrado/Não digitado") -> Código não encontrado/Não digitado | M70: =IFERROR(VLOOKUP(L70, DADOS_RM_EVENTOS_original!K:L, 2, FALSE), "Código não encontrado/Não digitado") -> Código não encontrado/Não digitado
A71: 0004 | B71: 0973 | C71: 1/3 de Férias Proporcionais 1 | D71: P-PROVENTO | E71: 1 | F71: 0063 | G71: 1/3 Ferias Rescisao | I71: =IFERROR(VLOOKUP(H71, DADOS_RM_EVENTOS_original!C:D, 2, FALSE), "Código não encontrado/Não digitado") -> Código não encontrado/Não digitado | K71: =IFERROR(VLOOKUP(J71, DADOS_RM_EVENTOS_original!E:J, 2, FALSE), "Código não encontrado/Não digitado") -> Código não encontrado/Não digitado | M71: =IFERROR(VLOOKUP(L71, DADOS_RM_EVENTOS_original!K:L, 2, FALSE), "Código não encontrado/Não digitado") -> Código não encontrado/Não digitado
A72: 0015 | B72: 0973 | C72: 1/3 de Férias Proporcionais 1 | D72: P-PROVENTO | E72: 2 | F72: 0063 | G72: 1/3 Ferias Rescisao | I72: =IFERROR(VLOOKUP(H72, DADOS_RM_EVENTOS_original!C:D, 2, FALSE), "Código não encontrado/Não digitado") -> Código não encontrado/Não digitado | K72: =IFERROR(VLOOKUP(J72, DADOS_RM_EVENTOS_original!E:J, 2, FALSE), "Código não encontrado/Não digitado") -> Código não encontrado/Não digitado | M72: =IFERROR(VLOOKUP(L72, DADOS_RM_EVENTOS_original!K:L, 2, FALSE), "Código não encontrado/Não digitado") -> Código não encontrado/Não digitado
A73: 0017 | B73: 0969 | C73: 1/3 de Férias Vencidas | D73: P-PROVENTO | E73: 3 | F73: 0803 | G73: Adicional 1/3 Ferias Vencidas | I73: =IFERROR(VLOOKUP(H73, DADOS_RM_EVENTOS_original!C:D, 2, FALSE), "Código não encontrado/Não digitado") -> Código não encontrado/Não digitado | K73: =IFERROR(VLOOKUP(J73, DADOS_RM_EVENTOS_original!E:J, 2, FALSE), "Código não encontrado/Não digitado") -> Código não encontrado/Não digitado | M73: =IFERROR(VLOOKUP(L73, DADOS_RM_EVENTOS_original!K:L, 2, FALSE), "Código não encontrado/Não digitado") -> Código não encontrado/Não digitado
A74: 0005 | B74: 0961 | C74: 1/3 de Férias Vencidas | D74: P-PROVENTO | E74: 4 | F74: 0803 | G74: Adicional 1/3 Ferias Vencidas | I74: =IFERROR(VLOOKUP(H74, DADOS_RM_EVENTOS_original!C:D, 2, FALSE), "Código não encontrado/Não digitado") -> Código não encontrado/Não digitado | K74: =IFERROR(VLOOKUP(J74, DADOS_RM_EVENTOS_original!E:J, 2, FALSE), "Código não encontrado/Não digitado") -> Código não encontrado/Não digitado | M74: =IFERROR(VLOOKUP(L74, DADOS_RM_EVENTOS_original!K:L, 2, FALSE), "Código não encontrado/Não digitado") -> Código não encontrado/Não digitado
... A558: 0012 | B558: 0949 | C558: Refeição Mês Anterior | D558: P-PROVENTO | E558: 5 | F558: 0147 | G558: Reembolso Desc. Vale Refeicao | I558: =IFERROR(VLOOKUP(H558, DADOS_RM_EVENTOS_original!C:D, 2, FALSE), "Código não encontrado/Não digitado") -> Código não encontrado/Não digitado | K558: =IFERROR(VLOOKUP(J558, DADOS_RM_EVENTOS_original!E:J, 2, FALSE), "Código não encontrado/Não digitado") -> Código não encontrado/Não digitado | M558: =IFERROR(VLOOKUP(L558, DADOS_RM_EVENTOS_original!K:L, 2, FALSE), "Código não encontrado/Não digitado") -> Código não encontrado/Não digitado
A559: 0004 | B559: 0110 | C559: REMUNERAÇÃO DE FÉRIAS | D559: P-PROVENTO | E559: 1 | F559: 0041 | G559: Ferias no Mes | H559: 0041 | I559: =IFERROR(VLOOKUP(H559, DADOS_RM_EVENTOS_original!A:D, 2, FALSE), "Código não encontrado/Não digitado") -> Ferias no Mes | J559: 0042 | K559: =IFERROR(VLOOKUP(J559, DADOS_RM_EVENTOS_original!A:J, 2, FALSE), "Código não encontrado/Não digitado") -> Ferias no Proximo Mes | L559: 0038 | M559: =IFERROR(VLOOKUP(L559, DADOS_RM_EVENTOS_original!A:L, 2, FALSE), "Código não encontrado/Não digitado") -> Dias de Ferias (Recibo)
A560: 0015 | B560: 0110 | C560: REMUNERAÇÃO DE FÉRIAS | D560: P-PROVENTO | E560: 2 | F560: 0041 | G560: Ferias no Mes | H560: 0041 | I560: =IFERROR(VLOOKUP(H560, DADOS_RM_EVENTOS_original!A:D, 2, FALSE), "Código não encontrado/Não digitado") -> Ferias no Mes | J560: 0042 | K560: =IFERROR(VLOOKUP(J560, DADOS_RM_EVENTOS_original!A:J, 2, FALSE), "Código não encontrado/Não digitado") -> Ferias no Proximo Mes | L560: 0038 | M560: =IFERROR(VLOOKUP(L560, DADOS_RM_EVENTOS_original!A:L, 2, FALSE), "Código não encontrado/Não digitado") -> Dias de Ferias (Recibo)
A561: 0017 | B561: 0110 | C561: Remuneração de Férias | D561: P-PROVENTO | E561: 3 | F561: 0016 | G561: Provento ferias | I561: =IFERROR(VLOOKUP(H561, DADOS_RM_EVENTOS_original!C:D, 2, FALSE), "Código não encontrado/Não digitado") -> Código não encontrado/Não digitado | K561: =IFERROR(VLOOKUP(J561, DADOS_RM_EVENTOS_original!E:J, 2, FALSE), "Código não encontrado/Não digitado") -> Código não encontrado/Não digitado | M561: =IFERROR(VLOOKUP(L561, DADOS_RM_EVENTOS_original!K:L, 2, FALSE), "Código não encontrado/Não digitado") -> Código não encontrado/Não digitado
A562: 0005 | B562: 0110 | C562: Remuneração de Férias | D562: P-PROVENTO | E562: 4 | F562: 0041 | G562: Ferias no Mes | H562: 0041 | I562: =IFERROR(VLOOKUP(H562, DADOS_RM_EVENTOS_original!A:D, 2, FALSE), "Código não encontrado/Não digitado") -> Ferias no Mes | J562: 0042 | K562: =IFERROR(VLOOKUP(J562, DADOS_RM_EVENTOS_original!A:J, 2, FALSE), "Código não encontrado/Não digitado") -> Ferias no Proximo Mes | L562: 0038 | M562: =IFERROR(VLOOKUP(L562, DADOS_RM_EVENTOS_original!A:L, 2, FALSE), "Código não encontrado/Não digitado") -> Dias de Ferias (Recibo)
A563: 0012 | B563: 0110 | C563: Remuneração de Férias | D563: P-PROVENTO | E563: 5 | F563: 0041 | G563: Ferias no Mes | H563: 0041 | I563: =IFERROR(VLOOKUP(H563, DADOS_RM_EVENTOS_original!A:D, 2, FALSE), "Código não encontrado/Não digitado") -> Ferias no Mes | J563: 0042 | K563: =IFERROR(VLOOKUP(J563, DADOS_RM_EVENTOS_original!A:J, 2, FALSE), "Código não encontrado/Não digitado") -> Ferias no Proximo Mes | L563: 0038 | M563: =IFERROR(VLOOKUP(L563, DADOS_RM_EVENTOS_original!A:L, 2, FALSE), "Código não encontrado/Não digitado") -> Dias de Ferias (Recibo)
A564: 0022 | B564: 0110 | C564: Remuneração de Férias | D564: P-PROVENTO | E564: 6 | F564: 0041 | G564: Ferias no Mes | H564: 0041 | I564: =IFERROR(VLOOKUP(H564, DADOS_RM_EVENTOS_original!A:D, 2, FALSE), "Código não encontrado/Não digitado") -> Ferias no Mes | J564: 0042 | K564: =IFERROR(VLOOKUP(J564, DADOS_RM_EVENTOS_original!A:J, 2, FALSE), "Código não encontrado/Não digitado") -> Ferias no Proximo Mes | L564: 0038 | M564: =IFERROR(VLOOKUP(L564, DADOS_RM_EVENTOS_original!A:L, 2, FALSE), "Código não encontrado/Não digitado") -> Dias de Ferias (Recibo)
A565: 0004 | B565: 0112 | C565: REMUNERAÇÃO DE FÉRIAS EM DOBRO | D565: P-PROVENTO | E565: 1 | F565: 0240 | G565: Ferias em Dobro | I565: =IFERROR(VLOOKUP(H565, DADOS_RM_EVENTOS_original!C:D, 2, FALSE), "Código não encontrado/Não digitado") -> Código não encontrado/Não digitado | K565: =IFERROR(VLOOKUP(J565, DADOS_RM_EVENTOS_original!E:J, 2, FALSE), "Código não encontrado/Não digitado") -> Código não encontrado/Não digitado | M565: =IFERROR(VLOOKUP(L565, DADOS_RM_EVENTOS_original!K:L, 2, FALSE), "Código não encontrado/Não digitado") -> Código não encontrado/Não digitado
A566: 0017 | B566: 0601 | C566: Remuneração Fixa | D566: B-BASE | E566: 3 | F566: NÃO IMPORTAR | G566: Código não encontrado/Não digitado | I566: =IFERROR(VLOOKUP(H566, DADOS_RM_EVENTOS_original!C:D, 2, FALSE), "Código não encontrado/Não digitado") -> Código não encontrado/Não digitado | K566: =IFERROR(VLOOKUP(J566, DADOS_RM_EVENTOS_original!E:J, 2, FALSE), "Código não encontrado/Não digitado") -> Código não encontrado/Não digitado | M566: =IFERROR(VLOOKUP(L566, DADOS_RM_EVENTOS_original!K:L, 2, FALSE), "Código não encontrado/Não digitado") -> Código não encontrado/Não digitado
A567: 0005 | B567: 0601 | C567: Remuneração Fixa | D567: B-BASE | E567: 4 | F567: NÃO IMPORTAR | G567: Código não encontrado/Não digitado | I567: =IFERROR(VLOOKUP(H567, DADOS_RM_EVENTOS_original!C:D, 2, FALSE), "Código não encontrado/Não digitado") -> Código não encontrado/Não digitado | K567: =IFERROR(VLOOKUP(J567, DADOS_RM_EVENTOS_original!E:J, 2, FALSE), "Código não encontrado/Não digitado") -> Código não encontrado/Não digitado | M567: =IFERROR(VLOOKUP(L567, DADOS_RM_EVENTOS_original!K:L, 2, FALSE), "Código não encontrado/Não digitado") -> Código não encontrado/Não digitado
A568: 0012 | B568: 0601 | C568: Remuneração Fixa | D568: B-BASE | E568: 5 | F568: NÃO IMPORTAR | G568: Código não encontrado/Não digitado | I568: =IFERROR(VLOOKUP(H568, DADOS_RM_EVENTOS_original!C:D, 2, FALSE), "Código não encontrado/Não digitado") -> Código não encontrado/Não digitado | K568: =IFERROR(VLOOKUP(J568, DADOS_RM_EVENTOS_original!E:J, 2, FALSE), "Código não encontrado/Não digitado") -> Código não encontrado/Não digitado | M568: =IFERROR(VLOOKUP(L568, DADOS_RM_EVENTOS_original!K:L, 2, FALSE), "Código não encontrado/Não digitado") -> Código não encontrado/Não digitado
A569: 0022 | B569: 0601 | C569: Remuneração Fixa | D569: B-BASE | E569: 6 | F569: NÃO IMPORTAR | G569: Código não encontrado/Não digitado | I569: =IFERROR(VLOOKUP(H569, DADOS_RM_EVENTOS_original!C:D, 2, FALSE), "Código não encontrado/Não digitado") -> Código não encontrado/Não digitado | K569: =IFERROR(VLOOKUP(J569, DADOS_RM_EVENTOS_original!E:J, 2, FALSE), "Código não encontrado/Não digitado") -> Código não encontrado/Não digitado | M569: =IFERROR(VLOOKUP(L569, DADOS_RM_EVENTOS_original!K:L, 2, FALSE), "Código não encontrado/Não digitado") -> Código não encontrado/Não digitado
A570: 0004 | B570: 0914 | C570: Reposiçao de Adicional Noturno | D570: P-PROVENTO | E570: 1 | F570: CRIAR EVENTO | G570: Código não encontrado/Não digitado | I570: =IFERROR(VLOOKUP(H570, DADOS_RM_EVENTOS_original!C:D, 2, FALSE), "Código não encontrado/Não digitado") -> Código não encontrado/Não digitado | K570: =IFERROR(VLOOKUP(J570, DADOS_RM_EVENTOS_original!E:J, 2, FALSE), "Código não encontrado/Não digitado") -> Código não encontrado/Não digitado | M570: =IFERROR(VLOOKUP(L570, DADOS_RM_EVENTOS_original!K:L, 2, FALSE), "Código não encontrado/Não digitado") -> Código não encontrado/Não digitado
A571: 0004 | B571: 0501 | C571: RESC. ANTES DO PRAZO DETERMINADO (DESC.) | D571: D-DESCONTO | E571: 1 | F571: 0514 | G571: Desc. Artigo 480 - Multa da CLT | I571: =IFERROR(VLOOKUP(H571, DADOS_RM_EVENTOS_original!C:D, 2, FALSE), "Código não encontrado/Não digitado") -> Código não encontrado/Não digitado | K571: =IFERROR(VLOOKUP(J571, DADOS_RM_EVENTOS_original!E:J, 2, FALSE), "Código não encontrado/Não digitado") -> Código não encontrado/Não digitado | M571: =IFERROR(VLOOKUP(L571, DADOS_RM_EVENTOS_original!K:L, 2, FALSE), "Código não encontrado/Não digitado") -> Código não encontrado/Não digitado
A572: 0017 | B572: 0501 | C572: Resc. Antes do Prazo Determinado (Desc.) | D572: D-DESCONTO | E572: 3 | F572: 0514 | G572: Desc. Artigo 480 - Multa da CLT | I572: =IFERROR(VLOOKUP(H572, DADOS_RM_EVENTOS_original!C:D, 2, FALSE), "Código não encontrado/Não digitado") -> Código não encontrado/Não digitado | K572: =IFERROR(VLOOKUP(J572, DADOS_RM_EVENTOS_original!E:J, 2, FALSE), "Código não encontrado/Não digitado") -> Código não encontrado/Não digitado | M572: =IFERROR(VLOOKUP(L572, DADOS_RM_EVENTOS_original!K:L, 2, FALSE), "Código não encontrado/Não digitado") -> Código não encontrado/Não digitado
A573: 0005 | B573: 0501 | C573: Resc. Antes do Prazo Determinado (Desc.) | D573: D-DESCONTO | E573: 4 | F573: 0514 | G573: Desc. Artigo 480 - Multa da CLT | I573: =IFERROR(VLOOKUP(H573, DADOS_RM_EVENTOS_original!C:D, 2, FALSE), "Código não encontrado/Não digitado") -> Código não encontrado/Não digitado | K573: =IFERROR(VLOOKUP(J573, DADOS_RM_EVENTOS_original!E:J, 2, FALSE), "Código não encontrado/Não digitado") -> Código não encontrado/Não digitado | M573: =IFERROR(VLOOKUP(L573, DADOS_RM_EVENTOS_original!K:L, 2, FALSE), "Código não encontrado/Não digitado") -> Código não encontrado/Não digitado
A574: 0004 | B574: 0201 | C574: RESC. ANTES DO PRAZO DETERMINADO (PROV.) | D574: P-PROVENTO | E574: 1 | F574: 0171 | G574: Art 479 - Indenizacao da CLT | I574: =IFERROR(VLOOKUP(H574, DADOS_RM_EVENTOS_original!C:D, 2, FALSE), "Código não encontrado/Não digitado") -> Código não encontrado/Não digitado | K574: =IFERROR(VLOOKUP(J574, DADOS_RM_EVENTOS_original!E:J, 2, FALSE), "Código não encontrado/Não digitado") -> Código não encontrado/Não digitado | M574: =IFERROR(VLOOKUP(L574, DADOS_RM_EVENTOS_original!K:L, 2, FALSE), "Código não encontrado/Não digitado") -> Código não encontrado/Não digitado
A575: 0017 | B575: 0201 | C575: Resc. Antes do Prazo Determinado (Prov.) | D575: P-PROVENTO | E575: 3 | F575: 0171 | G575: Art 479 - Indenizacao da CLT | I575: =IFERROR(VLOOKUP(H575, DADOS_RM_EVENTOS_original!C:D, 2, FALSE), "Código não encontrado/Não digitado") -> Código não encontrado/Não digitado | K575: =IFERROR(VLOOKUP(J575, DADOS_RM_EVENTOS_original!E:J, 2, FALSE), "Código não encontrado/Não digitado") -> Código não encontrado/Não digitado | M575: =IFERROR(VLOOKUP(L575, DADOS_RM_EVENTOS_original!K:L, 2, FALSE), "Código não encontrado/Não digitado") -> Código não encontrado/Não digitado
A576: 0005 | B576: 0201 | C576: Resc. Antes do Prazo Determinado (Prov.) | D576: P-PROVENTO | E576: 4 | F576: 0171 | G576: Art 479 - Indenizacao da CLT | I576: =IFERROR(VLOOKUP(H576, DADOS_RM_EVENTOS_original!C:D, 2, FALSE), "Código não encontrado/Não digitado") -> Código não encontrado/Não digitado | K576: =IFERROR(VLOOKUP(J576, DADOS_RM_EVENTOS_original!E:J, 2, FALSE), "Código não encontrado/Não digitado") -> Código não encontrado/Não digitado | M576: =IFERROR(VLOOKUP(L576, DADOS_RM_EVENTOS_original!K:L, 2, FALSE), "Código não encontrado/Não digitado") -> Código não encontrado/Não digitado
... A651: 0022 | B651: 0320 | C651: Vale-Transporte | D651: D-DESCONTO | E651: 6 | F651: 0006 | G651: Desc. Vale Transporte | I651: =IFERROR(VLOOKUP(H651, DADOS_RM_EVENTOS_original!C:D, 2, FALSE), "Código não encontrado/Não digitado") -> Código não encontrado/Não digitado | K651: =IFERROR(VLOOKUP(J651, DADOS_RM_EVENTOS_original!E:J, 2, FALSE), "Código não encontrado/Não digitado") -> Código não encontrado/Não digitado | M651: =IFERROR(VLOOKUP(L651, DADOS_RM_EVENTOS_original!K:L, 2, FALSE), "Código não encontrado/Não digitado") -> Código não encontrado/Não digitado

Sheet DADOS_RM_EVENTOS
A1: CODIGO | B1: DESCRICAO | C1: TIPOEVENTO | D1: VALHORDIAREF | E1: NAT_ESOCIAL
A2: CODIGO | B2: DESCRICAO | C2: PROVDESCBASE | D2: VALHORDIAREF | E2: NATRUBRICA_DESCRICAO
A3: 0001 | B3: SALARIO BASE EM HORAS | C3: P | D3: H | E3: 1000 - Salário, vencimento, soldo
A4: 0002 | B4: SALARIO BASE EM DIAS | C4: P | D4: D | E4: 1000 - Salário, vencimento, soldo
A5: 0003 | B5: DESC. INSS SEGURADO | C5: D | D5: V | E5: 9201 - Contribuição Previdenciária
A6: 0004 | B6: DESC. IRRF NA FONTE | C6: D | D6: V | E6: 9203 - Imposto de renda retido na fonte
A7: 0005 | B7: COTA DE SALARIO FAMILIA | C7: P | D7: V | E7: 1409 - Salário família
A8: 0006 | B8: DESC. VALE TRANSPORTE | C8: D | D8: V | E8: 9216 - Desconto de valetransporte
A9: 0007 | B9: ADICIONAL DE PENOSIDADE | C9: P | D9: V | E9: 1214 - Adicional de penosidade
A10: 0008 | B10: DESC. FALTAS (EM DIAS) | C10: D | D10: D | E10: 9209 - Faltas ou atrasos
A11: 0009 | B11: 1ª PARCELA 13º SALARIO | C11: P | D11: V | E11: 5504 - 13º salário ¿ Adiantamento
A12: 0010 | B12: REFLEXO SOBRE ESCALA | C12: P | D12: V | E12: 1012 - Descanso semanal remunerado - DSR e feriado
... A880: 1024 | B880: DEVOLUCAO RECEBIMENTO INDEVIDO(D) | C880: D | D880: V | E880: 9299 - Outros descontos
A1320: NI | B1320: NAO IMPORTAR | C1320: NI
A1321: VC | B1321: VER COM CLIENTE | C1321: VC
A1322: CRIAR | B1322: CRIAR | C1322: CRIAR

Sheet CRIAR_EVENTOS
A1: NOME_DE | B1: TIPO_EVENTO | C1: PARA_EVENTO | D1: PARA_EVENTO
A2: # 1ª VIA CARTÃO HAPVIDA | B2: D-DESCONTO | C2: 1025 | D2: # 1ª VIA CARTÃO HAPVIDA
A3: # OUTROS (PROVENTO) | B3: P-PROVENTO | C3: 1026 | D3: OUTROS PROVENTOS
A4: # TRANSPORTE/ALIMENTACAO | B4: P-PROVENTO | C4: 1027 | D4: # TRANSPORTE/ALIMENTACAO
A5: 2ª VIA CARTAO ALIMENTAÇÃO | B5: D-DESCONTO | C5: 1028 | D5: 2ª VIA CARTAO ALIMENTAÇÃO
A6: 2ª VIA CARTAO REFEICAO | B6: D-DESCONTO | C6: 1029 | D6: 2ª VIA CARTAO REFEICAO
A7: 2ª VIA CARTÃO SUPER CONTA | B7: D-DESCONTO | C7: 1030 | D7: 2ª VIA CARTÃO SUPER CONTA
A8: ADIANT. DE RECESSO | B8: D-DESCONTO | C8: 1031 | D8: ADIANT. DE RECESSO
A9: ADIANTAMENTO DE VT | B9: D-DESCONTO | C9: 1032 | D9: ADIANTAMENTO DE VT
A10: ADICIONAL NOTURNO | B10: P-PROVENTO | C10: 1033 | D10: ADICIONAL NOTURNO
A11: ADICIONAL NOTURNO 21% | B11: P-PROVENTO | C11: 1034 | D11: ADICIONAL NOTURNO 21%
A12: AJUDA CUSTOS ALIMENTAÇ ÃO - CCT SINDICAM | B12: P-PROVENTO | C12: 1035 | D12: AJUDA CUSTOS ALIMENTAÇ ÃO - CCT SINDICAM
A13: ASSITENCIA MEDICA SINDICATO | B13: D-DESCONTO | C13: 1036 | D13: ASSITENCIA MEDICA SINDICATO
... A17: DESC.DIFERENCA REAJ.SALARIAL | B17: D-DESCONTO | C17: 1038 | D17: CESTA BASICA
A18: DESCONTO DE ADIANTAMENTO DE FERIAS | B18: D-DESCONTO | C18: 43 | D18: DESC. ADTO LIQUIDO DE FERIAS | E18: JÁ EXISTENTE
A19: DESCONTO DEVIDOS | B19: D-DESCONTO | C19: 1039 | D19: DESCONTO DEVIDOS
A20: DESCONTO DO PAGAMENTO INDEVIDO | B20: D-DESCONTO | C20: 1024 | D20: DEVOLUCAO RECEBIMENTO INDEVIDO(D) | E20: JÁ EXISTENTE
A21: DESCONTO EPI - REPOSIÇÃO | B21: D-DESCONTO | C21: 1040 | D21: DESCONTO EPI - REPOSIÇÃO
A22: DESCONTO INSS SEGURADO MÊS ANTERIOR | B22: D-DESCONTO | C22: 1041 | D22: DESCONTO INSS SEGURADO MÊS ANTERIOR
A23: DESCONTOS DEVIDO | B23: D-DESCONTO | C23: 1039 | D23: DESCONTOS DEVIDO
A24: DEVOLUÇÃO DE PAGAMENTO INDEVIDO | B24: D-DESCONTO | C24: 1024 | D24: DEVOLUCAO RECEBIMENTO INDEVIDO(D) | E24: JÁ EXISTENTE
A25: DIA DA CATEGORIA PROFISSIONAL | B25: P-PROVENTO | C25: 1042 | D25: DIA DA CATEGORIA PROFISSIONAL
A26: DIÁRIA | B26: P-PROVENTO | C26: 1043 | D26: DIÁRIA
A27: DIF. DE REAJUSTE SALARIAL- CCT 2021/2022 | B27: P-PROVENTO | C27: 1044 | D27: DIF. REAJUSTE SALARIAL
A28: DIF. DE REAJUSTE SALARIAL-MNUS-2022-2023 | B28: P-PROVENTO | C28: 1044 | D28: DIF. REAJUSTE SALARIAL
A29: DIF.ADIC. PERICULOSIDADE(MESES ANTERIORE | B29: P-PROVENTO | C29: 1045 | D29: DIF.ADIC. PERICULOSIDADE(MESES ANTERIORE
A30: DIF.REAJ.SALARIAL CCT2021/2022 | B30: P-PROVENTO | C30: 1047 | D30: DIF. REAJUSTE SALARIAL
A31: DIF.REAJUSTE SAL MES FEVEREIRO - CCT2022 | B31: P-PROVENTO | C31: 1044 | D31: DIF. REAJUSTE SALARIAL
A32: DIF.REAJUSTE SALARIAL | B32: P-PROVENTO | C32: 1044 | D32: DIF. REAJUSTE SALARIAL
A33: DIF.REAJUSTE SALARIAL CCT 2019/2020 | B33: P-PROVENTO | C33: 1044 | D33: DIF. REAJUSTE SALARIAL
A34: DIF.REAJUSTE SALARIAL- CCT 2021/2022 | B34: P-PROVENTO | C34: 1044 | D34: DIF. REAJUSTE SALARIAL
A35: DIF.REAJUSTE SALARIAL- CCT 2022/2023 | B35: P-PROVENTO | C35: 1044 | D35: DIF. REAJUSTE SALARIAL
A36: DIF.REAJUSTE SALARIAL- CCT JANEIRO/2022 | B36: P-PROVENTO | C36: 1044 | D36: DIF. REAJUSTE SALARIAL
... A55: DIFERENÇA DE PLR - 04/2023 | B55: P-PROVENTO | C55: 1048 | D55: DIF. PLR
A56: DIFERENCA SALARIAL | B56: P-PROVENTO | C56: 37 | D56: DIF. SALARIAL | E56: JÁ EXISTENTE
A57: DIFERENCA SALARIAL 2025 | B57: P-PROVENTO | C57: 37 | D57: DIF. SALARIAL | E57: JÁ EXISTENTE
A58: DIFERENCA SALARIAL - 2023 | B58: P-PROVENTO | C58: 37 | D58: DIF. SALARIAL | E58: JÁ EXISTENTE
A59: DIFERENCA SALARIAL - 2024 | B59: P-PROVENTO | C59: 37 | D59: DIF. SALARIAL | E59: JÁ EXISTENTE
A60: DIFERENCA SALARIAL - 2025 | B60: P-PROVENTO | C60: 37 | D60: DIF. SALARIAL | E60: JÁ EXISTENTE
A61: DIFERENCA SALARIAL - 2026 | B61: P-PROVENTO | C61: 37 | D61: DIF. SALARIAL | E61: JÁ EXISTENTE
A62: DIFERENÇA SALARIAL 2025 | B62: P-PROVENTO | C62: 37 | D62: DIF. SALARIAL | E62: JÁ EXISTENTE
A63: DIFERENÇA SALARIAL JANEIRO/2024 | B63: P-PROVENTO | C63: 37 | D63: DIF. SALARIAL | E63: JÁ EXISTENTE
A64: DIFERENÇAS SALARIAIS PARC 1/4 - CCT 2023 | B64: P-PROVENTO | C64: 1049 | D64: DIF. SALARIAL 1/4
A65: DIFERENÇAS SALARIAIS PARC 2/4 - CCT 2023 | B65: P-PROVENTO | C65: 1050 | D65: DIF. SALARIAL 2/4
A66: DIFERENÇAS SALARIAIS PARC 3/4 -CCT 2023 | B66: P-PROVENTO | C66: 1051 | D66: DIF. SALARIAL 3/4
A67: DIFERENÇAS SALARIAIS PARC 4/4 - CCT2023 | B67: P-PROVENTO | C67: 1052 | D67: DIF. SALARIAL 4/4
A68: EXAME MEDICO | B68: P-PROVENTO | C68: 1053 | D68: EXAME MEDICO
A69: HORA EXTRA 110% | B69: P-PROVENTO | C69: 1054 | D69: HORA EXTRA 110%
A70: HORA EXTRA 67% | B70: P-PROVENTO | C70: 1055 | D70: HORA EXTRA 67%
A71: HORA EXTRA 75% | B71: P-PROVENTO | C71: 1056 | D71: HORA EXTRA 75%
A72: IND. USO CELULAR 05/23 A 04/25 | B72: P-PROVENTO | C72: 1057 | D72: IND. USO CELULAR 05/23 A 04/25
A73: INDENIZAÇÃO | B73: P-PROVENTO | C73: 1058 | D73: INDENIZACAO
A74: OUTROS (DESCONTO) | B74: D-DESCONTO | C74: 1026 | D74: OUTROS PROVENTOS
A75: OUTROS (PROVENTO) | B75: P-PROVENTO | C75: 1027 | D75: OUTROS DESCONTOS
... A83: TX EMISSÃO DE CARTÃO 1ª VIA | B83: D-DESCONTO | C83: 1065 | D83: TX EMISSÃO DE CARTÃO 1ª VIA

Sheet DADOS_RM_MOTIVOS
A1: CODCLIENTE | B1: DESCRICAO
A2: 01 | B2: Admissão
A3: 02 | B3: Aposentadoria p/invalidez acidente de trabalho
A4: 03 | B4: Afastamento p/Férias
A5: 04 | B5: Retorno das Férias
A6: 06 | B6: Transferência entre Coligadas
A7: 07 | B7: Transferência entre Filiais
A8: 08 | B8: Demissão
A9: 09 | B9: Licença maternidade
A10: 10 | B10: Licença maternidade p/aborto não criminoso
A11: 11 | B11: Licença Remunerada
A12: 12 | B12: Licença maternidade por adoção
... A32: CV | B32: Afastamento por COVID-19

Sheet ZDEPARA_COLIGADAS
A1: ID | B1: EMPRESA_DE | C1: NOME_DE | D1: RAZAOSOCIAL | E1: CNPJ | F1: DESATIVADA | G1: ATIVOS | H1: INATIVOS | I1: TOTAL | J1: CODCOLIGADA | K1: FILIAL_PARA
A2: 2 | B2: 0004 | C2: FUTURECOM | D2: LCS CONSTRUCAO E SERVICOS LTDA | E2: 05.603.629/0001-40 | F2: 0 | G2: 347 | H2: 6242 | I2: 6589 | J2: 1 | K2: 1
A3: 4 | B3: 0015 | C3: BOA EMPREENDIME | D3: BOA EMPREENDIMENTOS IMOBILIARIOS LTDA | E3: 17.027.472/0001-30 | F3: 0 | G3: 1 | H3: 6 | I3: 7 | J3: 2 | K3: 1
A4: 5 | B4: 0017 | C4: PATIO CASTELAO | D4: PATIO CASTELAO EMPREENDIMENTOS LTDA | E4: 48.636.176/0001-60 | F4: 0 | G4: 2 | H4: 64 | I4: 66 | J4: 3 | K4: 1
A5: 3 | B5: 0005 | C5: M ARACI | D5: ANJO ETERNO PET LTDA | E5: 11.465.561/0001-82 | F5: 0 | G5: 7 | H5: 291 | I5: 298 | J5: 4 | K5: 1
A6: 1 | B6: 0012 | C6: ATIVA COOPERADO | D6: ATIVA COOPERADOS LTDA EPP | E6: 05.525.104/0001-33 | F6: 0 | G6: 11 | H6: 61 | I6: 72 | J6: 5 | K6: 1
A7: 6 | B7: 0022 | C7: MC Coffee Shop | D7: Mc Coffee Shop | E7: 60.538.885/0001-09 | F7: 0 | G7: 3 | H7: 1 | I7: 4 | J7: 6 | K7: 1

Sheet ZDEPARA_FUNCOES
A1: EMPRESA_DE | B1: CODIGO_DE | C1: NOME_DE | D1: CBO | E1: CBO_2002 | F1: CODIGO_PARA
A2: 0012 | B2: 282 | C2: ADMINISTRADOR | D2: 252105 | E2: 252105 | F2: 000001
A3: 0004 | B3: 828 | C3: AJUDANTE DE CACAMBA | D3: 514225 | E3: 514225 | F3: 000002
A4: 0004 | B4: 878 | C4: AJUDANTE DE CAÇAMBA-APRENDIZ | D4: 514225 | E4: 514225 | F4: 000003
A5: 0004 | B5: 838 | C5: AJUDANTE DE COLETA | D5: 514215 | E5: 514215 | F5: 000004
A6: 0004 | B6: 017 | C6: AJUDANTE DE OFICIAL DE REDE | D6: 951105 | E6: 951105 | F6: 000005
A7: 0004 | B7: 769 | C7: ALMMOXARIFE I | D7: 414105 | E7: 414105 | F7: 000006
A8: 0004 | B8: 246 | C8: ALMOXARIFE | D8: 414105 | E8: 414105 | F8: 000007
A9: 0017 | B9: 031 | C9: ALMOXARIFE | D9: 414105 | E9: 414105 | F9: 000007
A10: 0015 | B10: 836 | C10: ANALISTA ADMINISTRATIVO | D10: 252105 | E10: 111510 | F10: 000008
A11: 0004 | B11: 836 | C11: ANALISTA ADMINISTRATIVO | D11: 252105 | E11: 252105 | F11: 000009
A12: 0004 | B12: 834 | C12: Analista Administrativo(a) | D12: 252105 | E12: 252105 | F12: 000010
... A18: 0004 | B18: 875 | C18: ANALISTA DE FROTA | D18: 342115 | E18: 342115 | F18: 000016
A19: 0004 | B19: 876 | C19: ANALISTA DE MARKETING | E19: 142335 | F19: 000017
A20: 0015 | B20: 853 | C20: ANALISTA DE MARKETING | E20: 142335 | F20: 000017
A21: 0004 | B21: 884 | C21: ANALISTA DE MARKETING I | E21: 142335 | F21: 000018
A22: 0004 | B22: 840 | C22: ANALISTA DE PRODUCAO | D22: 214905 | E22: 214905 | F22: 000019
A23: 0004 | B23: 844 | C23: ANALISTA DE PROJETOS | D23: 318105 | E23: 318105 | F23: 000020
A24: 0004 | B24: 804 | C24: ANALISTA DE RH | D24: 252105 | E24: 252405 | F24: 000021
A25: 0004 | B25: 808 | C25: ANALISTA DE TI | D25: 212405 | E25: 212405 | F25: 000022
A26: 0004 | B26: 783 | C26: ANALISTA FINANCEIRO | D26: 252545 | E26: 252545 | F26: 000023
A27: 0004 | B27: 841 | C27: ANALISTA FINANCEIRO I | D27: 252545 | E27: 252545 | F27: 000024
A28: 0004 | B28: 855 | C28: ANALISTA FINANCEIRO II | D28: 252545 | E28: 252545 | F28: 000025
A29: 0004 | B29: 771 | C29: ANALISTA FINANCEIRO PLENO | D29: 252545 | E29: 251215 | F29: 000026
A30: 0004 | B30: 746 | C30: APONTADOR | D30: 414205 | E30: 414205 | F30: 000027
A31: 0004 | B31: 861 | C31: APONTADOR DE OBRAS - PESADA | D31: 414205 | E31: 414205 | F31: 000028
A32: 0004 | B32: 818 | C32: APONTADOR I | D32: 414205 | E32: 414205 | F32: 000029
A33: 0012 | B33: 053 | C33: ARMADOR DE FERRO | D33: 715315 | E33: 715315 | F33: 000030
... A54: 0004 | B54: 760 | C54: ASSISTENTE OPERACIONAL II | D54: 411010 | E54: 411010 | F54: 000049
A55: 0022 | B55: 027 | C55: ATENDENTE DE CAFETERIA | E55: 513435 | F55: 000050
A56: 0004 | B56: 122 | C56: AUX. ADMINISTRATIVO/OPERACIONAL | D56: 411005 | E56: 411005 | F56: 000051
A57: 0004 | B57: 016 | C57: AUX. CONTABILIDADE | D57: 413110 | E57: 413110 | F57: 000052
A58: 0004 | B58: 217 | C58: AUX. DE CARPINTEIRO | D58: 715505 | E58: 715505 | F58: 000053
A59: 0017 | B59: 035 | C59: AUX. DE ELETRICISTA | D59: 715615 | E59: 715615 | F59: 000054
A60: 0004 | B60: 634 | C60: AUX. DE MECANICO | D60: 314110 | E60: 314110 | F60: 000055
A61: 0004 | B61: 113 | C61: AUX. DE SALA TECNICA | D61: 848505 | E61: 312105 | F61: 000056
A62: 0004 | B62: 021 | C62: AUX. DE TECNICO DE FIBRA OTICA | D62: 951105 | E62: 951105 | F62: 000057
A63: 0004 | B63: 124 | C63: AUX. DEPART PESSOAL | D63: 411030 | E63: 411030 | F63: 000058
A64: 0005 | B64: 124 | C64: AUX. DEPART PESSOAL | D64: 848505 | E64: 848505 | F64: 000059
A65: 0004 | B65: 110 | C65: AUX. ELETRICISTA | D65: 715615 | E65: 715615 | F65: 000060
A66: 0004 | B66: 005 | C66: AUX. ESCRITORIO | D66: 411005 | E66: 411005 | F66: 000061
A67: 0004 | B67: 774 | C67: AUX. ESCRITORIO / APRENDIZ | D67: 411005 | E67: 411005 | F67: 000062
... A70: 0004 | B70: 195 | C70: AUX.BOMBEIRO HIDRAULICO | D70: 724110 | E70: 724110 | F70: 000065
A71: 0004 | B71: 881 | C71: AUX.MANUTENÇÃO PREDIAL-APRENDIZ | E71: 514310 | F71: 000066
A72: 0004 | B72: 642 | C72: AUXILIAR ADMINISTRATIVO I | D72: 411005 | E72: 411005 | F72: 000067
A73: 0004 | B73: 761 | C73: AUXILIAR ADMINISTRATIVO II | D73: 411005 | E73: 411005 | F73: 000068
A74: 0004 | B74: 065 | C74: AUXILIAR DA QUALIDADE | D74: 391215 | E74: 391215 | F74: 000069
A75: 0004 | B75: 688 | C75: AUXILIAR DE ALMOXARIFADO | D75: 414105 | E75: 414105 | F75: 000070
A76: 0017 | B76: 045 | C76: AUXILIAR DE ALMOXARIFE | E76: 414140 | F76: 000071
A77: 0004 | B77: 655 | C77: AUXILIAR DE CARPINTEIRO | D77: 715505 | E77: 715505 | F77: 000072
A78: 0017 | B78: 037 | C78: AUXILIAR DE CARPINTEIRO | D78: 715505 | E78: 715505 | F78: 000072
A79: 0004 | B79: 873 | C79: AUXILIAR DE CARPINTEIRO - PESADA | D79: 715525 | E79: 715525 | F79: 000073
A80: 0004 | B80: 080 | C80: AUXILIAR DE FERREIRO | D80: 722105 | E80: 722105 | F80: 000074
A81: 0004 | B81: 238 | C81: AUXILIAR DE FISCAL | D81: 414215 | E81: 414210 | F81: 000075
A82: 0004 | B82: 793 | C82: AUXILIAR DE LABORATORIO | D82: 818110 | E82: 818110 | F82: 000076
A83: 0004 | B83: 883 | C83: AUXILIAR DE LIMPEZA/APRENDIZ | D83: 514210 | E83: 514320 | F83: 000077
A84: 0004 | B84: 708 | C84: AUXILIAR DE MANUTENCAO | D84: 991405 | E84: 514325 | F84: 000078
A85: 0004 | B85: 684 | C85: AUXILIAR DE MECANICA | D85: 913120 | E85: 913120 | F85: 000079
A86: 0005 | B86: 684 | C86: AUXILIAR DE MECANICA | D86: 913120 | E86: 913120 | F86: 000079
A87: 0004 | B87: 788 | C87: AUXILIAR DE PEDREIRO | D87: 717020 | E87: 717020 | F87: 000080
A88: 0004 | B88: 786 | C88: AUXILIAR DE TOPOGRAFO | D88: 312320 | E88: 312320 | F88: 000081
... A150: 0004 | B150: 801 | C150: ENGENHEIRO PLANEJAMENTO | D150: 214205 | E150: 214205 | F150: 000138
A151: 0004 | B151: 740 | C151: ESTAGIARIO | E151: 411010 | F151: 000139
A152: 0005 | B152: 740 | C152: ESTAGIARIO | D152: 411010 | E152: 411010 | F152: 000139
A153: 0005 | B153: 796 | C153: ESTAGIARIO DE POS GRADUAÇÃO | D153: 411010 | E153: 411010 | F153: 000140
A154: 0004 | B154: 779 | C154: ESTAGIARIO NA CONSTRUÇÃO CIVIL | D154: 214215 | E154: 214215 | F154: 000141
A155: 0004 | B155: 078 | C155: FERREIRO | D155: 722105 | E155: 722105 | F155: 000142
A156: 0017 | B156: 033 | C156: FERREIRO | D156: 722105 | E156: 722105 | F156: 000142
A157: 0004 | B157: 869 | C157: FERREIRO - PESADA | D157: 715315 | E157: 722105 | F157: 000143
A158: 0004 | B158: 813 | C158: FERREIRO I | D158: 722105 | E158: 722105 | F158: 000144
A159: 0005 | B159: 744 | C159: FISCAL | D159: 511205 | E159: 511205 | F159: 000145
A160: 0004 | B160: 199 | C160: FISCAL DE OBRA | D160: 848505 | E160: 848505 | F160: 000146
A161: 0004 | B161: 744 | C161: FISCAL FTZA I | D161: 511205 | E161: 511205 | F161: 000147
A162: 0004 | B162: 762 | C162: FISCAL FTZA II | D162: 511205 | E162: 511205 | F162: 000148
A163: 0004 | B163: 848 | C163: FISCAL FTZA III | D163: 511205 | E163: 511205 | F163: 000149
... A224: 0015 | B224: 851 | C224: OFICIAL DE MANUTENÇÃO PREDIAL | D224: 991405 | E224: 514325 | F224: 000202
A225: 0017 | B225: 044 | C225: OFICIAL DE MANUTENÇÃO PREDIAL | E225: 514325 | F225: 000202
A226: 0004 | B226: 018 | C226: OFICIAL DE REDE | D226: 951105 | E226: 951105 | F226: 000203
A227: 0004 | B227: 777 | C227: OP. BETONEIRA NÃO CARREGAVEL | D227: 715405 | E227: 715405 | F227: 000204
A228: 0017 | B228: 039 | C228: OP. BETONEIRA NÃO CARREGAVEL | D228: 715405 | E228: 715405 | F228: 000204
A229: 0004 | B229: 669 | C229: OPER. DE RETROESCAVADEIRA | D229: 715125 | E229: 715125 | F229: 000205
A230: 0004 | B230: 685 | C230: OPER. PA MECANICO | D230: 715135 | E230: 715135 | F230: 000206
A231: 0004 | B231: 673 | C231: OPER. PA-CARREGADEIRA | D231: 715135 | E231: 715135 | F231: 000207
A232: 0004 | B232: 770 | C232: OPERADOR DE BETONEIRA | D232: 715405 | E232: 715405 | F232: 000208
A233: 0005 | B233: 062 | C233: OPERADOR DE FORNO | D233: 848505 | E233: 848505 | F233: 000209
A234: 0005 | B234: 762 | C234: OPERADOR DE FORNO CREMATORIO | D234: 516605 | E234: 516605 | F234: 000210
A235: 0004 | B235: 066 | C235: OPERADOR DE MAQUINA | D235: 715125 | E235: 715125 | F235: 000211
A236: 0005 | B236: 066 | C236: OPERADOR DE MAQUINA | D236: 715125 | E236: 715125 | F236: 000211
A237: 0004 | B237: 650 | C237: OPERADOR DE MAQUINA 1 | D237: 761205 | E237: 761205 | F237: 000212
... A299: 0012 | B299: 024 | C299: ZELADOR | D299: 514120 | E299: 514120 | F299: 000260

Sheet ZDEPARA_SINDICATOS
A1: EMPRESA_DE | B1: CODIGO_DE | C1: NOME_DE | D1: CNPJ | E1: COLIGADA_PARA | F1: CODIGO_PARA
A2: 0005 | B2: 217 | C2: SIND. DOS EMPREG. EM EMP. FUNERARIAS E CEMIT. PART. EST. CE | D2: 09464265000115 | E2: 4 | F2: 217
A3: 0005 | B3: 007 | C3: SIND DE ASSEIO E CONSERVACAO | D3: 23443849000135 | E3: 4 | F3: 007
A4: 0012 | B4: 217 | C4: SIND. DOS EMPREG. EM EMP. FUNERARIAS E CEMIT. PART. EST. CE | D4: 09464265000115 | E4: 5 | F4: 217
A5: 0012 | B5: 007 | C5: SIND DE ASSEIO E CONSERVACAO | D5: 23443849000135 | E5: 5 | F5: 007
A6: 0004 | B6: 007 | C6: SIND DE ASSEIO E CONSERVACAO | D6: 23443849000135 | E6: 1 | F6: 007
A7: 0022 | B7: 225 | C7: SINDICATO DOS TRAB EM REST CHUR PIZZARIAS LANC FAST FOOD | D7: 24878457000161 | E7: 6 | F7: 225
A8: 0004 | B8: 218 | C8: SINDICATO DA CONSTRUÇÃO PESADA - SINTRAPAV SP | D8: 00000000000000 | E8: 1 | F8: 218
A9: 0012 | B9: 114 | C9: SINDICATO DA INDUSTRIA DA CONSTRU CIVIL | D9: 07341019000140 | E9: 5 | F9: 114
A10: 0004 | B10: 001 | C10: SINDICATO DOS COMERCIARIOS | D10: 00000000000001 | E10: 1 | F10: 001
A11: 0004 | B11: 008 | C11: SINDICATO DOS EMP EM EMP DE ASSEIO E CONS DO ESTADO DO AM | D11: 23006562000148 | E11: 1 | F11: 008
A12: 0015 | B12: 007 | C12: SIND DE ASSEIO E CONSERVACAO | D12: 23443849000135 | E12: 2 | F12: 007
... A29: 0012 | B29: 000 | C29: 0000000000000000 | D29: 00000000000000 | E29: 5 | F29: 000

Sheet ZDEPARA_SECOES
A1: EMPRESA_DE | B1: FILIAL_DE | C1: CODIGO_DE | D1: NOME_DE | E1: COLIGADA_PARA | F1: FILIAL_PARA | G1: CODIGO_PARA | H1: DESCRICAO_SECAO_PARA
A2: 0004 | B2: 0001 | C2: 00101 | D2: (S/M) PRESIDENCIA | E2: 1 | F2: 1 | H2: =IFERROR(__xludf.DUMMYFUNCTION("IF(G2="""", """", IF(COUNTIFS(DADOS_RM_SECOES!A:A, E2, DADOS_RM_SECOES!B:B, F2, DADOS_RM_SECOES!C:C, G2&"".*"")>0, ""NÍVEL INCOMPLETO"", IFERROR(INDEX(FILTER(DADOS_RM_SECOES!D:D, DADOS_RM_SECOES!A:A=E2, DADOS_RM_SECOES!B:B=F2, DADOS_RM_SECOES!C:C=G2), 1),"&" ""Não Encontrado""))) "),"")
A3: 0004 | B3: 0001 | C3: 00102 | D3: (S/M) SISTEMA DE GESTÃO DA QUALIDADE | E3: 1 | F3: 1 | H3: =IFERROR(__xludf.DUMMYFUNCTION("IF(G3="""", """", IF(COUNTIFS(DADOS_RM_SECOES!A:A, E3, DADOS_RM_SECOES!B:B, F3, DADOS_RM_SECOES!C:C, G3&"".*"")>0, ""NÍVEL INCOMPLETO"", IFERROR(INDEX(FILTER(DADOS_RM_SECOES!D:D, DADOS_RM_SECOES!A:A=E3, DADOS_RM_SECOES!B:B=F3, DADOS_RM_SECOES!C:C=G3), 1),"&" ""Não Encontrado""))) "),"")
A4: 0004 | B4: 0001 | C4: 0010301 | D4: (S/M) GERÊNCIA DE OBRAS | E4: 1 | F4: 1 | H4: =IFERROR(__xludf.DUMMYFUNCTION("IF(G4="""", """", IF(COUNTIFS(DADOS_RM_SECOES!A:A, E4, DADOS_RM_SECOES!B:B, F4, DADOS_RM_SECOES!C:C, G4&"".*"")>0, ""NÍVEL INCOMPLETO"", IFERROR(INDEX(FILTER(DADOS_RM_SECOES!D:D, DADOS_RM_SECOES!A:A=E4, DADOS_RM_SECOES!B:B=F4, DADOS_RM_SECOES!C:C=G4), 1),"&" ""Não Encontrado""))) "),"")
A5: 0004 | B5: 0001 | C5: 0010302 | D5: (S/M) ORÇAMENTOS - OBRAS | E5: 1 | F5: 1 | H5: =IFERROR(__xludf.DUMMYFUNCTION("IF(G5="""", """", IF(COUNTIFS(DADOS_RM_SECOES!A:A, E5, DADOS_RM_SECOES!B:B, F5, DADOS_RM_SECOES!C:C, G5&"".*"")>0, ""NÍVEL INCOMPLETO"", IFERROR(INDEX(FILTER(DADOS_RM_SECOES!D:D, DADOS_RM_SECOES!A:A=E5, DADOS_RM_SECOES!B:B=F5, DADOS_RM_SECOES!C:C=G5), 1),"&" ""Não Encontrado""))) "),"")
A6: 0004 | B6: 0001 | C6: 0010303 | D6: (S/M) PLAN E CONTROLE - OBRAS | E6: 1 | F6: 1 | H6: =IFERROR(__xludf.DUMMYFUNCTION("IF(G6="""", """", IF(COUNTIFS(DADOS_RM_SECOES!A:A, E6, DADOS_RM_SECOES!B:B, F6, DADOS_RM_SECOES!C:C, G6&"".*"")>0, ""NÍVEL INCOMPLETO"", IFERROR(INDEX(FILTER(DADOS_RM_SECOES!D:D, DADOS_RM_SECOES!A:A=E6, DADOS_RM_SECOES!B:B=F6, DADOS_RM_SECOES!C:C=G6), 1),"&" ""Não Encontrado""))) "),"")
A7: 0004 | B7: 0001 | C7: 0010304 | D7: (S/M) ADMINISTRACAO - OBRAS | E7: 1 | F7: 1 | H7: =IFERROR(__xludf.DUMMYFUNCTION("IF(G7="""", """", IF(COUNTIFS(DADOS_RM_SECOES!A:A, E7, DADOS_RM_SECOES!B:B, F7, DADOS_RM_SECOES!C:C, G7&"".*"")>0, ""NÍVEL INCOMPLETO"", IFERROR(INDEX(FILTER(DADOS_RM_SECOES!D:D, DADOS_RM_SECOES!A:A=E7, DADOS_RM_SECOES!B:B=F7, DADOS_RM_SECOES!C:C=G7), 1),"&" ""Não Encontrado""))) "),"")
A8: 0004 | B8: 0001 | C8: 00104 | D8: (S/M) GERÊNCIA COMERCIAL | E8: 1 | F8: 1 | H8: =IFERROR(__xludf.DUMMYFUNCTION("IF(G8="""", """", IF(COUNTIFS(DADOS_RM_SECOES!A:A, E8, DADOS_RM_SECOES!B:B, F8, DADOS_RM_SECOES!C:C, G8&"".*"")>0, ""NÍVEL INCOMPLETO"", IFERROR(INDEX(FILTER(DADOS_RM_SECOES!D:D, DADOS_RM_SECOES!A:A=E8, DADOS_RM_SECOES!B:B=F8, DADOS_RM_SECOES!C:C=G8), 1),"&" ""Não Encontrado""))) "),"")
A9: 0004 | B9: 0001 | C9: 0010501 | D9: (S/M) GERÊNCIA ADM - FIN | E9: 1 | F9: 1 | H9: =IFERROR(__xludf.DUMMYFUNCTION("IF(G9="""", """", IF(COUNTIFS(DADOS_RM_SECOES!A:A, E9, DADOS_RM_SECOES!B:B, F9, DADOS_RM_SECOES!C:C, G9&"".*"")>0, ""NÍVEL INCOMPLETO"", IFERROR(INDEX(FILTER(DADOS_RM_SECOES!D:D, DADOS_RM_SECOES!A:A=E9, DADOS_RM_SECOES!B:B=F9, DADOS_RM_SECOES!C:C=G9), 1),"&" ""Não Encontrado""))) "),"")
A10: 0004 | B10: 0001 | C10: 0010502 | D10: (S/M) RECEPÇÃO | E10: 1 | F10: 1 | H10: =IFERROR(__xludf.DUMMYFUNCTION("IF(G10="""", """", IF(COUNTIFS(DADOS_RM_SECOES!A:A, E10, DADOS_RM_SECOES!B:B, F10, DADOS_RM_SECOES!C:C, G10&"".*"")>0, ""NÍVEL INCOMPLETO"", IFERROR(INDEX(FILTER(DADOS_RM_SECOES!D:D, DADOS_RM_SECOES!A:A=E10, DADOS_RM_SECOES!B:B=F10, DADOS_RM_SECOES!C:C=G1"&"0), 1), ""Não Encontrado""))) "),"")
A11: 0004 | B11: 0001 | C11: 0010503 | D11: (S/M) SERVIÇOS GERAIS | E11: 1 | F11: 1 | H11: =IFERROR(__xludf.DUMMYFUNCTION("IF(G11="""", """", IF(COUNTIFS(DADOS_RM_SECOES!A:A, E11, DADOS_RM_SECOES!B:B, F11, DADOS_RM_SECOES!C:C, G11&"".*"")>0, ""NÍVEL INCOMPLETO"", IFERROR(INDEX(FILTER(DADOS_RM_SECOES!D:D, DADOS_RM_SECOES!A:A=E11, DADOS_RM_SECOES!B:B=F11, DADOS_RM_SECOES!C:C=G1"&"1), 1), ""Não Encontrado""))) "),"")
A12: 0004 | B12: 0001 | C12: 0010504 | D12: (S/M) COPA | E12: 1 | F12: 1 | H12: =IFERROR(__xludf.DUMMYFUNCTION("IF(G12="""", """", IF(COUNTIFS(DADOS_RM_SECOES!A:A, E12, DADOS_RM_SECOES!B:B, F12, DADOS_RM_SECOES!C:C, G12&"".*"")>0, ""NÍVEL INCOMPLETO"", IFERROR(INDEX(FILTER(DADOS_RM_SECOES!D:D, DADOS_RM_SECOES!A:A=E12, DADOS_RM_SECOES!B:B=F12, DADOS_RM_SECOES!C:C=G1"&"2), 1), ""Não Encontrado""))) "),"")
A13: 0004 | B13: 0001 | C13: 0010505 | D13: (S/M) TECNOLOGIA DA INFORMAÇÃO | E13: 1 | F13: 1 | H13: =IFERROR(__xludf.DUMMYFUNCTION("IF(G13="""", """", IF(COUNTIFS(DADOS_RM_SECOES!A:A, E13, DADOS_RM_SECOES!B:B, F13, DADOS_RM_SECOES!C:C, G13&"".*"")>0, ""NÍVEL INCOMPLETO"", IFERROR(INDEX(FILTER(DADOS_RM_SECOES!D:D, DADOS_RM_SECOES!A:A=E13, DADOS_RM_SECOES!B:B=F13, DADOS_RM_SECOES!C:C=G1"&"3), 1), ""Não Encontrado""))) "),"")
A14: 0004 | B14: 0001 | C14: 0010506 | D14: (S/M) COMPRAS | E14: 1 | F14: 1 | G14: 001.01.001.09 | H14: =IFERROR(__xludf.DUMMYFUNCTION("IF(G14="""", """", IF(COUNTIFS(DADOS_RM_SECOES!A:A, E14, DADOS_RM_SECOES!B:B, F14, DADOS_RM_SECOES!C:C, G14&"".*"")>0, ""NÍVEL INCOMPLETO"", IFERROR(INDEX(FILTER(DADOS_RM_SECOES!D:D, DADOS_RM_SECOES!A:A=E14, DADOS_RM_SECOES!B:B=F14, DADOS_RM_SECOES!C:C=G1"&"4), 1), ""Não Encontrado""))) "),"COMPRAS") -> COMPRAS
A15: 0004 | B15: 0001 | C15: 0010507 | D15: (S/M) CONTAS A PAGAR | E15: 1 | F15: 1 | H15: =IFERROR(__xludf.DUMMYFUNCTION("IF(G15="""", """", IF(COUNTIFS(DADOS_RM_SECOES!A:A, E15, DADOS_RM_SECOES!B:B, F15, DADOS_RM_SECOES!C:C, G15&"".*"")>0, ""NÍVEL INCOMPLETO"", IFERROR(INDEX(FILTER(DADOS_RM_SECOES!D:D, DADOS_RM_SECOES!A:A=E15, DADOS_RM_SECOES!B:B=F15, DADOS_RM_SECOES!C:C=G1"&"5), 1), ""Não Encontrado""))) "),"")
A16: 0004 | B16: 0001 | C16: 0010508 | D16: (S/M) RECURSOS HUMANOS | E16: 1 | F16: 1 | G16: 001.01.001.03 | H16: =IFERROR(__xludf.DUMMYFUNCTION("IF(G16="""", """", IF(COUNTIFS(DADOS_RM_SECOES!A:A, E16, DADOS_RM_SECOES!B:B, F16, DADOS_RM_SECOES!C:C, G16&"".*"")>0, ""NÍVEL INCOMPLETO"", IFERROR(INDEX(FILTER(DADOS_RM_SECOES!D:D, DADOS_RM_SECOES!A:A=E16, DADOS_RM_SECOES!B:B=F16, DADOS_RM_SECOES!C:C=G1"&"6), 1), ""Não Encontrado""))) "),"RECURSOS HUMANOS") -> RECURSOS HUMANOS
A17: 0004 | B17: 0001 | C17: 0010509 | D17: (S/M) PORTARIA | E17: 1 | F17: 1 | G17: 001.01.001.14 | H17: =IFERROR(__xludf.DUMMYFUNCTION("IF(G17="""", """", IF(COUNTIFS(DADOS_RM_SECOES!A:A, E17, DADOS_RM_SECOES!B:B, F17, DADOS_RM_SECOES!C:C, G17&"".*"")>0, ""NÍVEL INCOMPLETO"", IFERROR(INDEX(FILTER(DADOS_RM_SECOES!D:D, DADOS_RM_SECOES!A:A=E17, DADOS_RM_SECOES!B:B=F17, DADOS_RM_SECOES!C:C=G1"&"7), 1), ""Não Encontrado""))) "),"PORTARIA") -> PORTARIA
A18: 0004 | B18: 0001 | C18: 0010601 | D18: (S/M) GERÊNCIA DE CONTROLADORIA | E18: 1 | F18: 1 | G18: 001.01.001.07 | H18: =IFERROR(__xludf.DUMMYFUNCTION("IF(G18="""", """", IF(COUNTIFS(DADOS_RM_SECOES!A:A, E18, DADOS_RM_SECOES!B:B, F18, DADOS_RM_SECOES!C:C, G18&"".*"")>0, ""NÍVEL INCOMPLETO"", IFERROR(INDEX(FILTER(DADOS_RM_SECOES!D:D, DADOS_RM_SECOES!A:A=E18, DADOS_RM_SECOES!B:B=F18, DADOS_RM_SECOES!C:C=G1"&"8), 1), ""Não Encontrado""))) "),"CONTROLADORIA") -> CONTROLADORIA
A19: 0004 | B19: 0001 | C19: 0010602 | D19: (S/M) CONTABILIDADE | E19: 1 | F19: 1 | G19: 001.01.001.06 | H19: =IFERROR(__xludf.DUMMYFUNCTION("IF(G19="""", """", IF(COUNTIFS(DADOS_RM_SECOES!A:A, E19, DADOS_RM_SECOES!B:B, F19, DADOS_RM_SECOES!C:C, G19&"".*"")>0, ""NÍVEL INCOMPLETO"", IFERROR(INDEX(FILTER(DADOS_RM_SECOES!D:D, DADOS_RM_SECOES!A:A=E19, DADOS_RM_SECOES!B:B=F19, DADOS_RM_SECOES!C:C=G1"&"9), 1), ""Não Encontrado""))) "),"CONTABIL") -> CONTABIL
A20: 0004 | B20: 0001 | C20: 00107 | D20: (S/M) RECURSOS HUMANOS | E20: 1 | F20: 1 | G20: 001.01.001.03 | H20: =IFERROR(__xludf.DUMMYFUNCTION("IF(G20="""", """", IF(COUNTIFS(DADOS_RM_SECOES!A:A, E20, DADOS_RM_SECOES!B:B, F20, DADOS_RM_SECOES!C:C, G20&"".*"")>0, ""NÍVEL INCOMPLETO"", IFERROR(INDEX(FILTER(DADOS_RM_SECOES!D:D, DADOS_RM_SECOES!A:A=E20, DADOS_RM_SECOES!B:B=F20, DADOS_RM_SECOES!C:C=G2"&"0), 1), ""Não Encontrado""))) "),"RECURSOS HUMANOS") -> RECURSOS HUMANOS
A21: 0004 | B21: 0001 | C21: 00108 | D21: ADM MATRIZ ECOFOR | E21: 1 | F21: 1 | H21: =IFERROR(__xludf.DUMMYFUNCTION("IF(G21="""", """", IF(COUNTIFS(DADOS_RM_SECOES!A:A, E21, DADOS_RM_SECOES!B:B, F21, DADOS_RM_SECOES!C:C, G21&"".*"")>0, ""NÍVEL INCOMPLETO"", IFERROR(INDEX(FILTER(DADOS_RM_SECOES!D:D, DADOS_RM_SECOES!A:A=E21, DADOS_RM_SECOES!B:B=F21, DADOS_RM_SECOES!C:C=G2"&"1), 1), ""Não Encontrado""))) "),"")
A22: 0004 | B22: 0001 | C22: 0020101 | D22: (S/M) GERENCIA DE OPERAÇÃO | E22: 1 | F22: 1 | H22: =IFERROR(__xludf.DUMMYFUNCTION("IF(G22="""", """", IF(COUNTIFS(DADOS_RM_SECOES!A:A, E22, DADOS_RM_SECOES!B:B, F22, DADOS_RM_SECOES!C:C, G22&"".*"")>0, ""NÍVEL INCOMPLETO"", IFERROR(INDEX(FILTER(DADOS_RM_SECOES!D:D, DADOS_RM_SECOES!A:A=E22, DADOS_RM_SECOES!B:B=F22, DADOS_RM_SECOES!C:C=G2"&"2), 1), ""Não Encontrado""))) "),"")
A23: 0004 | B23: 0001 | C23: 0020102 | D23: (S/M) SEGURANÇA DO TRABALHO | E23: 1 | F23: 1 | G23: 001.01.001.11 | H23: =IFERROR(__xludf.DUMMYFUNCTION("IF(G23="""", """", IF(COUNTIFS(DADOS_RM_SECOES!A:A, E23, DADOS_RM_SECOES!B:B, F23, DADOS_RM_SECOES!C:C, G23&"".*"")>0, ""NÍVEL INCOMPLETO"", IFERROR(INDEX(FILTER(DADOS_RM_SECOES!D:D, DADOS_RM_SECOES!A:A=E23, DADOS_RM_SECOES!B:B=F23, DADOS_RM_SECOES!C:C=G2"&"3), 1), ""Não Encontrado""))) "),"SESMT") -> SESMT
A24: 0004 | B24: 0001 | C24: 0020103 | D24: (S/M) ALMOXARIFADO | E24: 1 | F24: 1 | G24: 001.01.001.10 | H24: =IFERROR(__xludf.DUMMYFUNCTION("IF(G24="""", """", IF(COUNTIFS(DADOS_RM_SECOES!A:A, E24, DADOS_RM_SECOES!B:B, F24, DADOS_RM_SECOES!C:C, G24&"".*"")>0, ""NÍVEL INCOMPLETO"", IFERROR(INDEX(FILTER(DADOS_RM_SECOES!D:D, DADOS_RM_SECOES!A:A=E24, DADOS_RM_SECOES!B:B=F24, DADOS_RM_SECOES!C:C=G2"&"4), 1), ""Não Encontrado""))) "),"ALMOXARIFE") -> ALMOXARIFE
A25: 0004 | B25: 0001 | C25: 0020104 | D25: (S/M) MANUTENÇÃO | E25: 1 | F25: 1 | H25: =IFERROR(__xludf.DUMMYFUNCTION("IF(G25="""", """", IF(COUNTIFS(DADOS_RM_SECOES!A:A, E25, DADOS_RM_SECOES!B:B, F25, DADOS_RM_SECOES!C:C, G25&"".*"")>0, ""NÍVEL INCOMPLETO"", IFERROR(INDEX(FILTER(DADOS_RM_SECOES!D:D, DADOS_RM_SECOES!A:A=E25, DADOS_RM_SECOES!B:B=F25, DADOS_RM_SECOES!C:C=G2"&"5), 1), ""Não Encontrado""))) "),"")
A26: 0004 | B26: 0001 | C26: 0020105 | D26: (S/M) MAQ. EQUIPAMENTOS | E26: 1 | F26: 1 | H26: =IFERROR(__xludf.DUMMYFUNCTION("IF(G26="""", """", IF(COUNTIFS(DADOS_RM_SECOES!A:A, E26, DADOS_RM_SECOES!B:B, F26, DADOS_RM_SECOES!C:C, G26&"".*"")>0, ""NÍVEL INCOMPLETO"", IFERROR(INDEX(FILTER(DADOS_RM_SECOES!D:D, DADOS_RM_SECOES!A:A=E26, DADOS_RM_SECOES!B:B=F26, DADOS_RM_SECOES!C:C=G2"&"6), 1), ""Não Encontrado""))) "),"")
A27: 0004 | B27: 0001 | C27: 002010600 | D27: OPERACAO FTZA | E27: 1 | F27: 1 | G27: 001.03.002 | H27: =IFERROR(__xludf.DUMMYFUNCTION("IF(G27="""", """", IF(COUNTIFS(DADOS_RM_SECOES!A:A, E27, DADOS_RM_SECOES!B:B, F27, DADOS_RM_SECOES!C:C, G27&"".*"")>0, ""NÍVEL INCOMPLETO"", IFERROR(INDEX(FILTER(DADOS_RM_SECOES!D:D, DADOS_RM_SECOES!A:A=E27, DADOS_RM_SECOES!B:B=F27, DADOS_RM_SECOES!C:C=G2"&"7), 1), ""Não Encontrado""))) "),"NÍVEL INCOMPLETO") -> NÍVEL INCOMPLETO
A28: 0004 | B28: 0001 | C28: 002010601 | D28: AJUDANTE DE CAÇAMBA - SER I | E28: 1 | F28: 1 | G28: 001.03.002.01 | H28: =IFERROR(__xludf.DUMMYFUNCTION("IF(G28="""", """", IF(COUNTIFS(DADOS_RM_SECOES!A:A, E28, DADOS_RM_SECOES!B:B, F28, DADOS_RM_SECOES!C:C, G28&"".*"")>0, ""NÍVEL INCOMPLETO"", IFERROR(INDEX(FILTER(DADOS_RM_SECOES!D:D, DADOS_RM_SECOES!A:A=E28, DADOS_RM_SECOES!B:B=F28, DADOS_RM_SECOES!C:C=G2"&"8), 1), ""Não Encontrado""))) "),"REGIONAL I") -> REGIONAL I
A29: 0004 | B29: 0001 | C29: 002010602 | D29: AJUDANTE DE CAÇAMBA - SER II | E29: 1 | F29: 1 | G29: 001.03.002.02 | H29: =IFERROR(__xludf.DUMMYFUNCTION("IF(G29="""", """", IF(COUNTIFS(DADOS_RM_SECOES!A:A, E29, DADOS_RM_SECOES!B:B, F29, DADOS_RM_SECOES!C:C, G29&"".*"")>0, ""NÍVEL INCOMPLETO"", IFERROR(INDEX(FILTER(DADOS_RM_SECOES!D:D, DADOS_RM_SECOES!A:A=E29, DADOS_RM_SECOES!B:B=F29, DADOS_RM_SECOES!C:C=G2"&"9), 1), ""Não Encontrado""))) "),"REGIONAL II") -> REGIONAL II
A30: 0004 | B30: 0001 | C30: 002010603 | D30: AJUDANTE DE CAÇAMBA - SER III | E30: 1 | F30: 1 | G30: 001.03.002.03 | H30: =IFERROR(__xludf.DUMMYFUNCTION("IF(G30="""", """", IF(COUNTIFS(DADOS_RM_SECOES!A:A, E30, DADOS_RM_SECOES!B:B, F30, DADOS_RM_SECOES!C:C, G30&"".*"")>0, ""NÍVEL INCOMPLETO"", IFERROR(INDEX(FILTER(DADOS_RM_SECOES!D:D, DADOS_RM_SECOES!A:A=E30, DADOS_RM_SECOES!B:B=F30, DADOS_RM_SECOES!C:C=G3"&"0), 1), ""Não Encontrado""))) "),"REGIONAL III") -> REGIONAL III
A31: 0004 | B31: 0001 | C31: 002010604 | D31: AJUDANTE DE CAÇAMBA - SER IV | E31: 1 | F31: 1 | G31: 001.03.002.04 | H31: =IFERROR(__xludf.DUMMYFUNCTION("IF(G31="""", """", IF(COUNTIFS(DADOS_RM_SECOES!A:A, E31, DADOS_RM_SECOES!B:B, F31, DADOS_RM_SECOES!C:C, G31&"".*"")>0, ""NÍVEL INCOMPLETO"", IFERROR(INDEX(FILTER(DADOS_RM_SECOES!D:D, DADOS_RM_SECOES!A:A=E31, DADOS_RM_SECOES!B:B=F31, DADOS_RM_SECOES!C:C=G3"&"1), 1), ""Não Encontrado""))) "),"REGIONAL IV") -> REGIONAL IV
A32: 0004 | B32: 0001 | C32: 002010605 | D32: AJUDANTE DE CAÇAMBA - SER V | E32: 1 | F32: 1 | G32: 001.03.002.05 | H32: =IFERROR(__xludf.DUMMYFUNCTION("IF(G32="""", """", IF(COUNTIFS(DADOS_RM_SECOES!A:A, E32, DADOS_RM_SECOES!B:B, F32, DADOS_RM_SECOES!C:C, G32&"".*"")>0, ""NÍVEL INCOMPLETO"", IFERROR(INDEX(FILTER(DADOS_RM_SECOES!D:D, DADOS_RM_SECOES!A:A=E32, DADOS_RM_SECOES!B:B=F32, DADOS_RM_SECOES!C:C=G3"&"2), 1), ""Não Encontrado""))) "),"REGIONAL V") -> REGIONAL V
A33: 0004 | B33: 0001 | C33: 002010606 | D33: AJUDANTE DE CAÇAMBA - SER VI | E33: 1 | F33: 1 | G33: 001.03.002.06 | H33: =IFERROR(__xludf.DUMMYFUNCTION("IF(G33="""", """", IF(COUNTIFS(DADOS_RM_SECOES!A:A, E33, DADOS_RM_SECOES!B:B, F33, DADOS_RM_SECOES!C:C, G33&"".*"")>0, ""NÍVEL INCOMPLETO"", IFERROR(INDEX(FILTER(DADOS_RM_SECOES!D:D, DADOS_RM_SECOES!A:A=E33, DADOS_RM_SECOES!B:B=F33, DADOS_RM_SECOES!C:C=G3"&"3), 1), ""Não Encontrado""))) "),"REGIONAL VI") -> REGIONAL VI
A34: 0004 | B34: 0001 | C34: 0020106071 | D34: (S/M) AJUDANTE DE CAÇAMBA - SER N-1 | E34: 1 | F34: 1 | G34: 001.03.002.01 | H34: =IFERROR(__xludf.DUMMYFUNCTION("IF(G34="""", """", IF(COUNTIFS(DADOS_RM_SECOES!A:A, E34, DADOS_RM_SECOES!B:B, F34, DADOS_RM_SECOES!C:C, G34&"".*"")>0, ""NÍVEL INCOMPLETO"", IFERROR(INDEX(FILTER(DADOS_RM_SECOES!D:D, DADOS_RM_SECOES!A:A=E34, DADOS_RM_SECOES!B:B=F34, DADOS_RM_SECOES!C:C=G3"&"4), 1), ""Não Encontrado""))) "),"REGIONAL I") -> REGIONAL I
A35: 0004 | B35: 0001 | C35: 0020106072 | D35: AJUDANTE DE CAÇAMBA - SER N-2 | E35: 1 | F35: 1 | G35: 001.03.002.01 | H35: =IFERROR(__xludf.DUMMYFUNCTION("IF(G35="""", """", IF(COUNTIFS(DADOS_RM_SECOES!A:A, E35, DADOS_RM_SECOES!B:B, F35, DADOS_RM_SECOES!C:C, G35&"".*"")>0, ""NÍVEL INCOMPLETO"", IFERROR(INDEX(FILTER(DADOS_RM_SECOES!D:D, DADOS_RM_SECOES!A:A=E35, DADOS_RM_SECOES!B:B=F35, DADOS_RM_SECOES!C:C=G3"&"5), 1), ""Não Encontrado""))) "),"REGIONAL I") -> REGIONAL I
A36: 0004 | B36: 0001 | C36: 0020106073 | D36: (S/M) AJUDANTE DE CAÇAMBA - SER N-3 | E36: 1 | F36: 1 | G36: 001.03.002.03 | H36: =IFERROR(__xludf.DUMMYFUNCTION("IF(G36="""", """", IF(COUNTIFS(DADOS_RM_SECOES!A:A, E36, DADOS_RM_SECOES!B:B, F36, DADOS_RM_SECOES!C:C, G36&"".*"")>0, ""NÍVEL INCOMPLETO"", IFERROR(INDEX(FILTER(DADOS_RM_SECOES!D:D, DADOS_RM_SECOES!A:A=E36, DADOS_RM_SECOES!B:B=F36, DADOS_RM_SECOES!C:C=G3"&"6), 1), ""Não Encontrado""))) "),"REGIONAL III") -> REGIONAL III
A37: 0004 | B37: 0001 | C37: 0020106074 | D37: (S/M) AJUDANTE DE CAÇAMBA - SER N-4 | E37: 1 | F37: 1 | G37: 001.03.002.04 | H37: =IFERROR(__xludf.DUMMYFUNCTION("IF(G37="""", """", IF(COUNTIFS(DADOS_RM_SECOES!A:A, E37, DADOS_RM_SECOES!B:B, F37, DADOS_RM_SECOES!C:C, G37&"".*"")>0, ""NÍVEL INCOMPLETO"", IFERROR(INDEX(FILTER(DADOS_RM_SECOES!D:D, DADOS_RM_SECOES!A:A=E37, DADOS_RM_SECOES!B:B=F37, DADOS_RM_SECOES!C:C=G3"&"7), 1), ""Não Encontrado""))) "),"REGIONAL IV") -> REGIONAL IV
A38: 0004 | B38: 0001 | C38: 002010608 | D38: ECOPONTO | E38: 1 | F38: 1 | G38: 001.03.002.08 | H38: =IFERROR(__xludf.DUMMYFUNCTION("IF(G38="""", """", IF(COUNTIFS(DADOS_RM_SECOES!A:A, E38, DADOS_RM_SECOES!B:B, F38, DADOS_RM_SECOES!C:C, G38&"".*"")>0, ""NÍVEL INCOMPLETO"", IFERROR(INDEX(FILTER(DADOS_RM_SECOES!D:D, DADOS_RM_SECOES!A:A=E38, DADOS_RM_SECOES!B:B=F38, DADOS_RM_SECOES!C:C=G3"&"8), 1), ""Não Encontrado""))) "),"ECOPONTO") -> ECOPONTO
A39: 0004 | B39: 0001 | C39: 002010609 | D39: NOITE | E39: 1 | F39: 1 | G39: 001.03.002.07 | H39: =IFERROR(__xludf.DUMMYFUNCTION("IF(G39="""", """", IF(COUNTIFS(DADOS_RM_SECOES!A:A, E39, DADOS_RM_SECOES!B:B, F39, DADOS_RM_SECOES!C:C, G39&"".*"")>0, ""NÍVEL INCOMPLETO"", IFERROR(INDEX(FILTER(DADOS_RM_SECOES!D:D, DADOS_RM_SECOES!A:A=E39, DADOS_RM_SECOES!B:B=F39, DADOS_RM_SECOES!C:C=G3"&"9), 1), ""Não Encontrado""))) "),"REGIONAL NOITE") -> REGIONAL NOITE
A40: 0004 | B40: 0001 | C40: 002010611 | D40: FROTA - MOTORISTAS | E40: 1 | F40: 1 | G40: 001.01.002 | H40: =IFERROR(__xludf.DUMMYFUNCTION("IF(G40="""", """", IF(COUNTIFS(DADOS_RM_SECOES!A:A, E40, DADOS_RM_SECOES!B:B, F40, DADOS_RM_SECOES!C:C, G40&"".*"")>0, ""NÍVEL INCOMPLETO"", IFERROR(INDEX(FILTER(DADOS_RM_SECOES!D:D, DADOS_RM_SECOES!A:A=E40, DADOS_RM_SECOES!B:B=F40, DADOS_RM_SECOES!C:C=G4"&"0), 1), ""Não Encontrado""))) "),"NÍVEL INCOMPLETO") -> NÍVEL INCOMPLETO
A41: 0004 | B41: 0001 | C41: 002010620 | D41: AJUDANTE DE CAÇAMBA - SCSP | E41: 1 | F41: 1 | H41: =IFERROR(__xludf.DUMMYFUNCTION("IF(G41="""", """", IF(COUNTIFS(DADOS_RM_SECOES!A:A, E41, DADOS_RM_SECOES!B:B, F41, DADOS_RM_SECOES!C:C, G41&"".*"")>0, ""NÍVEL INCOMPLETO"", IFERROR(INDEX(FILTER(DADOS_RM_SECOES!D:D, DADOS_RM_SECOES!A:A=E41, DADOS_RM_SECOES!B:B=F41, DADOS_RM_SECOES!C:C=G4"&"1), 1), ""Não Encontrado""))) "),"")
A42: 0004 | B42: 0001 | C42: 002010701 | D42: (S/M) (OLD) GARI - SER II (NÃO USAR) | E42: 1 | F42: 1 | G42: 001.03.002.02 | H42: =IFERROR(__xludf.DUMMYFUNCTION("IF(G42="""", """", IF(COUNTIFS(DADOS_RM_SECOES!A:A, E42, DADOS_RM_SECOES!B:B, F42, DADOS_RM_SECOES!C:C, G42&"".*"")>0, ""NÍVEL INCOMPLETO"", IFERROR(INDEX(FILTER(DADOS_RM_SECOES!D:D, DADOS_RM_SECOES!A:A=E42, DADOS_RM_SECOES!B:B=F42, DADOS_RM_SECOES!C:C=G4"&"2), 1), ""Não Encontrado""))) "),"REGIONAL II") -> REGIONAL II
A43: 0004 | B43: 0001 | C43: 002010702 | D43: (S/M) (OLD) FISCAL - SER II (NÃO USAR) | E43: 1 | F43: 1 | G43: 001.03.002.02 | H43: =IFERROR(__xludf.DUMMYFUNCTION("IF(G43="""", """", IF(COUNTIFS(DADOS_RM_SECOES!A:A, E43, DADOS_RM_SECOES!B:B, F43, DADOS_RM_SECOES!C:C, G43&"".*"")>0, ""NÍVEL INCOMPLETO"", IFERROR(INDEX(FILTER(DADOS_RM_SECOES!D:D, DADOS_RM_SECOES!A:A=E43, DADOS_RM_SECOES!B:B=F43, DADOS_RM_SECOES!C:C=G4"&"3), 1), ""Não Encontrado""))) "),"REGIONAL II") -> REGIONAL II
A44: 0004 | B44: 0001 | C44: 002010801 | D44: (S/M) (OLD) GARI - SER III (NÃO USAR) | E44: 1 | F44: 1 | G44: 001.03.002.03 | H44: =IFERROR(__xludf.DUMMYFUNCTION("IF(G44="""", """", IF(COUNTIFS(DADOS_RM_SECOES!A:A, E44, DADOS_RM_SECOES!B:B, F44, DADOS_RM_SECOES!C:C, G44&"".*"")>0, ""NÍVEL INCOMPLETO"", IFERROR(INDEX(FILTER(DADOS_RM_SECOES!D:D, DADOS_RM_SECOES!A:A=E44, DADOS_RM_SECOES!B:B=F44, DADOS_RM_SECOES!C:C=G4"&"4), 1), ""Não Encontrado""))) "),"REGIONAL III") -> REGIONAL III
A45: 0004 | B45: 0001 | C45: 002010802 | D45: (S/M) (OLD) FISCAL - SER III (NÃO USAR) | E45: 1 | F45: 1 | G45: 001.03.002.03 | H45: =IFERROR(__xludf.DUMMYFUNCTION("IF(G45="""", """", IF(COUNTIFS(DADOS_RM_SECOES!A:A, E45, DADOS_RM_SECOES!B:B, F45, DADOS_RM_SECOES!C:C, G45&"".*"")>0, ""NÍVEL INCOMPLETO"", IFERROR(INDEX(FILTER(DADOS_RM_SECOES!D:D, DADOS_RM_SECOES!A:A=E45, DADOS_RM_SECOES!B:B=F45, DADOS_RM_SECOES!C:C=G4"&"5), 1), ""Não Encontrado""))) "),"REGIONAL III") -> REGIONAL III
A46: 0004 | B46: 0001 | C46: 002010901 | D46: (S/M) (OLD) GARI - SER IV (NÃO USAR) | E46: 1 | F46: 1 | G46: 001.03.002.04 | H46: =IFERROR(__xludf.DUMMYFUNCTION("IF(G46="""", """", IF(COUNTIFS(DADOS_RM_SECOES!A:A, E46, DADOS_RM_SECOES!B:B, F46, DADOS_RM_SECOES!C:C, G46&"".*"")>0, ""NÍVEL INCOMPLETO"", IFERROR(INDEX(FILTER(DADOS_RM_SECOES!D:D, DADOS_RM_SECOES!A:A=E46, DADOS_RM_SECOES!B:B=F46, DADOS_RM_SECOES!C:C=G4"&"6), 1), ""Não Encontrado""))) "),"REGIONAL IV") -> REGIONAL IV
A47: 0004 | B47: 0001 | C47: 002010902 | D47: (S/M) (OLD) FISCAL - SER IV (NÃO USAR) | E47: 1 | F47: 1 | G47: 001.03.002.04 | H47: =IFERROR(__xludf.DUMMYFUNCTION("IF(G47="""", """", IF(COUNTIFS(DADOS_RM_SECOES!A:A, E47, DADOS_RM_SECOES!B:B, F47, DADOS_RM_SECOES!C:C, G47&"".*"")>0, ""NÍVEL INCOMPLETO"", IFERROR(INDEX(FILTER(DADOS_RM_SECOES!D:D, DADOS_RM_SECOES!A:A=E47, DADOS_RM_SECOES!B:B=F47, DADOS_RM_SECOES!C:C=G4"&"7), 1), ""Não Encontrado""))) "),"REGIONAL IV") -> REGIONAL IV
A48: 0004 | B48: 0001 | C48: 002011001 | D48: (S/M) (OLD) GARI - SER V (NÃO USAR) | E48: 1 | F48: 1 | G48: 001.03.002.05 | H48: =IFERROR(__xludf.DUMMYFUNCTION("IF(G48="""", """", IF(COUNTIFS(DADOS_RM_SECOES!A:A, E48, DADOS_RM_SECOES!B:B, F48, DADOS_RM_SECOES!C:C, G48&"".*"")>0, ""NÍVEL INCOMPLETO"", IFERROR(INDEX(FILTER(DADOS_RM_SECOES!D:D, DADOS_RM_SECOES!A:A=E48, DADOS_RM_SECOES!B:B=F48, DADOS_RM_SECOES!C:C=G4"&"8), 1), ""Não Encontrado""))) "),"REGIONAL V") -> REGIONAL V
A49: 0004 | B49: 0001 | C49: 002011002 | D49: (S/M) (OLD) FISCAL - SER V (NÃO USAR) | E49: 1 | F49: 1 | G49: 001.03.002.05 | H49: =IFERROR(__xludf.DUMMYFUNCTION("IF(G49="""", """", IF(COUNTIFS(DADOS_RM_SECOES!A:A, E49, DADOS_RM_SECOES!B:B, F49, DADOS_RM_SECOES!C:C, G49&"".*"")>0, ""NÍVEL INCOMPLETO"", IFERROR(INDEX(FILTER(DADOS_RM_SECOES!D:D, DADOS_RM_SECOES!A:A=E49, DADOS_RM_SECOES!B:B=F49, DADOS_RM_SECOES!C:C=G4"&"9), 1), ""Não Encontrado""))) "),"REGIONAL V") -> REGIONAL V
A50: 0004 | B50: 0001 | C50: 002011101 | D50: (S/M) (OLD) GARI - SER VI (NÃO USAR) | E50: 1 | F50: 1 | G50: 001.03.002.06 | H50: =IFERROR(__xludf.DUMMYFUNCTION("IF(G50="""", """", IF(COUNTIFS(DADOS_RM_SECOES!A:A, E50, DADOS_RM_SECOES!B:B, F50, DADOS_RM_SECOES!C:C, G50&"".*"")>0, ""NÍVEL INCOMPLETO"", IFERROR(INDEX(FILTER(DADOS_RM_SECOES!D:D, DADOS_RM_SECOES!A:A=E50, DADOS_RM_SECOES!B:B=F50, DADOS_RM_SECOES!C:C=G5"&"0), 1), ""Não Encontrado""))) "),"REGIONAL VI") -> REGIONAL VI
A51: 0004 | B51: 0001 | C51: 002011102 | D51: (S/M) (OLD) FISCAL - SER VI (NÃO USAR) | E51: 1 | F51: 1 | G51: 001.03.002.06 | H51: =IFERROR(__xludf.DUMMYFUNCTION("IF(G51="""", """", IF(COUNTIFS(DADOS_RM_SECOES!A:A, E51, DADOS_RM_SECOES!B:B, F51, DADOS_RM_SECOES!C:C, G51&"".*"")>0, ""NÍVEL INCOMPLETO"", IFERROR(INDEX(FILTER(DADOS_RM_SECOES!D:D, DADOS_RM_SECOES!A:A=E51, DADOS_RM_SECOES!B:B=F51, DADOS_RM_SECOES!C:C=G5"&"1), 1), ""Não Encontrado""))) "),"REGIONAL VI") -> REGIONAL VI
A52: 0004 | B52: 0001 | C52: 002011103 | D52: (S/M) (OLD) ANTIGA GARI - SER VI - 2 (NÃO USAR) | E52: 1 | F52: 1 | G52: 001.03.002.06 | H52: =IFERROR(__xludf.DUMMYFUNCTION("IF(G52="""", """", IF(COUNTIFS(DADOS_RM_SECOES!A:A, E52, DADOS_RM_SECOES!B:B, F52, DADOS_RM_SECOES!C:C, G52&"".*"")>0, ""NÍVEL INCOMPLETO"", IFERROR(INDEX(FILTER(DADOS_RM_SECOES!D:D, DADOS_RM_SECOES!A:A=E52, DADOS_RM_SECOES!B:B=F52, DADOS_RM_SECOES!C:C=G5"&"2), 1), ""Não Encontrado""))) "),"REGIONAL VI") -> REGIONAL VI
A53: 0004 | B53: 0001 | C53: 002011104 | D53: (S/M) (OLD) ANTIGA FISCAL - SER VI - 2 (NÃO USAR) | E53: 1 | F53: 1 | G53: 001.03.002.06 | H53: =IFERROR(__xludf.DUMMYFUNCTION("IF(G53="""", """", IF(COUNTIFS(DADOS_RM_SECOES!A:A, E53, DADOS_RM_SECOES!B:B, F53, DADOS_RM_SECOES!C:C, G53&"".*"")>0, ""NÍVEL INCOMPLETO"", IFERROR(INDEX(FILTER(DADOS_RM_SECOES!D:D, DADOS_RM_SECOES!A:A=E53, DADOS_RM_SECOES!B:B=F53, DADOS_RM_SECOES!C:C=G5"&"3), 1), ""Não Encontrado""))) "),"REGIONAL VI") -> REGIONAL VI
A54: 0004 | B54: 0001 | C54: 002011201 | D54: (S/M) (OLD) GARI - SER N - 1 (NÃO USAR) | E54: 1 | F54: 1 | G54: 001.03.002.01 | H54: =IFERROR(__xludf.DUMMYFUNCTION("IF(G54="""", """", IF(COUNTIFS(DADOS_RM_SECOES!A:A, E54, DADOS_RM_SECOES!B:B, F54, DADOS_RM_SECOES!C:C, G54&"".*"")>0, ""NÍVEL INCOMPLETO"", IFERROR(INDEX(FILTER(DADOS_RM_SECOES!D:D, DADOS_RM_SECOES!A:A=E54, DADOS_RM_SECOES!B:B=F54, DADOS_RM_SECOES!C:C=G5"&"4), 1), ""Não Encontrado""))) "),"REGIONAL I") -> REGIONAL I
A55: 0004 | B55: 0001 | C55: 002011202 | D55: (S/M) (OLD) FISCAL - SER N - 1 (NÃO USAR) | E55: 1 | F55: 1 | G55: 001.03.002.01 | H55: =IFERROR(__xludf.DUMMYFUNCTION("IF(G55="""", """", IF(COUNTIFS(DADOS_RM_SECOES!A:A, E55, DADOS_RM_SECOES!B:B, F55, DADOS_RM_SECOES!C:C, G55&"".*"")>0, ""NÍVEL INCOMPLETO"", IFERROR(INDEX(FILTER(DADOS_RM_SECOES!D:D, DADOS_RM_SECOES!A:A=E55, DADOS_RM_SECOES!B:B=F55, DADOS_RM_SECOES!C:C=G5"&"5), 1), ""Não Encontrado""))) "),"REGIONAL I") -> REGIONAL I
A56: 0004 | B56: 0001 | C56: 002011203 | D56: (S/M) (OLD) GARI - SER N - 2 (NÃO USAR) | E56: 1 | F56: 1 | G56: 001.03.002.02 | H56: =IFERROR(__xludf.DUMMYFUNCTION("IF(G56="""", """", IF(COUNTIFS(DADOS_RM_SECOES!A:A, E56, DADOS_RM_SECOES!B:B, F56, DADOS_RM_SECOES!C:C, G56&"".*"")>0, ""NÍVEL INCOMPLETO"", IFERROR(INDEX(FILTER(DADOS_RM_SECOES!D:D, DADOS_RM_SECOES!A:A=E56, DADOS_RM_SECOES!B:B=F56, DADOS_RM_SECOES!C:C=G5"&"6), 1), ""Não Encontrado""))) "),"REGIONAL II") -> REGIONAL II
A57: 0004 | B57: 0001 | C57: 002011205 | D57: (S/M) (OLD) GARI - SER N - 3 (NÃO USAR) | E57: 1 | F57: 1 | G57: 001.03.002.03 | H57: =IFERROR(__xludf.DUMMYFUNCTION("IF(G57="""", """", IF(COUNTIFS(DADOS_RM_SECOES!A:A, E57, DADOS_RM_SECOES!B:B, F57, DADOS_RM_SECOES!C:C, G57&"".*"")>0, ""NÍVEL INCOMPLETO"", IFERROR(INDEX(FILTER(DADOS_RM_SECOES!D:D, DADOS_RM_SECOES!A:A=E57, DADOS_RM_SECOES!B:B=F57, DADOS_RM_SECOES!C:C=G5"&"7), 1), ""Não Encontrado""))) "),"REGIONAL III") -> REGIONAL III
A58: 0004 | B58: 0001 | C58: 002011206 | D58: (S/M) (OLD) FISCAL - SER N - 3 (NÃO USAR) | E58: 1 | F58: 1 | G58: 001.03.002.03 | H58: =IFERROR(__xludf.DUMMYFUNCTION("IF(G58="""", """", IF(COUNTIFS(DADOS_RM_SECOES!A:A, E58, DADOS_RM_SECOES!B:B, F58, DADOS_RM_SECOES!C:C, G58&"".*"")>0, ""NÍVEL INCOMPLETO"", IFERROR(INDEX(FILTER(DADOS_RM_SECOES!D:D, DADOS_RM_SECOES!A:A=E58, DADOS_RM_SECOES!B:B=F58, DADOS_RM_SECOES!C:C=G5"&"8), 1), ""Não Encontrado""))) "),"REGIONAL III") -> REGIONAL III
A59: 0004 | B59: 0001 | C59: 0020113 | D59: (S/M) S G ESPECIAL | E59: 1 | F59: 1 | H59: =IFERROR(__xludf.DUMMYFUNCTION("IF(G59="""", """", IF(COUNTIFS(DADOS_RM_SECOES!A:A, E59, DADOS_RM_SECOES!B:B, F59, DADOS_RM_SECOES!C:C, G59&"".*"")>0, ""NÍVEL INCOMPLETO"", IFERROR(INDEX(FILTER(DADOS_RM_SECOES!D:D, DADOS_RM_SECOES!A:A=E59, DADOS_RM_SECOES!B:B=F59, DADOS_RM_SECOES!C:C=G5"&"9), 1), ""Não Encontrado""))) "),"")
A60: 0004 | B60: 0001 | C60: 002011401 | D60: GARI MNUS | E60: 1 | F60: 1 | H60: =IFERROR(__xludf.DUMMYFUNCTION("IF(G60="""", """", IF(COUNTIFS(DADOS_RM_SECOES!A:A, E60, DADOS_RM_SECOES!B:B, F60, DADOS_RM_SECOES!C:C, G60&"".*"")>0, ""NÍVEL INCOMPLETO"", IFERROR(INDEX(FILTER(DADOS_RM_SECOES!D:D, DADOS_RM_SECOES!A:A=E60, DADOS_RM_SECOES!B:B=F60, DADOS_RM_SECOES!C:C=G6"&"0), 1), ""Não Encontrado""))) "),"")
A61: 0004 | B61: 0001 | C61: 002011402 | D61: (S/M) FISCAL - MANAUS | E61: 1 | F61: 1 | H61: =IFERROR(__xludf.DUMMYFUNCTION("IF(G61="""", """", IF(COUNTIFS(DADOS_RM_SECOES!A:A, E61, DADOS_RM_SECOES!B:B, F61, DADOS_RM_SECOES!C:C, G61&"".*"")>0, ""NÍVEL INCOMPLETO"", IFERROR(INDEX(FILTER(DADOS_RM_SECOES!D:D, DADOS_RM_SECOES!A:A=E61, DADOS_RM_SECOES!B:B=F61, DADOS_RM_SECOES!C:C=G6"&"1), 1), ""Não Encontrado""))) "),"")
A62: 0004 | B62: 0001 | C62: 002011403 | D62: ADM MANAUS | E62: 1 | F62: 1 | H62: =IFERROR(__xludf.DUMMYFUNCTION("IF(G62="""", """", IF(COUNTIFS(DADOS_RM_SECOES!A:A, E62, DADOS_RM_SECOES!B:B, F62, DADOS_RM_SECOES!C:C, G62&"".*"")>0, ""NÍVEL INCOMPLETO"", IFERROR(INDEX(FILTER(DADOS_RM_SECOES!D:D, DADOS_RM_SECOES!A:A=E62, DADOS_RM_SECOES!B:B=F62, DADOS_RM_SECOES!C:C=G6"&"2), 1), ""Não Encontrado""))) "),"")
A63: 0004 | B63: 0001 | C63: 002011404 | D63: (S/M) MOTORISTA MNS | E63: 1 | F63: 1 | H63: =IFERROR(__xludf.DUMMYFUNCTION("IF(G63="""", """", IF(COUNTIFS(DADOS_RM_SECOES!A:A, E63, DADOS_RM_SECOES!B:B, F63, DADOS_RM_SECOES!C:C, G63&"".*"")>0, ""NÍVEL INCOMPLETO"", IFERROR(INDEX(FILTER(DADOS_RM_SECOES!D:D, DADOS_RM_SECOES!A:A=E63, DADOS_RM_SECOES!B:B=F63, DADOS_RM_SECOES!C:C=G6"&"3), 1), ""Não Encontrado""))) "),"")
A64: 0004 | B64: 0001 | C64: 002011405 | D64: (S/M) MAQ.EQUIPAMENTOS | E64: 1 | F64: 1 | H64: =IFERROR(__xludf.DUMMYFUNCTION("IF(G64="""", """", IF(COUNTIFS(DADOS_RM_SECOES!A:A, E64, DADOS_RM_SECOES!B:B, F64, DADOS_RM_SECOES!C:C, G64&"".*"")>0, ""NÍVEL INCOMPLETO"", IFERROR(INDEX(FILTER(DADOS_RM_SECOES!D:D, DADOS_RM_SECOES!A:A=E64, DADOS_RM_SECOES!B:B=F64, DADOS_RM_SECOES!C:C=G6"&"4), 1), ""Não Encontrado""))) "),"")
A65: 0004 | B65: 0001 | C65: 0020115 | D65: (S/M) ESPECIAL GARIS | E65: 1 | F65: 1 | H65: =IFERROR(__xludf.DUMMYFUNCTION("IF(G65="""", """", IF(COUNTIFS(DADOS_RM_SECOES!A:A, E65, DADOS_RM_SECOES!B:B, F65, DADOS_RM_SECOES!C:C, G65&"".*"")>0, ""NÍVEL INCOMPLETO"", IFERROR(INDEX(FILTER(DADOS_RM_SECOES!D:D, DADOS_RM_SECOES!A:A=E65, DADOS_RM_SECOES!B:B=F65, DADOS_RM_SECOES!C:C=G6"&"5), 1), ""Não Encontrado""))) "),"")
A66: 0004 | B66: 0001 | C66: 0020116 | D66: (S/M) SERVIÇOS GERAIS | E66: 1 | F66: 1 | H66: =IFERROR(__xludf.DUMMYFUNCTION("IF(G66="""", """", IF(COUNTIFS(DADOS_RM_SECOES!A:A, E66, DADOS_RM_SECOES!B:B, F66, DADOS_RM_SECOES!C:C, G66&"".*"")>0, ""NÍVEL INCOMPLETO"", IFERROR(INDEX(FILTER(DADOS_RM_SECOES!D:D, DADOS_RM_SECOES!A:A=E66, DADOS_RM_SECOES!B:B=F66, DADOS_RM_SECOES!C:C=G6"&"6), 1), ""Não Encontrado""))) "),"")
A67: 0004 | B67: 0001 | C67: 002011701 | D67: (S/M) GARI | E67: 1 | F67: 1 | H67: =IFERROR(__xludf.DUMMYFUNCTION("IF(G67="""", """", IF(COUNTIFS(DADOS_RM_SECOES!A:A, E67, DADOS_RM_SECOES!B:B, F67, DADOS_RM_SECOES!C:C, G67&"".*"")>0, ""NÍVEL INCOMPLETO"", IFERROR(INDEX(FILTER(DADOS_RM_SECOES!D:D, DADOS_RM_SECOES!A:A=E67, DADOS_RM_SECOES!B:B=F67, DADOS_RM_SECOES!C:C=G6"&"7), 1), ""Não Encontrado""))) "),"")
A68: 0004 | B68: 0001 | C68: 002011702 | D68: (S/M) FISCAL | E68: 1 | F68: 1 | H68: =IFERROR(__xludf.DUMMYFUNCTION("IF(G68="""", """", IF(COUNTIFS(DADOS_RM_SECOES!A:A, E68, DADOS_RM_SECOES!B:B, F68, DADOS_RM_SECOES!C:C, G68&"".*"")>0, ""NÍVEL INCOMPLETO"", IFERROR(INDEX(FILTER(DADOS_RM_SECOES!D:D, DADOS_RM_SECOES!A:A=E68, DADOS_RM_SECOES!B:B=F68, DADOS_RM_SECOES!C:C=G6"&"8), 1), ""Não Encontrado""))) "),"")
A69: 0004 | B69: 0001 | C69: 002011703 | D69: (S/M) ADM ECOFOR (NÃO USAR) | E69: 1 | F69: 1 | H69: =IFERROR(__xludf.DUMMYFUNCTION("IF(G69="""", """", IF(COUNTIFS(DADOS_RM_SECOES!A:A, E69, DADOS_RM_SECOES!B:B, F69, DADOS_RM_SECOES!C:C, G69&"".*"")>0, ""NÍVEL INCOMPLETO"", IFERROR(INDEX(FILTER(DADOS_RM_SECOES!D:D, DADOS_RM_SECOES!A:A=E69, DADOS_RM_SECOES!B:B=F69, DADOS_RM_SECOES!C:C=G6"&"9), 1), ""Não Encontrado""))) "),"")
A70: 0004 | B70: 0001 | C70: 0020118 | D70: ADM ECOFOR (NOVO) | E70: 1 | F70: 1 | H70: =IFERROR(__xludf.DUMMYFUNCTION("IF(G70="""", """", IF(COUNTIFS(DADOS_RM_SECOES!A:A, E70, DADOS_RM_SECOES!B:B, F70, DADOS_RM_SECOES!C:C, G70&"".*"")>0, ""NÍVEL INCOMPLETO"", IFERROR(INDEX(FILTER(DADOS_RM_SECOES!D:D, DADOS_RM_SECOES!A:A=E70, DADOS_RM_SECOES!B:B=F70, DADOS_RM_SECOES!C:C=G7"&"0), 1), ""Não Encontrado""))) "),"")
A71: 0004 | B71: 0001 | C71: 0020119 | D71: (S/M) ADM ADM (NÃO USAR) | E71: 1 | F71: 1 | H71: =IFERROR(__xludf.DUMMYFUNCTION("IF(G71="""", """", IF(COUNTIFS(DADOS_RM_SECOES!A:A, E71, DADOS_RM_SECOES!B:B, F71, DADOS_RM_SECOES!C:C, G71&"".*"")>0, ""NÍVEL INCOMPLETO"", IFERROR(INDEX(FILTER(DADOS_RM_SECOES!D:D, DADOS_RM_SECOES!A:A=E71, DADOS_RM_SECOES!B:B=F71, DADOS_RM_SECOES!C:C=G7"&"1), 1), ""Não Encontrado""))) "),"")
A72: 0004 | B72: 0001 | C72: 0020201 | D72: (S/M) GERENCIA ADM-FINANCEIRA | E72: 1 | F72: 1 | H72: =IFERROR(__xludf.DUMMYFUNCTION("IF(G72="""", """", IF(COUNTIFS(DADOS_RM_SECOES!A:A, E72, DADOS_RM_SECOES!B:B, F72, DADOS_RM_SECOES!C:C, G72&"".*"")>0, ""NÍVEL INCOMPLETO"", IFERROR(INDEX(FILTER(DADOS_RM_SECOES!D:D, DADOS_RM_SECOES!A:A=E72, DADOS_RM_SECOES!B:B=F72, DADOS_RM_SECOES!C:C=G7"&"2), 1), ""Não Encontrado""))) "),"")
A73: 0004 | B73: 0001 | C73: 0020202 | D73: (S/M) RECURSOS HUMANOS | E73: 1 | F73: 1 | H73: =IFERROR(__xludf.DUMMYFUNCTION("IF(G73="""", """", IF(COUNTIFS(DADOS_RM_SECOES!A:A, E73, DADOS_RM_SECOES!B:B, F73, DADOS_RM_SECOES!C:C, G73&"".*"")>0, ""NÍVEL INCOMPLETO"", IFERROR(INDEX(FILTER(DADOS_RM_SECOES!D:D, DADOS_RM_SECOES!A:A=E73, DADOS_RM_SECOES!B:B=F73, DADOS_RM_SECOES!C:C=G7"&"3), 1), ""Não Encontrado""))) "),"")
A74: 0004 | B74: 0001 | C74: 0020203 | D74: (S/M) SETOR PESSOAL | E74: 1 | F74: 1 | H74: =IFERROR(__xludf.DUMMYFUNCTION("IF(G74="""", """", IF(COUNTIFS(DADOS_RM_SECOES!A:A, E74, DADOS_RM_SECOES!B:B, F74, DADOS_RM_SECOES!C:C, G74&"".*"")>0, ""NÍVEL INCOMPLETO"", IFERROR(INDEX(FILTER(DADOS_RM_SECOES!D:D, DADOS_RM_SECOES!A:A=E74, DADOS_RM_SECOES!B:B=F74, DADOS_RM_SECOES!C:C=G7"&"4), 1), ""Não Encontrado""))) "),"")
A75: 0004 | B75: 0001 | C75: 0020204 | D75: (S/M) CONTAS A PAGAR | E75: 1 | F75: 1 | H75: =IFERROR(__xludf.DUMMYFUNCTION("IF(G75="""", """", IF(COUNTIFS(DADOS_RM_SECOES!A:A, E75, DADOS_RM_SECOES!B:B, F75, DADOS_RM_SECOES!C:C, G75&"".*"")>0, ""NÍVEL INCOMPLETO"", IFERROR(INDEX(FILTER(DADOS_RM_SECOES!D:D, DADOS_RM_SECOES!A:A=E75, DADOS_RM_SECOES!B:B=F75, DADOS_RM_SECOES!C:C=G7"&"5), 1), ""Não Encontrado""))) "),"")
A76: 0004 | B76: 0001 | C76: 0020205 | D76: (S/M) CONTABILIDADE | E76: 1 | F76: 1 | H76: =IFERROR(__xludf.DUMMYFUNCTION("IF(G76="""", """", IF(COUNTIFS(DADOS_RM_SECOES!A:A, E76, DADOS_RM_SECOES!B:B, F76, DADOS_RM_SECOES!C:C, G76&"".*"")>0, ""NÍVEL INCOMPLETO"", IFERROR(INDEX(FILTER(DADOS_RM_SECOES!D:D, DADOS_RM_SECOES!A:A=E76, DADOS_RM_SECOES!B:B=F76, DADOS_RM_SECOES!C:C=G7"&"6), 1), ""Não Encontrado""))) "),"")
A77: 0004 | B77: 0001 | C77: 0020301 | D77: ADM SGLO | E77: 1 | F77: 1 | H77: =IFERROR(__xludf.DUMMYFUNCTION("IF(G77="""", """", IF(COUNTIFS(DADOS_RM_SECOES!A:A, E77, DADOS_RM_SECOES!B:B, F77, DADOS_RM_SECOES!C:C, G77&"".*"")>0, ""NÍVEL INCOMPLETO"", IFERROR(INDEX(FILTER(DADOS_RM_SECOES!D:D, DADOS_RM_SECOES!A:A=E77, DADOS_RM_SECOES!B:B=F77, DADOS_RM_SECOES!C:C=G7"&"7), 1), ""Não Encontrado""))) "),"")
A78: 0004 | B78: 0001 | C78: 0020302 | D78: GARI SGLO | E78: 1 | F78: 1 | H78: =IFERROR(__xludf.DUMMYFUNCTION("IF(G78="""", """", IF(COUNTIFS(DADOS_RM_SECOES!A:A, E78, DADOS_RM_SECOES!B:B, F78, DADOS_RM_SECOES!C:C, G78&"".*"")>0, ""NÍVEL INCOMPLETO"", IFERROR(INDEX(FILTER(DADOS_RM_SECOES!D:D, DADOS_RM_SECOES!A:A=E78, DADOS_RM_SECOES!B:B=F78, DADOS_RM_SECOES!C:C=G7"&"8), 1), ""Não Encontrado""))) "),"")
A79: 0004 | B79: 0001 | C79: 00204 | D79: (S/M) POSTO | E79: 1 | F79: 1 | H79: =IFERROR(__xludf.DUMMYFUNCTION("IF(G79="""", """", IF(COUNTIFS(DADOS_RM_SECOES!A:A, E79, DADOS_RM_SECOES!B:B, F79, DADOS_RM_SECOES!C:C, G79&"".*"")>0, ""NÍVEL INCOMPLETO"", IFERROR(INDEX(FILTER(DADOS_RM_SECOES!D:D, DADOS_RM_SECOES!A:A=E79, DADOS_RM_SECOES!B:B=F79, DADOS_RM_SECOES!C:C=G7"&"9), 1), ""Não Encontrado""))) "),"")
A80: 0004 | B80: 0001 | C80: 00205 | D80: (S/M) JANGURUSSU | E80: 1 | F80: 1 | H80: =IFERROR(__xludf.DUMMYFUNCTION("IF(G80="""", """", IF(COUNTIFS(DADOS_RM_SECOES!A:A, E80, DADOS_RM_SECOES!B:B, F80, DADOS_RM_SECOES!C:C, G80&"".*"")>0, ""NÍVEL INCOMPLETO"", IFERROR(INDEX(FILTER(DADOS_RM_SECOES!D:D, DADOS_RM_SECOES!A:A=E80, DADOS_RM_SECOES!B:B=F80, DADOS_RM_SECOES!C:C=G8"&"0), 1), ""Não Encontrado""))) "),"")
A81: 0004 | B81: 0001 | C81: 00301 | D81: (S/M) ADMINISTRAÇÃO | E81: 1 | F81: 1 | H81: =IFERROR(__xludf.DUMMYFUNCTION("IF(G81="""", """", IF(COUNTIFS(DADOS_RM_SECOES!A:A, E81, DADOS_RM_SECOES!B:B, F81, DADOS_RM_SECOES!C:C, G81&"".*"")>0, ""NÍVEL INCOMPLETO"", IFERROR(INDEX(FILTER(DADOS_RM_SECOES!D:D, DADOS_RM_SECOES!A:A=E81, DADOS_RM_SECOES!B:B=F81, DADOS_RM_SECOES!C:C=G8"&"1), 1), ""Não Encontrado""))) "),"")
A82: 0004 | B82: 0001 | C82: 00302 | D82: (S/M) COORDENAÇÃO | E82: 1 | F82: 1 | H82: =IFERROR(__xludf.DUMMYFUNCTION("IF(G82="""", """", IF(COUNTIFS(DADOS_RM_SECOES!A:A, E82, DADOS_RM_SECOES!B:B, F82, DADOS_RM_SECOES!C:C, G82&"".*"")>0, ""NÍVEL INCOMPLETO"", IFERROR(INDEX(FILTER(DADOS_RM_SECOES!D:D, DADOS_RM_SECOES!A:A=E82, DADOS_RM_SECOES!B:B=F82, DADOS_RM_SECOES!C:C=G8"&"2), 1), ""Não Encontrado""))) "),"")
A83: 0004 | B83: 0001 | C83: 00306 | D83: (S/M) PEDREIROS | E83: 1 | F83: 1 | H83: =IFERROR(__xludf.DUMMYFUNCTION("IF(G83="""", """", IF(COUNTIFS(DADOS_RM_SECOES!A:A, E83, DADOS_RM_SECOES!B:B, F83, DADOS_RM_SECOES!C:C, G83&"".*"")>0, ""NÍVEL INCOMPLETO"", IFERROR(INDEX(FILTER(DADOS_RM_SECOES!D:D, DADOS_RM_SECOES!A:A=E83, DADOS_RM_SECOES!B:B=F83, DADOS_RM_SECOES!C:C=G8"&"3), 1), ""Não Encontrado""))) "),"")
A84: 0004 | B84: 0001 | C84: 00401 | D84: (S/M) ADMINISTRAÇÃO | E84: 1 | F84: 1 | H84: =IFERROR(__xludf.DUMMYFUNCTION("IF(G84="""", """", IF(COUNTIFS(DADOS_RM_SECOES!A:A, E84, DADOS_RM_SECOES!B:B, F84, DADOS_RM_SECOES!C:C, G84&"".*"")>0, ""NÍVEL INCOMPLETO"", IFERROR(INDEX(FILTER(DADOS_RM_SECOES!D:D, DADOS_RM_SECOES!A:A=E84, DADOS_RM_SECOES!B:B=F84, DADOS_RM_SECOES!C:C=G8"&"4), 1), ""Não Encontrado""))) "),"")
A85: 0004 | B85: 0001 | C85: 00501 | D85: (S/M) ADMINISTRAÇÃO | E85: 1 | F85: 1 | H85: =IFERROR(__xludf.DUMMYFUNCTION("IF(G85="""", """", IF(COUNTIFS(DADOS_RM_SECOES!A:A, E85, DADOS_RM_SECOES!B:B, F85, DADOS_RM_SECOES!C:C, G85&"".*"")>0, ""NÍVEL INCOMPLETO"", IFERROR(INDEX(FILTER(DADOS_RM_SECOES!D:D, DADOS_RM_SECOES!A:A=E85, DADOS_RM_SECOES!B:B=F85, DADOS_RM_SECOES!C:C=G8"&"5), 1), ""Não Encontrado""))) "),"")
A86: 0004 | B86: 0001 | C86: 00503 | D86: (S/M) SERVIÇOS GERAIS | E86: 1 | F86: 1 | H86: =IFERROR(__xludf.DUMMYFUNCTION("IF(G86="""", """", IF(COUNTIFS(DADOS_RM_SECOES!A:A, E86, DADOS_RM_SECOES!B:B, F86, DADOS_RM_SECOES!C:C, G86&"".*"")>0, ""NÍVEL INCOMPLETO"", IFERROR(INDEX(FILTER(DADOS_RM_SECOES!D:D, DADOS_RM_SECOES!A:A=E86, DADOS_RM_SECOES!B:B=F86, DADOS_RM_SECOES!C:C=G8"&"6), 1), ""Não Encontrado""))) "),"")
A87: 0004 | B87: 0001 | C87: 00601 | D87: GERENCIA DE OBRAS | E87: 1 | F87: 1 | H87: =IFERROR(__xludf.DUMMYFUNCTION("IF(G87="""", """", IF(COUNTIFS(DADOS_RM_SECOES!A:A, E87, DADOS_RM_SECOES!B:B, F87, DADOS_RM_SECOES!C:C, G87&"".*"")>0, ""NÍVEL INCOMPLETO"", IFERROR(INDEX(FILTER(DADOS_RM_SECOES!D:D, DADOS_RM_SECOES!A:A=E87, DADOS_RM_SECOES!B:B=F87, DADOS_RM_SECOES!C:C=G8"&"7), 1), ""Não Encontrado""))) "),"")
A88: 0004 | B88: 0001 | C88: 00604 | D88: APOIO OBRA | E88: 1 | F88: 1 | H88: =IFERROR(__xludf.DUMMYFUNCTION("IF(G88="""", """", IF(COUNTIFS(DADOS_RM_SECOES!A:A, E88, DADOS_RM_SECOES!B:B, F88, DADOS_RM_SECOES!C:C, G88&"".*"")>0, ""NÍVEL INCOMPLETO"", IFERROR(INDEX(FILTER(DADOS_RM_SECOES!D:D, DADOS_RM_SECOES!A:A=E88, DADOS_RM_SECOES!B:B=F88, DADOS_RM_SECOES!C:C=G8"&"8), 1), ""Não Encontrado""))) "),"")
A89: 0004 | B89: 0001 | C89: 00605 | D89: ADMINISTRAÇÃO | E89: 1 | F89: 1 | G89: 001.01.001.01 | H89: =IFERROR(__xludf.DUMMYFUNCTION("IF(G89="""", """", IF(COUNTIFS(DADOS_RM_SECOES!A:A, E89, DADOS_RM_SECOES!B:B, F89, DADOS_RM_SECOES!C:C, G89&"".*"")>0, ""NÍVEL INCOMPLETO"", IFERROR(INDEX(FILTER(DADOS_RM_SECOES!D:D, DADOS_RM_SECOES!A:A=E89, DADOS_RM_SECOES!B:B=F89, DADOS_RM_SECOES!C:C=G8"&"9), 1), ""Não Encontrado""))) "),"ADMINISTRACAO") -> ADMINISTRACAO
A90: 0004 | B90: 0001 | C90: 00606 | D90: (S/M) FERREIRO | E90: 1 | F90: 1 | H90: =IFERROR(__xludf.DUMMYFUNCTION("IF(G90="""", """", IF(COUNTIFS(DADOS_RM_SECOES!A:A, E90, DADOS_RM_SECOES!B:B, F90, DADOS_RM_SECOES!C:C, G90&"".*"")>0, ""NÍVEL INCOMPLETO"", IFERROR(INDEX(FILTER(DADOS_RM_SECOES!D:D, DADOS_RM_SECOES!A:A=E90, DADOS_RM_SECOES!B:B=F90, DADOS_RM_SECOES!C:C=G9"&"0), 1), ""Não Encontrado""))) "),"")
A91: 0004 | B91: 0001 | C91: 00607 | D91: (S/M) ELETRICISTA | E91: 1 | F91: 1 | H91: =IFERROR(__xludf.DUMMYFUNCTION("IF(G91="""", """", IF(COUNTIFS(DADOS_RM_SECOES!A:A, E91, DADOS_RM_SECOES!B:B, F91, DADOS_RM_SECOES!C:C, G91&"".*"")>0, ""NÍVEL INCOMPLETO"", IFERROR(INDEX(FILTER(DADOS_RM_SECOES!D:D, DADOS_RM_SECOES!A:A=E91, DADOS_RM_SECOES!B:B=F91, DADOS_RM_SECOES!C:C=G9"&"1), 1), ""Não Encontrado""))) "),"")
A92: 0004 | B92: 0001 | C92: 00608 | D92: (S/M) ENCARREGADO DE SETOR | E92: 1 | F92: 1 | H92: =IFERROR(__xludf.DUMMYFUNCTION("IF(G92="""", """", IF(COUNTIFS(DADOS_RM_SECOES!A:A, E92, DADOS_RM_SECOES!B:B, F92, DADOS_RM_SECOES!C:C, G92&"".*"")>0, ""NÍVEL INCOMPLETO"", IFERROR(INDEX(FILTER(DADOS_RM_SECOES!D:D, DADOS_RM_SECOES!A:A=E92, DADOS_RM_SECOES!B:B=F92, DADOS_RM_SECOES!C:C=G9"&"2), 1), ""Não Encontrado""))) "),"")
A93: 0004 | B93: 0001 | C93: 00609 | D93: (S/M) PEDREIROS | E93: 1 | F93: 1 | H93: =IFERROR(__xludf.DUMMYFUNCTION("IF(G93="""", """", IF(COUNTIFS(DADOS_RM_SECOES!A:A, E93, DADOS_RM_SECOES!B:B, F93, DADOS_RM_SECOES!C:C, G93&"".*"")>0, ""NÍVEL INCOMPLETO"", IFERROR(INDEX(FILTER(DADOS_RM_SECOES!D:D, DADOS_RM_SECOES!A:A=E93, DADOS_RM_SECOES!B:B=F93, DADOS_RM_SECOES!C:C=G9"&"3), 1), ""Não Encontrado""))) "),"")
A94: 0004 | B94: 0001 | C94: 00610 | D94: (S/M) APOIO ADMINISTRATIVO | E94: 1 | F94: 1 | H94: =IFERROR(__xludf.DUMMYFUNCTION("IF(G94="""", """", IF(COUNTIFS(DADOS_RM_SECOES!A:A, E94, DADOS_RM_SECOES!B:B, F94, DADOS_RM_SECOES!C:C, G94&"".*"")>0, ""NÍVEL INCOMPLETO"", IFERROR(INDEX(FILTER(DADOS_RM_SECOES!D:D, DADOS_RM_SECOES!A:A=E94, DADOS_RM_SECOES!B:B=F94, DADOS_RM_SECOES!C:C=G9"&"4), 1), ""Não Encontrado""))) "),"")
A95: 0004 | B95: 0001 | C95: 00611 | D95: (S/M) CARPINTEIRO | E95: 1 | F95: 1 | H95: =IFERROR(__xludf.DUMMYFUNCTION("IF(G95="""", """", IF(COUNTIFS(DADOS_RM_SECOES!A:A, E95, DADOS_RM_SECOES!B:B, F95, DADOS_RM_SECOES!C:C, G95&"".*"")>0, ""NÍVEL INCOMPLETO"", IFERROR(INDEX(FILTER(DADOS_RM_SECOES!D:D, DADOS_RM_SECOES!A:A=E95, DADOS_RM_SECOES!B:B=F95, DADOS_RM_SECOES!C:C=G9"&"5), 1), ""Não Encontrado""))) "),"")
A96: 0004 | B96: 0001 | C96: 00612 | D96: (S/M) BOMBEIRO HIDRAULICO | E96: 1 | F96: 1 | H96: =IFERROR(__xludf.DUMMYFUNCTION("IF(G96="""", """", IF(COUNTIFS(DADOS_RM_SECOES!A:A, E96, DADOS_RM_SECOES!B:B, F96, DADOS_RM_SECOES!C:C, G96&"".*"")>0, ""NÍVEL INCOMPLETO"", IFERROR(INDEX(FILTER(DADOS_RM_SECOES!D:D, DADOS_RM_SECOES!A:A=E96, DADOS_RM_SECOES!B:B=F96, DADOS_RM_SECOES!C:C=G9"&"6), 1), ""Não Encontrado""))) "),"")
A97: 0004 | B97: 0001 | C97: 00701 | D97: (S/M) GARI | E97: 1 | F97: 1 | H97: =IFERROR(__xludf.DUMMYFUNCTION("IF(G97="""", """", IF(COUNTIFS(DADOS_RM_SECOES!A:A, E97, DADOS_RM_SECOES!B:B, F97, DADOS_RM_SECOES!C:C, G97&"".*"")>0, ""NÍVEL INCOMPLETO"", IFERROR(INDEX(FILTER(DADOS_RM_SECOES!D:D, DADOS_RM_SECOES!A:A=E97, DADOS_RM_SECOES!B:B=F97, DADOS_RM_SECOES!C:C=G9"&"7), 1), ""Não Encontrado""))) "),"")
A98: 0004 | B98: 0001 | C98: 00804 | D98: (S/M) APOIO OBRA | E98: 1 | F98: 1 | H98: =IFERROR(__xludf.DUMMYFUNCTION("IF(G98="""", """", IF(COUNTIFS(DADOS_RM_SECOES!A:A, E98, DADOS_RM_SECOES!B:B, F98, DADOS_RM_SECOES!C:C, G98&"".*"")>0, ""NÍVEL INCOMPLETO"", IFERROR(INDEX(FILTER(DADOS_RM_SECOES!D:D, DADOS_RM_SECOES!A:A=E98, DADOS_RM_SECOES!B:B=F98, DADOS_RM_SECOES!C:C=G9"&"8), 1), ""Não Encontrado""))) "),"")
A99: 0004 | B99: 0001 | C99: 00901 | D99: (S/M) APOIO OBRA | E99: 1 | F99: 1 | H99: =IFERROR(__xludf.DUMMYFUNCTION("IF(G99="""", """", IF(COUNTIFS(DADOS_RM_SECOES!A:A, E99, DADOS_RM_SECOES!B:B, F99, DADOS_RM_SECOES!C:C, G99&"".*"")>0, ""NÍVEL INCOMPLETO"", IFERROR(INDEX(FILTER(DADOS_RM_SECOES!D:D, DADOS_RM_SECOES!A:A=E99, DADOS_RM_SECOES!B:B=F99, DADOS_RM_SECOES!C:C=G9"&"9), 1), ""Não Encontrado""))) "),"")
A100: 0004 | B100: 0001 | C100: 010 | D100: OBRA GNR | E100: 1 | F100: 1 | H100: =IFERROR(__xludf.DUMMYFUNCTION("IF(G100="""", """", IF(COUNTIFS(DADOS_RM_SECOES!A:A, E100, DADOS_RM_SECOES!B:B, F100, DADOS_RM_SECOES!C:C, G100&"".*"")>0, ""NÍVEL INCOMPLETO"", IFERROR(INDEX(FILTER(DADOS_RM_SECOES!D:D, DADOS_RM_SECOES!A:A=E100, DADOS_RM_SECOES!B:B=F100, DADOS_RM_SECOES!"&"C:C=G100), 1), ""Não Encontrado""))) "),"")
...

Sheet DADOS_RM_SECOES
A1: COLIGADA | B1: FILIAL | C1: Código | D1: Descrição | E1: CNPJ | F1: CEI/CNO
A2: 1 | B2: 1 | C2: 0 | D2: LCS CONSTRUCAO E SERVICOS LTDA | E2: 05.603.629/0001-40
A3: 1 | B3: 1 | C3: 001 | D3: LCS CONSTRUCAO E SERVICOS LTDA | E3: 05.603.629/0001-40
A4: 1 | B4: 1 | C4: 001.01 | D4: ADMINISTRATIVO LCS (VISAO PROPOSTA) | E4: 05.603.629/0001-40
A5: 1 | B5: 1 | C5: 001.01.001 | D5: ADMINISTRATIVO LCS (VISAO PROPOSTA ) | E5: 05.603.629/0001-40
A6: 1 | B6: 1 | C6: 001.01.001.01 | D6: ADMINISTRACAO | E6: 05.603.629/0001-40
A7: 1 | B7: 1 | C7: 001.01.001.02 | D7: MARKETING | E7: 05.603.629/0001-40
A8: 1 | B8: 1 | C8: 001.01.001.03 | D8: RECURSOS HUMANOS | E8: 05.603.629/0001-40
A9: 1 | B9: 1 | C9: 001.01.001.04 | D9: SETOR DE PESSOAL | E9: 05.603.629/0001-40
A10: 1 | B10: 1 | C10: 001.01.001.05 | D10: FINANCEIRO | E10: 05.603.629/0001-40
A11: 1 | B11: 1 | C11: 001.01.001.06 | D11: CONTABIL | E11: 05.603.629/0001-40
A12: 1 | B12: 1 | C12: 001.01.001.07 | D12: CONTROLADORIA | E12: 05.603.629/0001-40
A13: 1 | B13: 1 | C13: 001.01.001.08 | D13: JURIDICO | E13: 05.603.629/0001-40
... A24: 1 | B24: 1 | C24: 001.02 | D24: OBRAS | E24: 05.603.629/0001-40
A25: 1 | B25: 1 | C25: 001.02.001 | D25: OBRA GUAJERU | E25: 05.603.629/0001-40 | F25: 51.314.15340/84
A26: 1 | B26: 1 | C26: 001.02.001.01 | D26: ADMINISTRACAO | E26: 05.603.629/0001-40
A27: 1 | B27: 1 | C27: 001.02.001.02 | D27: OPERACAO | E27: 05.603.629/0001-40
A28: 1 | B28: 1 | C28: 001.02.002 | D28: OBRA ASMOC | E28: 05.603.629/0001-40 | F28: 51.298.74911/87
A29: 1 | B29: 1 | C29: 001.02.002.01 | D29: ADMINISTRACAO | E29: 05.603.629/0001-40
A30: 1 | B30: 1 | C30: 001.02.002.02 | D30: OPERACAO | E30: 05.603.629/0001-40
A31: 1 | B31: 1 | C31: 001.02.003 | D31: CONSORCIO FTS LINHA LESTE | E31: 05.603.629/0001-40 | F31: 51.322.09177/82
A32: 1 | B32: 1 | C32: 001.02.003.01 | D32: ADMINISTRACAO | E32: 05.603.629/0001-40
A33: 1 | B33: 1 | C33: 001.02.003.02 | D33: OPERACAO | E33: 05.603.629/0001-40
A34: 1 | B34: 1 | C34: 001.02.004 | D34: DEMAIS OBRAS | E34: 05.603.629/0001-40
A35: 1 | B35: 1 | C35: 001.02.004.01 | D35: ADMINISTRACAO | E35: 05.603.629/0001-40
A36: 1 | B36: 1 | C36: 001.02.004.02 | D36: OPERACAO | E36: 05.603.629/0001-40
A37: 1 | B37: 1 | C37: 001.03 | D37: CLIENTE ECOFOR | E37: 05.603.629/0001-40
A38: 1 | B38: 1 | C38: 001.03.001 | D38: ADMINISTRATIVO ECOFOR | E38: 05.603.629/0001-40
A39: 1 | B39: 1 | C39: 001.03.001.01 | D39: ADMINISTRACAO | E39: 05.603.629/0001-40
A40: 1 | B40: 1 | C40: 001.03.001.02 | D40: MARKETING | E40: 05.603.629/0001-40
A41: 1 | B41: 1 | C41: 001.03.001.03 | D41: RECURSOS HUMANOS | E41: 05.603.629/0001-40
A42: 1 | B42: 1 | C42: 001.03.001.04 | D42: SETOR DE PESSOAL | E42: 05.603.629/0001-40
A43: 1 | B43: 1 | C43: 001.03.001.05 | D43: FINANCEIRO | E43: 05.603.629/0001-40
... A61: 1 | B61: 1 | C61: 001.03.002.08 | D61: ECOPONTO | E61: 05.603.629/0001-40
A65: 2 | B65: 1 | C65: 0 | D65: BOA EMPREENDIMENTOS | E65: 17.027.472/0001-30
A66: 2 | B66: 1 | C66: 001 | D66: BOA EMPREENDIMENTOS IMOBILIARIOS LTDA | E66: 17.027.472/0001-30
A67: 2 | B67: 1 | C67: 001.01 | D67: ADMINISTRATIVO | E67: 17.027.472/0001-30
A68: 2 | B68: 1 | C68: 001.01.01 | D68: ADMINISTRACAO | E68: 17.027.472/0001-30
A69: 2 | B69: 1 | C69: 001.02 | D69: OPERACAO | E69: 17.027.472/0001-30
A70: 2 | B70: 1 | C70: 001.02.01 | D70: OPERACIONAL | E70: 17.027.472/0001-30
A75: 3 | B75: 1 | C75: 0 | D75: PATIO CASTELAO | E75: 48.636.176/0001-60
A76: 3 | B76: 1 | C76: 001 | D76: PATIO CASTELAO EMPREENDIMENTOS LTDA | E76: 48.636.176/0001-60
A77: 3 | B77: 1 | C77: 001.01 | D77: ADMINISTRATIVO | E77: 48.636.176/0001-60
A78: 3 | B78: 1 | C78: 001.01.01 | D78: ADMINISTRACAO | E78: 48.636.176/0001-60
A79: 3 | B79: 1 | C79: 001.01.02 | D79: ALMOXARIFE | E79: 48.636.176/0001-61
A80: 3 | B80: 1 | C80: 001.02 | D80: OPERACAO | E80: 48.636.176/0001-60
A81: 3 | B81: 1 | C81: 001.02.01 | D81: MANUTENCAO | E81: 48.636.176/0001-60
A85: 4 | B85: 1 | C85: 0 | D85: ANJO ETERNO PET LTDA | E85: 11.465.561/0001-82
A86: 4 | B86: 1 | C86: 001 | D86: ANJO ETERNO PET LTDA | E86: 11.465.561/0001-82
A87: 4 | B87: 1 | C87: 001.01 | D87: ADMINISTRATIVO | E87: 11.465.561/0001-82
A88: 4 | B88: 1 | C88: 001.01.01 | D88: ADMINISTRACAO | E88: 11.465.561/0001-82
A89: 4 | B89: 1 | C89: 001.01.02 | D89: GERENCIA FINANCEIRA | E89: 11.465.561/0001-82
A90: 4 | B90: 1 | C90: 001.02 | D90: COMERCIAL | E90: 11.465.561/0001-82
... A94: 4 | B94: 1 | C94: 001.03.02 | D94: CREMATORIO | E94: 11.465.561/0001-82
A98: 5 | B98: 1 | C98: 0 | D98: ATIVA COOPERADOS LTDA | E98: 05.525.104/0001-33
A99: 5 | B99: 1 | C99: 001 | D99: ATIVA COOPERADOS LTDA | E99: 05.525.104/0001-33
A100: 5 | B100: 1 | C100: 001.01 | D100: ADMINISTRATIVO | E100: 05.525.104/0001-33
A101: 5 | B101: 1 | C101: 001.01.01 | D101: ADMINISTRACAO | E101: 05.525.104/0001-33
A102: 5 | B102: 1 | C102: 001.01.02 | D102: FINANCEIRO | E102: 05.525.104/0001-33
A103: 5 | B103: 1 | C103: 001.02 | D103: OPERACAO | E103: 05.525.104/0001-33
A104: 5 | B104: 1 | C104: 001.02.01 | D104: PATIO | E104: 05.525.104/0001-33
A107: 6 | B107: 1 | C107: 0 | D107: MC COFFEE SHOP LTDA | E107: 60.538.885/0001-09
A108: 6 | B108: 1 | C108: 001 | D108: MC COFFEE SHOP LTDA | E108: 60.538.885/0001-09
A109: 6 | B109: 1 | C109: 001.01 | D109: ADMINISTRATIVO | E109: 60.538.885/0001-09
A110: 6 | B110: 1 | C110: 001.01.01 | D110: GERENCIA | E110: 60.538.885/0001-09
A111: 6 | B111: 1 | C111: 001.02 | D111: OPERACAO | E111: 60.538.885/0001-09
A112: 6 | B112: 1 | C112: 001.02.01 | D112: FRENTE DE LOJA | E112: 60.538.885/0001-09

Sheet ZDEPARA_BANCO
A1: EMPRESA_DE | B1: CODIGO_BANCO_DE | C1: CODIGO_AGENCIA_DE | D1: NUMBANCO_DE | E1: NOME_BANCO_DE | F1: NUMAGENCIA_DE | G1: NOME_AGENCIA_DE | H1: CODIGO_BANCO_PARA | I1: CODIGO_AGENCIA_PARA | J1: DIGITO_AGENCIA_PARA
A2: 0004 | B2: 001 | C2: 5648 | D2: 001 | E2: BANCO DO BRASIL | F2: 46574 | G2: Agencia Ocara | H2: 001 | I2: 4657 | J2: 4
A3: 0004 | B3: 001 | C3: 5649 | D3: 001 | E3: BANCO DO BRASIL | F3: 22853 | G3: 2285-3 | H3: 001 | I3: 2285 | J3: 3
A4: 0004 | B4: 001 | C4: 2793 | D4: 001 | E4: BANCO DO BRASIL | F4: 27936 | G4: 2793-6 | H4: 001 | I4: 2793 | J4: 6
A5: 0004 | B5: 001 | C5: 0085 | D5: 001 | E5: BANCO DO BRASIL | F5: 0085X | G5: 0085-X | H5: 001 | I5: 0085 | J5: X
A6: 0004 | B6: 001 | C6: 3646 | D6: 001 | E6: BANCO DO BRASIL | F6: 36463 | G6: CAMBEBA | H6: 001 | I6: 3646 | J6: 3
A7: 0004 | B7: 001 | C7: 0581 | D7: 001 | E7: BANCO DO BRASIL | F7: 0852-4 | G7: CENTRO | H7: 001 | I7: 0852 | J7: 4
A8: 0004 | B8: 001 | C8: 0018 | D8: 001 | E8: BANCO DO BRASIL | F8: 32530 | G8: Agência (Fortaleza) | H8: 001 | I8: 3253 | J8: 0
A9: 0004 | B9: 001 | C9: 5624 | D9: 001 | E9: BANCO DO BRASIL | F9: 40525 | G9: SOBRAL 4052-5 | H9: 001 | I9: 4052 | J9: 5
A10: 0004 | B10: 001 | C10: 1790 | D10: 001 | E10: BANCO DO BRASIL | F10: 12920 | G10: 1292-0 | H10: 001 | I10: 1292 | J10: 0
A11: 0004 | B11: 013 | C11: 0004 | D11: 033 | E11: SANTANDE | F11: 1816 | G11: SANTANDER DEL PASEO | H11: 033 | I11: 1816
A12: 0004 | B12: 001 | C12: 5615 | D12: 001 | E12: BANCO DO BRASIL | F12: 35149 | G12: 3514-9 | H12: 001 | I12: 3514 | J12: 9
A13: 0004 | B13: 001 | C13: 5610 | D13: 001 | E13: BANCO DO BRASIL | F13: 02429 | G13: Agência 0242-9 | H13: 001 | I13: 0242 | J13: 9
A14: 0004 | B14: 001 | C14: 0094 | D14: 001 | E14: BANCO DO BRASIL | F14: 00949 | G14: CRATO | H14: 001 | I14: 0094 | J14: 9
A15: 0004 | B15: 003 | C15: 2987 | D15: 104 | E15: CEF | F15: 00048120-8 | G15: CAIXA ECONOMICA FERERAL | H15: 104 | I15: 4812
A16: 0004 | B16: 001 | C16: 4650 | D16: 001 | E16: BANCO DO BRASIL | F16: 41599 | G16: 4159-9 | H16: 001 | I16: 4159 | J16: 9
A17: 0004 | B17: 001 | C17: 5629 | D17: 001 | E17: BANCO DO BRASIL | F17: 03948 | G17: SAO GONÇCALO 0394-8 | H17: 001 | I17: 0394 | J17: 8
A18: 0004 | B18: 001 | C18: 5630 | D18: 001 | E18: BANCO DO BRASIL | F18: 12084 | G18: MANAUS 1208-4 | H18: 001 | I18: 1208 | J18: 4
A19: 0004 | B19: 009 | C19: 0004 | D19: 275 | E19: REAL | F19: 0132 | G19: FORTALEZA | H19: 275 | I19: 0132
A20: 0004 | B20: 001 | C20: 3887 | D20: 001 | E20: BANCO DO BRASIL | F20: 38873 | G20: CONJUNTO CEARA | H20: 001 | I20: 3887 | J20: 3
A21: 0005 | B21: 012 | C21: 0452 | D21: 012 | E21: BRADESCO | F21: 0452-9 | G21: 0452-9 | H21: 012 | I21: 0452 | J21: 9
A22: 0004 | B22: 001 | C22: 5623 | D22: 001 | E22: BANCO DO BRASIL | F22: 09628 | G22: PENTECOSTE 0962-8 | H22: 001 | I22: 0962 | J22: 8
A23: 0004 | B23: 001 | C23: 0011 | D23: 001 | E23: BANCO DO BRASIL | F23: 36536 | G23: Benfica (Fortaleza) | H23: 001 | I23: 3653 | J23: 6
A24: 0004 | B24: 001 | C24: 5617 | D24: 001 | E24: BANCO DO BRASIL | F24: 37311 | G24: 3731-1 | H24: 001 | I24: 3731 | J24: 1
A25: 0004 | B25: 001 | C25: 4042 | D25: 001 | E25: BANCO DO BRASIL | F25: 41599 | G25: AMONATADA | H25: 001 | I25: 4159 | J25: 9
A26: 0005 | B26: 013 | C26: 0003 | D26: 033 | E26: SANTANDE | F26: 0320 | G26: Super Conta | H26: 033 | I26: 0320
A27: 0004 | B27: 001 | C27: 0007 | D27: 001 | E27: BANCO DO BRASIL | F27: 16055 | G27: Praça do Carmo (Fortaleza) | H27: 001 | I27: 1605 | J27: 5
A28: 0004 | B28: 001 | C28: 5613 | D28: 001 | E28: BANCO DO BRASIL | F28: 42722 | G28: Agência 4272-2 | H28: 001 | I28: 4272 | J28: 2
A29: 0004 | B29: 013 | C29: 0005 | D29: 033 | E29: SANTANDE | F29: 1340 | G29: CIDADE NOVA 1340 | H29: 033 | I29: 1340
A30: 0004 | B30: 001 | C30: 0593 | D30: 001 | E30: BANCO DO BRASIL | F30: 1605-5 | G30: 1605-5 | H30: 001 | I30: 1605 | J30: 5
A31: 0004 | B31: 001 | C31: 5607 | D31: 001 | E31: BANCO DO BRASIL | F31: 42188 | G31: Agência 4218-8 | H31: 001 | I31: 4218 | J31: 8
A32: 0004 | B32: 001 | C32: 1788 | D32: 001 | E32: BANCO DO BRASIL | F32: 32964 | G32: 32964 | H32: 001 | I32: 3296 | J32: 4
A33: 0004 | B33: 001 | C33: 4041 | D33: 001 | E33: BANCO DO BRASIL | F33: 4041X | G33: CAMBEBA | H33: 001 | I33: 4041 | J33: X
A34: 0004 | B34: 001 | C34: 0013 | D34: 001 | E34: BANCO DO BRASIL | F34: 16683 | G34: Campus Universitário (Natal) | H34: 001 | I34: 1668 | J34: 3
A35: 0004 | B35: 001 | C35: 3673 | D35: 001 | E35: BANCO DO BRASIL | F35: 36730 | G35: 36730 | H35: 001 | I35: 3673 | J35: 0
A36: 0004 | B36: 001 | C36: 5657 | D36: 001 | E36: BANCO DO BRASIL | F36: 57851 | G36: 5785-1 | H36: 001 | I36: 5785 | J36: 1
A37: 0004 | B37: 001 | C37: 4053 | D37: 001 | E37: BANCO DO BRASIL | F37: 32530 | G37: 3253-0 | H37: 001 | I37: 3253 | J37: 0
A38: 0004 | B38: 001 | C38: 5669 | D38: 001 | E38: BANCO DO BRASIL | F38: 18627 | G38: Manaus 1862-7 | H38: 001 | I38: 1862 | J38: 7
A39: 0004 | B39: 001 | C39: 5627 | D39: 001 | E39: BANCO DO BRASIL | F39: 03948 | G39: SAO GONCALO 0394-8 | H39: 001 | I39: 0394 | J39: 8
A40: 0004 | B40: 001 | C40: 3473 | D40: 001 | E40: BANCO DO BRASIL | F40: 34738 | G40: PAPICU | H40: 001 | I40: 3473 | J40: 8
A41: 0004 | B41: 001 | C41: 3474 | D41: 001 | E41: BANCO DO BRASIL | F41: 34746 | G41: 34746 | H41: 001 | I41: 3474 | J41: 6
... A48: 0004 | B48: 001 | C48: 5656 | D48: 001 | E48: BANCO DO BRASIL | F48: 59269 | G48: 5926-9 | H48: 001 | I48: 5926 | J48: 9
A49: 0004 | B49: 013 | C49: 0003 | D49: 033 | E49: SANTANDE | F49: 0320 | G49: Super Conta | H49: 033 | I49: 0320
A50: 0004 | B50: 001 | C50: 5650 | D50: 001 | E50: BANCO DO BRASIL | F50: 42722 | G50: 4272-2 | H50: 001 | I50: 4272 | J50: 2
A51: 0004 | B51: 001 | C51: 5664 | D51: 001 | E51: BANCO DO BRASIL | F51: 41491 | G51: 41491 | H51: 001 | I51: 4149 | J51: 1
A52: 0004 | B52: 001 | C52: 2937 | D52: 001 | E52: BANCO DO BRASIL | F52: 29378 | G52: 29378 | H52: 001 | I52: 2937 | J52: 8
A53: 0004 | B53: 001 | C53: 5641 | D53: 001 | E53: BANCO DO BRASIL | F53: 25941 | G53: 2594-1 | H53: 001 | I53: 2594 | J53: 1
A54: 0004 | B54: 001 | C54: 4054 | D54: 001 | E54: BANCO DO BRASIL | F54: 3472X | G54: 3472-X | H54: 001 | I54: 3472 | J54: X
A55: 0004 | B55: 001 | C55: 3631 | D55: 001 | E55: BANCO DO BRASIL | F55: 11576 | G55: Sobral | H55: 001 | I55: 1157 | J55: 6
A56: 0004 | B56: 001 | C56: 0574 | D56: 001 | E56: BANCO DO BRASIL | F56: 1525-3 | G56: MANAUS | H56: 001 | I56: 1525 | J56: 3
A57: 0004 | B57: 001 | C57: 5673 | D57: 001 | E57: BANCO DO BRASIL | F57: 01023 | G57: 102-3-PVH | H57: 001 | I57: 0102 | J57: 3
A58: 0004 | B58: 001 | C58: 1780 | D58: 001 | E58: BANCO DO BRASIL | F58: 00000 | G58: PONTES VIEIRA | H58: 001 | I58: 0000 | J58: 0
A59: 0004 | B59: 001 | C59: 1799 | D59: 001 | E59: BANCO DO BRASIL | F59: 1799X | G59: 1799X | H59: 001 | I59: 1799 | J59: X
A60: 0004 | B60: 001 | C60: 5603 | D60: 001 | E60: BANCO DO BRASIL | F60: 29173 | G60: PONTES VIEIRA II | H60: 001 | I60: 2917 | J60: 3
A61: 0005 | B61: 003 | C61: 3424 | D61: 104 | E61: CEF | F61: 1958-5 | G61: AGENCIA 1958-5 | H61: 104 | I61: 1958
A62: 0004 | B62: 001 | C62: 5628 | D62: 001 | E62: BANCO DO BRASIL | F62: 28991 | G62: SAO GONCALO 2899-1 | H62: 001 | I62: 2899 | J62: 1
A63: 0004 | B63: 001 | C63: 5611 | D63: 001 | E63: BANCO DO BRASIL | F63: 00027 | G63: Agência 0002-7 | H63: 001 | I63: 0002 | J63: 7
A64: 0004 | B64: 001 | C64: 5608 | D64: 001 | E64: BANCO DO BRASIL | F64: 34797 | G64: Agência 3479-7 | H64: 001 | I64: 3479 | J64: 7
A65: 0004 | B65: 001 | C65: 5614 | D65: 001 | E65: BANCO DO BRASIL | F65: 57258 | G65: 5725-8 | H65: 001 | I65: 5725 | J65: 8
A66: 0004 | B66: 001 | C66: 5604 | D66: 001 | E66: BANCO DO BRASIL | F66: 22853 | G66: Agência 2285-3 | H66: 001 | I66: 2285 | J66: 3
A67: 0004 | B67: 001 | C67: 5634 | D67: 001 | E67: BANCO DO BRASIL | F67: 46825 | G67: 4682-5 | H67: 001 | I67: 4682 | J67: 5
A68: 0004 | B68: 001 | C68: 0567 | D68: 001 | E68: BANCO DO BRASIL | F68: 12181 | G68: 1218-1 | H68: 001 | I68: 1218 | J68: 1
A69: 0004 | B69: 001 | C69: 1786 | D69: 001 | E69: BANCO DO BRASIL | F69: 10413 | G69: 1041-3 | H69: 001 | I69: 1041 | J69: 3
A70: 0004 | B70: 001 | C70: 5616 | D70: 001 | E70: BANCO DO BRASIL | F70: 32867 | G70: 3286-7 | H70: 001 | I70: 3286 | J70: 7
A71: 0004 | B71: 001 | C71: 5643 | D71: 001 | E71: BANCO DO BRASIL | F71: 43818 | G71: 4381-8 | H71: 001 | I71: 4381 | J71: 8
A72: 0004 | B72: 001 | C72: 5638 | D72: 001 | E72: BANCO DO BRASIL | F72: 56634 | G72: 5663-4 FRECHEIRINHA | H72: 001 | I72: 5663 | J72: 4
A73: 0004 | B73: 003 | C73: 3425 | D73: 104 | E73: CEF | F73: 1548 | G73: 1548 | H73: 104 | I73: 1548
A74: 0004 | B74: 001 | C74: 3537 | D74: 001 | E74: BANCO DO BRASIL | F74: 03948 | G74: São Gonçalo | H74: 001 | I74: 0394 | J74: 8
A75: 0004 | B75: 001 | C75: 5640 | D75: 001 | E75: BANCO DO BRASIL | F75: 09423 | G75: 942-3 | H75: 001 | I75: 0942 | J75: 3
A76: 0004 | B76: 001 | C76: 3471 | D76: 001 | E76: BANCO DO BRASIL | F76: 34711 | G76: MONSENHOR TABOSA | H76: 001 | I76: 3471 | J76: 1
A77: 0004 | B77: 001 | C77: 4436 | D77: 001 | E77: BANCO DO BRASIL | F77: 44369 | G77: 4436-9 | H77: 001 | I77: 4436 | J77: 9
A78: 0004 | B78: 001 | C78: 5605 | D78: 001 | E78: BANCO DO BRASIL | F78: 33782 | G78: Agência 3378-2 | H78: 001 | I78: 3378 | J78: 2
A79: 0005 | B79: 001 | C79: 4043 | D79: 001 | E79: BANCO DO BRASIL | F79: 29068 | G79: AV.OSORIO DE PAIVA | H79: 001 | I79: 2906 | J79: 8
A80: 0004 | B80: 001 | C80: 5646 | D80: 001 | E80: BANCO DO BRASIL | F80: 50490 | G80: 50490 | H80: 001 | I80: 5049 | J80: 0
A81: 0004 | B81: 001 | C81: 0597 | D81: 001 | E81: BANCO DO BRASIL | F81: 3140-2 | G81: 3140-2 | H81: 001 | I81: 3140 | J81: 2
A82: 0004 | B82: 001 | C82: 3655 | D82: 001 | E82: BANCO DO BRASIL | F82: 36552 | G82: BARÃO DE ARACATI | H82: 001 | I82: 3655 | J82: 2
A83: 0004 | B83: 001 | C83: 5633 | D83: 001 | E83: BANCO DO BRASIL | F83: 03948 | G83: Sao Gonçalo | H83: 001 | I83: 0394 | J83: 8
A84: 0005 | B84: 001 | C84: 0002 | D84: 001 | E84: BANCO DO BRASIL | F84: 029173 | G84: PONTES VIEIRA - 2917-3 | H84: 001 | I84: 2917 | J84: 3
A85: 0004 | B85: 001 | C85: 0002 | D85: 001 | E85: BANCO DO BRASIL | F85: 029173 | G85: PONTES VIEIRA - 2917-3 | H85: 001 | I85: 2917 | J85: 3
A86: 0004 | B86: 001 | C86: 4552 | D86: 001 | E86: BANCO DO BRASIL | F86: 00001 | G86: AV. DESEMBARGADOR MOREIRA | H86: 001 | I86: 0000 | J86: 1
A87: 0004 | B87: 013 | C87: 0006 | D87: 033 | E87: SANTANDE | F87: 3508 | G87: AGENCIA 3508 | H87: 033 | I87: 3508
A88: 0004 | B88: 001 | C88: 5612 | D88: 001 | E88: BANCO DO BRASIL | F88: 42196 | G88: Agência 4219-6 | H88: 001 | I88: 4219 | J88: 6
A89: 0004 | B89: 001 | C89: 5647 | D89: 001 | E89: BANCO DO BRASIL | F89: 51101 | G89: 5110-1 | H89: 001 | I89: 5110 | J89: 1
A90: 0004 | B90: 013 | C90: 0001 | D90: 033 | E90: SANTANDE | F90: 3962 | G90: SANTANDER IGUATEMI | H90: 033 | I90: 3962
A91: 0004 | B91: 001 | C91: 5639 | D91: 001 | E91: BANCO DO BRASIL | F91: 2273X | G91: 2273-X | H91: 001 | I91: 2273 | J91: X
A92: 0004 | B92: 001 | C92: 0592 | D92: 001 | E92: BANCO DO BRASIL | F92: 06750 | G92: AGUA FRIA 1 | H92: 001 | I92: 0675 | J92: 0
A93: 0004 | B93: 001 | C93: 5632 | D93: 001 | E93: BANCO DO BRASIL | F93: 28991 | G93: sao gonçalo | H93: 001 | I93: 2899 | J93: 1
A94: 0004 | B94: 001 | C94: 4293 | D94: 001 | E94: BANCO DO BRASIL | F94: 42935 | G94: 42935 | H94: 001 | I94: 4293 | J94: 5
A95: 0004 | B95: 001 | C95: 5620 | D95: 001 | E95: BANCO DO BRASIL | F95: 11363 | G95: 1136-3 | H95: 001 | I95: 1136 | J95: 3
A96: 0004 | B96: 001 | C96: 5619 | D96: 001 | E96: BANCO DO BRASIL | F96: 1219X | G96: 1219-X | H96: 001 | I96: 1219 | J96: X
A97: 0004 | B97: 001 | C97: 5636 | D97: 001 | E97: BANCO DO BRASIL | F97: 08508 | G97: 0850-8 | H97: 001 | I97: 0850 | J97: 8
A98: 0004 | B98: 001 | C98: 5652 | D98: 001 | E98: BANCO DO BRASIL | F98: 80772 | G98: 80772 | H98: 001 | I98: 8077 | J98: 2
A99: 0004 | B99: 001 | C99: 2850 | D99: 001 | E99: BANCO DO BRASIL | F99: 28509 | G99: BEBERIBE | H99: 001 | I99: 2850 | J99: 9
A100: 0004 | B100: 001 | C100: 5645 | D100: 001 | E100: BANCO DO BRASIL | F100: 57231 | G100: 5723-1 | H100: 001 | I100: 5723 | J100: 1
A101: 0004 | B101: 001 | C101: 5662 | D101: 001 | E101: BANCO DO BRASIL | F101: 29270 | G101: 2927-0 | H101: 001 | I101: 2927 | J101: 0
A102: 0004 | B102: 001 | C102: 5631 | D102: 001 | E102: BANCO DO BRASIL | F102: 00728 | G102: Sao Gonçalo | H102: 001 | I102: 0072 | J102: 8
... A113: 0004 | B113: 001 | C113: 5665 | D113: 001 | E113: BANCO DO BRASIL | F113: 30538 | G113: 3053-8 | H113: 001 | I113: 3053 | J113: 8

Sheet ZDEPARA_SITUACAO
A1: CODIGO_DE | B1: NOME_DE | C1: CODSITUACAO_PARA | D1: CODMOTIVO_PARA | E1: CODSITUACAO_RETORNO_PARA | F1: CODMOTIVO_RETORNO_PARA
A2: 01 | B2: Férias | C2: F | D2: 03 | E2: A | F2: 04
A3: 02 | B3: Licença-maternidade | C3: E | D3: 09 | E3: A | F3: 38
A4: 03 | B4: Licença por motivo de doença | C4: P | D4: 40 | E4: A | F4: 38
A5: 04 | B5: Licença por motivo de acidente de trabalho | C5: T | D5: 91 | E5: A | F5: 38
A6: 05 | B6: Licença para prestação de serviço militar | C6: M | D6: 43 | E6: A | F6: 38
A7: 06 | B7: Licença não remunerada | C7: L | D7: 43 | E7: A | F7: 38
A8: 12 | B8: Licença em decorrencia do mesmo acidente de trabalho | C8: T | D8: 91 | E8: A | F8: 38
A9: 13 | B9: Licença em decorrencia da mesma doença (até 60 dias após) | C9: P | D9: 43 | E9: A | F9: 38
A10: 14 | B10: Licença por motivo de doença inferior a 15 dias | C10: R | D10: 39 | E10: A | F10: 38
A11: 15 | B11: Licença por motivo de acidente de trabalho inf. a 15 dias | C11: R | D11: 41 | E11: A | F11: 38
A12: 16 | B12: Aponsentadoria por Invalidez | C12: I | D12: 43
A13: 17 | B13: Licença Paternidade | C13: Y | D13: 33 | E13: A | F13: 43
A14: 18 | B14: Licença para Casamento | C14: R | D14: 43 | E14: A | F14: 38
A15: 19 | B15: Licença por doença relacionada ao trabalho | C15: O | D15: 37 | E15: A | F15: 38
A16: 20 | B16: Licença por motivo de doença até 15 dias | C16: R | D16: 39 | E16: A | F16: 38
A17: 21 | B17: Licença por acidente de trabalho até 15 dias | C17: R | D17: 41 | E17: A | F17: 38
A18: 22 | B18: Suspensão | C18: U | D18: 30 | E18: A | F18: 38
A19: 23 | B19: Suspensão temporária do contrato de trabalho MP 936/2020 | C19: U | D19: 32 | E19: A | F19: 38
A20: 24 | B20: Suspensão do Contrato de Trabalho - Carcere | C20: Q | D20: 28 | E20: A | F20: 38
B22: A | C22: Ativo | E22: 01 | F22: Admissão
B23: C | C23: Contrato de Trabalho Suspenso | E23: 02 | F23: Aposentadoria p/invalidez acidente de trabalho
B24: D | C24: Demitido | E24: 03 | F24: Afastamento p/Férias
B25: E | C25: Licença Mater. | E25: 04 | F25: Retorno das Férias
B26: F | C26: Férias | E26: 06 | F26: Transferência entre Coligadas
B27: G | C27: Recesso Remunerado de Estagio | E27: 07 | F27: Transferência entre Filiais
B28: I | C28: Apos. por Incapacidade Permanente | E28: 08 | F28: Demissão
B29: K | C29: Cessão / Requisição | E29: 09 | F29: Licença maternidade
B30: L | C30: Licença s/venc | E30: 10 | F30: Licença maternidade p/aborto não criminoso
B31: M | C31: Serv.Militar | E31: 11 | F31: Licença Remunerada
B32: N | C32: Mandato Sindical Ônus do Empregador | E32: 12 | F32: Licença maternidade por adoção
B33: O | C33: Doença Ocupacional | E33: 13 | F33: Admissão Alta Estação/Safra
... B44: Z | C44: Admissão prox.mês | E44: 38 | F44: Retorno de afastamento
E45: 39 | F45: Afast temp por Doença Igual ou Inferior a 15 dias
E46: 40 | F46: Afast temp por Doença Superior a 15 dias
E47: 41 | F47: Afast temp por Ac Trab igual ou inferior a 15 dias
E48: 42 | F48: Afast temp por Ac Trab Superior a 15 dias
E49: 43 | F49: Outros motivos de afastamento temporário
E50: 91 | F50: Espécie B91 Auxílio-acidente p/acidente trabalho
E51: 99 | F51: Implantação ERP
E52: CV | F52: Afastamento por COVID-19

Sheet ZDEPARA_HORARIOS
A1: EMPRESA_DE | B1: CODIGO_DE | C1: NOME_DE | D1: COLIGADA_PARA | E1: CODIGO_PARA
A2: 0004 | B2: 000001 | C2: APRENDIZ 07:30 - 11:30 | D2: 1 | E2: 00001
A3: 0004 | B3: 000002 | C3: APRENDIZ 08:01 - 12:01 | D3: 1 | E3: 00001
A4: 0004 | B4: 000003 | C4: ADM 08:00 12:00 - 13:30 18:15 | D4: 1 | E4: 00001
A5: 0004 | B5: 000004 | C5: APRENDIZ 13:30 - 17:30 | D5: 1 | E5: 00001
A6: 0004 | B6: 000005 | C6: CIV 07:00 11:30 - 12:30 17:00 | D6: 1 | E6: 00001
A7: 0004 | B7: 000006 | C7: ADM 07:00 12:00 - 13:30 17:15 | D7: 1 | E7: 00001
A8: 0004 | B8: 000007 | C8: ADM 08:00 12:00 - 13:30 17:30 | D8: 1 | E8: 00001
A9: 0004 | B9: 000008 | C9: OPER 07:00 12:00 - 13:30 17:15 | D9: 1 | E9: 00001
A10: 0004 | B10: 000009 | C10: N 2 16:00 21:00 - 22:00 01:50 | D10: 1 | E10: 00001
A11: 0004 | B11: 000010 | C11: 01) SER I | D11: 1 | E11: 00001
A12: 0004 | B12: 000011 | C12: 02) SER II | D12: 1 | E12: 00001
... A938: 0022 | B938: 000187 | C938: Jornada de trabalho 000187 - 07:00 as 19:00hs | D938: 6 | E938: 00001

Sheet ZDEPARA_PERIODO_FOLHA
A1: CODIGO_PERIODO_DE | B1: TIPO_FOLHA_DE | C1: PREFIXO_ESOCIAL | D1: NROPERIODO_PARA
A2: 1 | B2: Adiantamento de Folha | C2: M | D2: 1
A3: 2 | B3: Folha | C3: M | D3: 2
A4: 3 | B4: Complemento de Folha | C4: M | D4: 3
A5: 4 | B5: Férias | C5: F | D5: 4
A6: 5 | B6: Férias Coletivas | C6: F | D6: 5
A7: 6 | B7: Complemento de Férias | C7: F | D7: 6
A8: 7 | B8: Adiantamento de 13º Salário | C8: D | D8: 7
A9: 8 | B9: 13º Salário | C9: D | D9: 8
A10: 9 | B10: Complemento de 13º Salário | C10: D | D10: 9
A11: 10 | B11: Rescisão | C11: R | D11: 10
A12: 11 | B12: Complemento de Rescisão | C12: R | D12: 11
... A21: 20 | B21: Complemento de Férias Coletivas | C21: F | D21: 20

Sheet Layout Eventos
A1: Código Identificador do Evento | B1: Descrição do Evento | C1: Totalizador do Evento | D1: Indicador de Estado do Evento | E1: Indicativo de Composição de Comissão | F1: Provento/Desconto | G1: Valor/Hora/Dia/Referência | H1: Porcentagem de Incidência | I1: Código de Cálculo | J1: Prioridade do Evento | K1: Código da Fórmula de Valor | L1: Código da Fórmula de Hora | M1: Código da Fórmula de Referência | N1: Código da Fórmula de Crédito | O1: Incidência de Inss | P1: Incidência de Irrf | Q1: Incidência de Fgts | R1: Incidência de Rais | S1: Incidência no Informe de Rendimentos | T1: Incidência do Dsr | U1: Incidência em Vale-Transporte | V1: Incidência de Irrf nas Férias | W1: Incidência no Terço de Férias | X1: Incidência em Salário-Família | Y1: Incidência de Inss no 13. Salário | Z1: Incidência de Irrf no 13. Salário | AA1: Incremento de Acumuladores | AB1: Incidência de Salário | AC1: Prop. de Acordo com a Admissão | AD1: Proporcionalizar de Acordo com a Licença | AE1: Proporcionalizar de Acordo com as Férias | AF1: Dedutível de Irrf | AG1: Estorna Somente em Irrf de Férias | AH1: Indicativo de Est. de Base de Sal. Fam. | AI1: Indicativo de Est da Base de Vale-Transp | AJ1: Indicativo de Est.De Inss no 13. Sal. | AK1: Grupo Aas | AL1: Indicativo de Evento a Lançar | AM1: Número da Conta para Crédito | AN1: Número da Conta para Débito | AO1: Número do Histórico Padrão | AP1: Complemento do Histórico | AQ1: No Conta Gerencial para Crédito | AR1: No Conta Gerencial para Débito | AS1: Evento de Diferença de Salário | AT1: Código do Rateio que o Evento Segue | AU1: Sal.Composto Base de Calc. do Evento | AV1: Se o Evento Será Descont.No Mês Seguinte | AW1: Segue Rateio de Tomador de Serviço | AX1: Indic. de Evento para Pag. Obrigatório | AY1: Existe Intgr Contábil Conta Crédito | AZ1: Existe Intgr Contábil Conta Dédito | BA1: Existe Intgr Contábil Conta Ger Crédito | BB1: Existe Intgr Contábil Conta Ger Dédito | BC1: Existe Intgr Func Contab Conta Crédito | BD1: Existe Intgr Func Contab Conta Dédito | BE1: Existe Intgr Func Ger Conta Crédito | BF1: Existe Intgr Func Ger Conta Débito | BG1: Indicativo para Contab. Parcial | BH1: Evento Incide em Adic. Substituição | BI1: Indicativo de Est. da Base de Fgts 13O. | BJ1: Indicativo de Est. da Base de Irrf 13O. | BK1: Evento de Insuficiência de Saldos | BL1: Evento incide em pensão | BM1: Evento incide em pensão de férias | BN1: Evento incide em pensão de 13º salário | BO1: Evento incide em pensão de part. Lucros | BP1: Fórmula para compor Compl. Histórico | BQ1: Período de cálculo do rateio de eventos | BR1: Estorna FGTS | BS1: Estorna INSS | BT1: Estorna IRRF | BU1: Incide FGTS 13 | BV1: Proporcionalizar de acordo com demissão. | BW1: Exibir Evento na Entrada de Mov. via Web | BX1: Código do centro de custo do evento | BY1: Codigo de rubrica | BZ1: Conteúdo do memo (começa com /@ e termina com @/) | CA1: Indicativo de Evento Inativo | CB1: Indicativo de Estorno da Base de Cálculo | CC1: Indicativo de Estorno da Base de Férias | CD1: Identificador do memo | CE1: Segue rateio de salário composto | CF1: Conta Reversão | CG1: Fórmula para evento relacionado. | CH1: Remunerações Quadro de Pessoal | CI1: Ordem cálculo dentro de uma prioridade | CJ1: Evento dedutível em IRRF de 13o | CK1: Evento dedutível em IRRF de férias | CL1: Segue rateio do movimento de ensino | CM1: Natureza da rubrica | CN1: Incidência de INSS suspensa em decorrência de decisão judicial (campo descontinuado e substituido para o campo 136 INCINSSSUSPENSAO) | CO1: Incidência de IRRF suspensa em decorrência de decisão judicial (campo descontinuado e substituido para o campo 137 INCIRRFSUSPENSAO) | CP1: Incidência de FGTS suspensa em decorrência de decisão judicial (Valores válidos : 1, 2, 3) | CQ1: Número do Processo Administrativo/Judicial | CR1: Código Correspondente ao Tipo de Processo (A - Administrativo, J - Judicial) | CS1: Extensão da Decisão/Sentença | CT1: Número do Processo Administrativo/Judicial | CU1: Código Correspondente ao Tipo de Processo (A - Administrativo, J - Judicial) | CV1: Número do Processo Administrativo/Judicial | CW1: Código Correspondente ao Tipo de Processo (A - Administrativo, J - Judicial) | CX1: Incidência de Contribuição Sindical Suspensa | CY1: Número do Processo Administrativo/Judicial | CZ1: Código Correspondente ao Tipo de Processo (A - Administrativo, J - Judicial) | DA1: Incidência de Salário Maternidade Suspensa | DB1: Número do Processo Administrativo/Judicial | DC1: Código Correspondente ao Tipo de Processo (A - Administrativo, J - Judicial) | DD1: Incide no Custo do funcionário | DE1: Identificador do Item Contábil | DF1: Identificador da Classe de Valor | DG1: Tipo de Benefício PPE | DH1: Tipo de Desconto PPE | DI1: Incidência de PIS | DJ1: Estorna PIS | DK1: Compõe Remuneração Base de Professor | DL1: Rendimento não tributável em função de acordos internacionais de bitributação | DM1: Não é base de cálculo em função de acordos internacionais de previdência social | DN1: Incidência de INSS 13º suspensa em decorrência de decisão judicial (campo descontinuado e substituido para o campo 136 INCINSSSUSPENSAO) | DO1: Incidência de IRRF 13º suspensa em decorrência de decisão judicial (campo descontinuado e substituido para o campo 137 INCIRRFSUSPENSAO) | DP1: Incidência de FGTS 13º suspensa em decorrência de decisão judicial | DQ1: Incidência de IRRF Férias suspensa em decorrência de decisão judicial (campo descontinuado e substituido para o campo 137 INCIRRFSUSPENSAO) | DR1: Incidência de IRRF PLR suspensa em decorrência de decisão judicial (campo descontinuado e substituido para o campo 137 INCIRRFSUSPENSAO) | DS1: Incidência de INSS Sal.Matern. suspensa em decorrência de decisão judicial (campo descontinuado e substituido para o campo 136 INCINSSSUSPENSAO) | DT1: Incidência de INSS Sal.Mater.13º suspensa em decorrência de decisão judicial (campo descontinuado e substituido para o campo 136 INCINSSSUSPENSAO) | DU1: Incidência de Contribuição Sindical | DV1: Forçar incidência de IRRF | DW1: Incidência de IRRF Forçada | DX1: Isento de IRRF | DY1: Incidência IRRF Isenção | DZ1: Não calcula diferença para este evento | EA1: Incidência de Suspensão para Contribuição Previdenciária (Aba Proventos) | EB1: Evento de Diferença de Salário Negativa | EC1: Incidência de INSS exclusiva do empregador (Aba Proventos) | ED1: Incidência de INSS exclusiva do segurado - 13º salário | EE1: Incidência de INSS exclusiva do empregador (Aba Descontos) | EF1: Incidência de INSS suspensa em decorrência de decisão judicial (Valores válidos: 91, 92, 93, 94) | EG1: Incidência de IRRF suspensa em decorrência de decisão judicial(Valores válidos: Conforme tabela 21 do eSocial independente do layout do eSocial) | EH1: Compõe o teto remuneratório específico (art. 37, XI, da CF/1988) | EI1: Incidência de Suspensão para Contribuição Previvenciária (Aba Descontos) | EJ1: Incidência de INSS décimo terceiro exclusiva do empregador (Aba Proventos) | EK1: Incidência de INSS décimo terceiro exclusiva do empregador (Aba Descontos) | EL1: Incidência para as contribuições do Regime Próprio de Previdência Social - RPPS/regime militar (Aba Proventos) | EM1: Incidência para as contribuições do Regime Próprio de Previdência Social - RPPS/regime militar (Aba Descontos) | EN1: Tipo de Previdência Complementar | EO1: Incidência PIS/PASEP
A2: 1 | B2: 2 | C2: 3 | D2: 4 | E2: 5 | F2: 6 | G2: 7 | H2: 8 | I2: 9 | J2: 10 | K2: 11 | L2: 12 | M2: 13 | N2: 14 | O2: 15 | P2: 16 | Q2: 17 | R2: 18 | S2: 19 | T2: 20 | U2: 21 | V2: 22 | W2: 23 | X2: 24 | Y2: 25 | Z2: 26 | AA2: 27 | AB2: 28 | AC2: 29 | AD2: 30 | AE2: 31 | AF2: 32 | AG2: 33 | AH2: 34 | AI2: 35 | AJ2: 36 | AK2: 37 | AL2: 38 | AM2: 39 | AN2: 40 | AO2: 41 | AP2: 42 | AQ2: 43 | AR2: 44 | AS2: 45 | AT2: 46 | AU2: 47 | AV2: 48 | AW2: 49 | AX2: 50 | AY2: 51 | AZ2: 52 | BA2: 53 | BB2: 54 | BC2: 55 | BD2: 56 | BE2: 57 | BF2: 58 | BG2: 59 | BH2: 60 | BI2: 61 | BJ2: 62 | BK2: 63 | BL2: 64 | BM2: 65 | BN2: 66 | BO2: 67 | BP2: 68 | BQ2: 69 | BR2: 70 | BS2: 71 | BT2: 72 | BU2: 73 | BV2: 74 | BW2: 75 | BX2: 76 | BY2: 77 | BZ2: 78 | CA2: 79 | CB2: 80 | CC2: 81 | CD2: 82 | CE2: 83 | CF2: 84 | CG2: 85 | CH2: 86 | CI2: 87 | CJ2: 88 | CK2: 89 | CL2: 90 | CM2: 91 | CN2: 92 | CO2: 93 | CP2: 94 | CQ2: 95 | CR2: 96 | CS2: 97 | CT2: 98 | CU2: 99 | CV2: 100 | CW2: 101 | CX2: 102 | CY2: 103 | CZ2: 104 | DA2: 105 | DB2: 106 | DC2: 107 | DD2: 108 | DE2: 109 | DF2: 110 | DG2: 111 | DH2: 112 | DI2: 113 | DJ2: 114 | DK2: 115 | DL2: 116 | DM2: 117 | DN2: 118 | DO2: 119 | DP2: 120 | DQ2: 121 | DR2: 122 | DS2: 123 | DT2: 124 | DU2: 125 | DV2: 126 | DW2: 127 | DX2: 128 | DY2: 129 | DZ2: 130 | EA2: 131 | EB2: 132 | EC2: 133 | ED2: 134 | EE2: 135 | EF2: 136 | EG2: 137 | EH2: 138 | EI2: 139 | EJ2: 140 | EK2: 141 | EL2: 142 | EM2: 143 | EN2: 144 | EO2: 145
A3: PEVENTO.CODIGO | B3: PEVENTO.DESCRICAO | C3: PEVENTO.TOTALIZADOR | D3: PEVENTO.CHAVE | E3: PEVENTO.COMPOECOMISSAO | F3: PEVENTO.PROVDESCBASE | G3: PEVENTO.VALHORDIAREF | H3: PEVENTO.PORCINCID | I3: PEVENTO.CODIGOCALCULO | J3: PEVENTO.PRIORIDADE | K3: PEVENTO.FORMULAVALOR | L3: PEVENTO.FORMULAHORA | M3: PEVENTO.FORMULAREF | N3: PEVENTO.FORMULACRITICA | O3: PEVENTO.INCINSS | P3: PEVENTO.INCIRRF | Q3: PEVENTO.INCFGTS | R3: PEVENTO.INCRAIS | S3: PEVENTO.INCINFREND | T3: PEVENTO.INCDSR | U3: PEVENTO.INCVALETRANSP | V3: PEVENTO.INCIRRFFERIAS | W3: PEVENTO.INCTERCOFERIAS | X3: PEVENTO.INCSALFAMILIA | Y3: PEVENTO.INCINSS13 | Z3: PEVENTO.INCIRRF13 | AA3: PEVENTO.INCACUMULADOR | AB3: PEVENTO.INCSALARIO | AC3: PEVENTO.PROPORCADMISSAO | AD3: PEVENTO.PROPORCLICENCA | AE3: PEVENTO.PROPORCFERIAS | AF3: PEVENTO.DEDUTIVELIRRF | AG3: PEVENTO.ESTIRRFFERIAS | AH3: PEVENTO.ESTCALCSALFAM | AI3: PEVENTO.ESTCALCVALETR | AJ3: PEVENTO.ESTINSS13 | AK3: PEVENTO.GRUPOAAS | AL3: PEVENTO.EVTALANCAR | AM3: PEVENTO.CONTACREDITO | AN3: PEVENTO.CONTADEBITO | AO3: PEVENTO.NROHISTPADRAO | AP3: PEVENTO.COMPLHISTORICO | AQ3: PEVENTO.CGCREDITO | AR3: PEVENTO.CGDEBITO | AS3: PEVENTO.CODEVENTODIF | AT3: PEVENTO.CODRATEIO | AU3: PEVENTO.BASESALCOMPOSTO | AV3: PEVENTO.DESCONTOPERDOADO | AW3: PEVENTO.PROPPORTOMADOR | AX3: PEVENTO.PAGOBRIGATORIO | AY3: PEVENTO.TEMINTCONTCC | AZ3: PEVENTO.TEMINTCONTCD | BA3: PEVENTO.TEMINTCONTGC | BB3: PEVENTO.TEMINTCONTGD | BC3: PEVENTO.TEMINTFUNCCC | BD3: PEVENTO.TEMINTFUNCCD | BE3: PEVENTO.TEMINTFUNCGC | BF3: PEVENTO.TEMINTFUNCGD | BG3: PEVENTO.CONTPARCIAL | BH3: PEVENTO.INCSUBSTITUICAO | BI3: PEVENTO.ESTFGTS13 | BJ3: PEVENTO.ESTIRRF13 | BK3: PEVENTO.CODEVENTOINSUF | BL3: PEVENTO.INCPENSAO | BM3: PEVENTO.INCPENSAOFERIAS | BN3: PEVENTO.INCPENSAO13SAL | BO3: PEVENTO.INCPENSAOPARTICIP | BP3: PEVENTO.FORMCOMPLHIST | BQ3: PEVENTO.PERCALCRATEIO | BR3: PEVENTO.ESTFGTS | BS3: PEVENTO.ESTINSS | BT3: PEVENTO.ESTIRRF | BU3: PEVENTO.INCFGTS13 | BV3: PEVENTO.PROPORCDEMISSAO | BW3: PEVENTO.EVENTOEXIBIDOENTRADADADOSWEB | BX3: PEVENTO.CCUSTO | BY3: PEVENTO.CODRUBRICA | BZ3: PMEMO.VALMEMO | CA3: PEVENTO.INATIVO | CB3: PEVENTO.ESTCALCULO | CC3: PEVENTO.ESTCALCFERIAS | CD3: PEVENTO.IDANOTACAO | CE3: PEVENTO.SEGUERATEIOSALCMP | CF3: PEVENTO.CONTAREVERSAO | CG3: PEVENTO.FORMULAEVTRELAC | CH3: PEVENTO.QUADROREM | CI3: PEVENTO.ORDEMCALCULO | CJ3: PEVENTO.DEDUTIVELIRRF13 | CK3: PEVENTO.DEDUTIVELIRRFFERIAS | CL3: PEVENTO.SEGUERATEIOMOVENSINO | EQ3: PARA IMPORTAR
A4: 0076 | G4: V | EQ4: =TEXTJOIN(";",FALSE,A4:EO4) -> 0076;;;;;;V;;;;;;;;;;;;;;;;;;;;;;;;;;;;;;;;;;;;;;;;;;;;;;;;;;;;;;;;;;;;;;;;;;;;;;;;;;;;;;;;;;;;;;;;;;;;;;;;;;;;;;;;;;;;;;;;;;;;;;;;;;;;;;;;;;;;;;;;;;
